Workbook

Sheet Data Order
A1: / | B1: No | C1: ID | D1: Tanggal | E1: Closing | F1: Nama | G1: Nama Usaha | H1: Jenis Usaha | I1: No Whatsapp Bisnis | J1: Deskripsi Produk Jasa | K1: Lokasi | L1: Usia | M1: Jenis Kelamin | N1: Durasi | O1: Mulai | P1: Selesai | Q1: Catatan | R1: ChatId | S1: Video Selesai | T1: Total Bayar | U1: CS | V1: System Date | W1: Nama Singkat | X1: Campaign Name | Y1: AccountId | Z1: Fanspage | AA1: Link Whatsapp | AB1: KampanyeId | AC1: LimitBudget | AD1: Advertiser | AE1: Kategori | AF1: Tanggal Up | AG1: Status Pembayaran
A2: Baru | B2: 1 | C2: ORD-1 | D2: 45779 | E2: 45792 | F2: Dummy | G2: Dummy | H2: Dummy | I2: 085777110340 | J2: Dummy | K2: Dummy | L2: 17-50 | M2: perempuan | N2: 0 | R2: -4633975755 | T2: 0 | V2: {=E2:E1726} -> 45792 | W2: =IFERROR(__xludf.DUMMYFUNCTION("ARRAYFORMULA(IF(G2:G1726="""", """", IFERROR(REGEXEXTRACT(G2:G1726, ""^(\S+\s+\S+)""), G2:G1726) )) "),"Dummy") -> Dummy | X2: {=IF(W2:W1726="", "", "ON-" & W2:W1726 & "-" & TEXT(V2:V1726, "DDMMYYYY") & "+" & N2:N1726 & "-" & I2:I1726)} -> ON-Dummy-15052025+0-085777110340
A3: Iklan Tidak Aktif | B3: 2 | C3: ORD-2 | D3: 45795 | E3: 45795 | F3: ni luh sukasih | G3: LK spa n beauty | H3: SPA | I3: 6282341426767 | J3: profesional family Spa di Denpasar | K3: Bali | L3: 21 sampai max | M3: laki laki dan perempuan | N3: 14 | R3: -4633975755 | T3: 500000 | U3: Devi | V3: 45795 | W3: =IFERROR(__xludf.DUMMYFUNCTION("""COMPUTED_VALUE"""),"LK spa") -> LK spa | X3: ON-LK spa-18052025+14-6282341426767 | Y3: R11-759724529202804 | Z3: Promo UMKM Bersama-R10-569094022964012 | AA3: {="https://wa.me/" & I3:I1726} -> https://wa.me/6282341426767
A4: Perpanjang | B4: 3 | C4: ORD-3 | D4: 45798 | E4: 45796 | F4: Veronika Da Costa | G4: Verrocosta | H4: Kosmetik | I4: 61459676831 | K4: Bebonuk | L4: 17 th ke atas | M4: laki-laki dan perempuan | N4: 10 | O4: 45850 | P4: 45859 | R4: -4633975755 | T4: 375000 | U4: Isna | V4: 45796 | W4: =IFERROR(__xludf.DUMMYFUNCTION("""COMPUTED_VALUE"""),"Verrocosta") -> Verrocosta | X4: ON-Verrocosta-19052025+10-61459676831 | Y4: R10-174904221976312 | Z4: Promo UMKM Bersama-R10-569094022964012 | AA4: https://wa.me/61459676831 | AB4: 120225346217950694
A5: Iklan Tidak Aktif | B5: 4 | C5: ORD-4 | D5: 45799 | E5: 45798 | F5: Karyatukang87 | G5: Karyatukang87 | H5: Furniture Interior | I5: 628872305953 | K5: semarang dan jawa tengah | L5: 21-65 | M5: semua jenis | N5: 5 | R5: -4633975755 | T5: 197000 | U5: Devi | V5: 45798 | W5: =IFERROR(__xludf.DUMMYFUNCTION("""COMPUTED_VALUE"""),"Karyatukang87") -> Karyatukang87 | X5: ON-Karyatukang87-21052025+5-628872305953 | AA5: https://wa.me/628872305953
A6: Iklan Tidak Aktif | B6: 5 | C6: ORD-5 | D6: 45799 | E6: 45797 | F6: Ni Luh Suparwati | G6: Glam Beauty Salon & Spa | H6: Salon Kecantikan | I6: 67076472864 | K6: Seputaran Bungkulan Kubutambahan, Air Sanih, Sampai Dengan Ponjok Batu Dan Seputaran Buleleng Singaraja Bali | L6: Semua Usia | M6: Laki-laki & perempuan | N6: 10 | R6: -4633975755 | T6: 375000 | U6: Isna | V6: 45797 | W6: =IFERROR(__xludf.DUMMYFUNCTION("""COMPUTED_VALUE"""),"Glam Beauty") -> Glam Beauty | X6: ON-Glam Beauty-20052025+10-67076472864 | AA6: https://wa.me/67076472864
A7: Iklan Tidak Aktif | B7: 6 | C7: ORD-6 | D7: 45799 | E7: 45798 | F7: Iwan | G7: Iwan Audio | H7: Audio Mobil Eropa | I7: 6285711307707 | K7: seluruh indonesia | L7: 25 th ke atas | M7: laki-laki dan perempuan | N7: 5 | R7: -4633975755 | T7: 197000 | U7: Isna | V7: 45798 | W7: =IFERROR(__xludf.DUMMYFUNCTION("""COMPUTED_VALUE"""),"Iwan Audio") -> Iwan Audio | X7: ON-Iwan Audio-21052025+5-6285711307707 | AA7: https://wa.me/6285711307707
A8: Iklan Tidak Aktif | B8: 7 | C8: ORD-7 | D8: 45802.75 | E8: 45802.75 | F8: Vita | G8: Seblak Prasmanan Vita | H8: Seblak Prasmanan | I8: 6285270469663 | K8: lampahan.lorong koramil bener meriah aceh | L8: bebas | M8: semua jenis | N8: 0 | R8: -4633975755 | T8: 50000 | U8: Isna | V8: 45802.75 | W8: =IFERROR(__xludf.DUMMYFUNCTION("""COMPUTED_VALUE"""),"Seblak Prasmanan") -> Seblak Prasmanan | X8: ON-Seblak Prasmanan-25052025+0-6285270469663 | AA8: https://wa.me/6285270469663
A9: Iklan Tidak Aktif | B9: 9 | C9: ORD-9 | D9: 45802.755 | E9: 45801 | F9: Nur Musvita Ayu | G9: AR Salon | H9: Salon | I9: 6285757607630 | K9: Makassar, Gowa, Maros | L9: 18 th ke atas | M9: perempuan | N9: 5 | R9: -4633975755 | T9: 197000 | U9: Isna | V9: 45801 | W9: =IFERROR(__xludf.DUMMYFUNCTION("""COMPUTED_VALUE"""),"AR Salon") -> AR Salon | X9: ON-AR Salon-24052025+5-6285757607630 | AA9: https://wa.me/6285757607630
A10: Iklan Tidak Aktif | B10: 10 | C10: ORD-10 | D10: 45802.765 | E10: 45801 | F10: Winda nainggolan | G10: Winda Tebus emas | H10: Tebus emas | I10: 62882015054720 | K10: Medan dan prapat | M10: Perempuan | N10: 5 | R10: -4633975755 | T10: 197000 | U10: Devi | V10: 45801 | W10: =IFERROR(__xludf.DUMMYFUNCTION("""COMPUTED_VALUE"""),"Winda Tebus") -> Winda Tebus | X10: ON-Winda Tebus-24052025+5-62882015054720 | AA10: https://wa.me/62882015054720
A11: Iklan Tidak Aktif | B11: 11 | C11: ORD-11 | D11: 45802.845 | E11: 45802.845 | F11: Juni meika | G11: zL beauty homecare | H11: salon perawatan | I11: 6281549409606 | K11: smarinda kota | L11: Semua usia | M11: wanita dan laki2 | N11: 7 | R11: -4633975755 | T11: 297000 | U11: Yuni | V11: 45802.845 | W11: =IFERROR(__xludf.DUMMYFUNCTION("""COMPUTED_VALUE"""),"zL beauty") -> zL beauty | X11: ON-zL beauty-25052025+7-6281549409606 | AA11: https://wa.me/6281549409606
A12: Iklan Tidak Aktif | B12: 12 | C12: ORD-12 | D12: 45803.851 | E12: 45802.845 | F12: ramli | G12: Eny Laundry | H12: Laundry karpet & Pakaian | I12: 6283129638348 | J12: laundry karpet, pakaian,sofa,boneka.profesional murah berkualitas, dan bergaransi (paling diutamakan karpet) | K12: lombok tengah | L12: 25ke atas | M12: perempuan | N12: 5 | R12: -4633975755 | T12: 197000 | U12: Yuni | V12: 45802.845 | W12: =IFERROR(__xludf.DUMMYFUNCTION("""COMPUTED_VALUE"""),"Eny Laundry") -> Eny Laundry | X12: ON-Eny Laundry-25052025+5-6283129638348 | AA12: https://wa.me/6283129638348
A13: Iklan Tidak Aktif | B13: 13 | C13: ORD-13 | D13: 45805.229 | E13: 45803 | F13: Adi | G13: AJP ADI | H13: PLAFON | I13: 6283188945188 | K13: Watukumpul Pemalang Jawa Tengah | L13: 20-65 | M13: laki-laki & perempuan | N13: 5 | R13: -4633975755 | T13: 197000 | U13: Isna | V13: 45803 | W13: =IFERROR(__xludf.DUMMYFUNCTION("""COMPUTED_VALUE"""),"AJP ADI") -> AJP ADI | X13: ON-AJP ADI-26052025+5-6283188945188 | AA13: https://wa.me/6283188945188
A14: Iklan Tidak Aktif | B14: 14 | C14: ORD-14 | D14: 45805.232 | E14: 45804 | F14: Yara | G14: M&Y mahkota salon & yara wedding | H14: wedding dan salon kecantikan | J14: wo wedding organizer juga salon kecantikan | K14: kalimantan selatan, kalimantan tengah, kalimantan timur | L14: 15-60 | M14: perempuan | N14: 5 | R14: -4633975755 | T14: 197000 | U14: Isna | V14: 45804 | W14: =IFERROR(__xludf.DUMMYFUNCTION("""COMPUTED_VALUE"""),"M&Y mahkota") -> M&Y mahkota | X14: ON-M&Y mahkota-27052025+5- | AA14: https://wa.me/
A15: Iklan Tidak Aktif | B15: 15 | C15: ORD-15 | D15: 45806.487 | E15: 45804 | F15: Mira Cantika | G15: Mira Cantika Makeup | H15: Makeup pengantin (MUA) | I15: 6285758792669 | K15: Tebo , Bungo, Sarolangun, Jambi | L15: 18th ke atas | M15: perempuan | N15: 5 | R15: -4633975755 | T15: 197000 | U15: Devi | V15: 45804 | W15: =IFERROR(__xludf.DUMMYFUNCTION("""COMPUTED_VALUE"""),"Mira Cantika") -> Mira Cantika | X15: ON-Mira Cantika-27052025+5-6285758792669 | AA15: https://wa.me/6285758792669
A16: Iklan Tidak Aktif | B16: 16 | C16: ORD-16 | D16: 45806.492 | E16: 45805 | F16: Lina Nalurita | G16: Khairan Wedding | H16: Salon perawatan rambut,wajah dan MUA | I16: 6285220903499 | K16: daerah Sumedang dan sekitarnya, Bandung | L16: SMP sd 60 thnan | M16: khusus wanita salonnya. | N16: 5 | R16: -4633975755 | T16: 197000 | U16: Devi | V16: 45805 | W16: =IFERROR(__xludf.DUMMYFUNCTION("""COMPUTED_VALUE"""),"Khairan Wedding") -> Khairan Wedding | X16: ON-Khairan Wedding-28052025+5-6285220903499 | AA16: https://wa.me/6285220903499
A17: Iklan Tidak Aktif | B17: 17 | C17: ORD-17 | D17: 45806.494 | E17: 45805 | F17: Neng Ay salon | G17: Neng Ay salon | H17: Salon | I17: 6282290353409 | K17: kota sorong dan manokwari | M17: khusus wanita | N17: 10 | R17: -4633975755 | T17: 375000 | U17: Devi | V17: 45805 | W17: =IFERROR(__xludf.DUMMYFUNCTION("""COMPUTED_VALUE"""),"Neng Ay") -> Neng Ay | X17: ON-Neng Ay-28052025+10-6282290353409 | AA17: https://wa.me/6282290353409
A18: Iklan Tidak Aktif | B18: 18 | C18: ORD-18 | D18: 45806.498 | E18: 45805 | F18: ISAL | G18: ISAL SALON | H18: PERAWATAN RAMBUT | I18: 6285240684331 | J18: Diskon 20% untuk Smoting dan warna rambut | K18: kendari | L18: semua usia | M18: laki-laki dan perempuan | N18: 5 | R18: -4633975755 | T18: 197000 | U18: Devi | V18: 45805 | W18: =IFERROR(__xludf.DUMMYFUNCTION("""COMPUTED_VALUE"""),"ISAL SALON") -> ISAL SALON | X18: ON-ISAL SALON-28052025+5-6285240684331 | AA18: https://wa.me/6285240684331
A19: Iklan Tidak Aktif | B19: 19 | C19: ORD-19 | D19: 45807.359 | E19: 45805 | F19: Devi Andesta | G19: Devy Kikim | H19: Salon & Wedding | I19: 6282136666049 | J19: semua keahlian salon sudah bersertifikasi BNSP sudah bersertifikasi mua level 3 bnsp | K19: jabodetabek | L19: semua usia | M19: pria & wanita | N19: 5 | R19: -4633975755 | T19: 197000 | U19: Isna | V19: 45805 | W19: =IFERROR(__xludf.DUMMYFUNCTION("""COMPUTED_VALUE"""),"Devy Kikim") -> Devy Kikim | X19: ON-Devy Kikim-28052025+5-6282136666049 | AA19: https://wa.me/6282136666049
A20: Iklan Tidak Aktif | B20: 20 | C20: ORD-20 | D20: 45807.363 | E20: 45805 | F20: Nyaraa | G20: Nyaraa Salon | H20: Salon | I20: 6282348365032 | K20: desa mattaropuli kecamatan bengo kabupaten bone soppeng dan wajo | L20: 10-35 | M20: perempuan | N20: 5 | R20: -4633975755 | T20: 197000 | U20: Isna | V20: 45805 | W20: =IFERROR(__xludf.DUMMYFUNCTION("""COMPUTED_VALUE"""),"Nyaraa Salon") -> Nyaraa Salon | X20: ON-Nyaraa Salon-28052025+5-6282348365032 | AA20: https://wa.me/6282348365032
A21: Iklan Tidak Aktif | B21: 21 | C21: ORD-21 | D21: 45807.742 | E21: 45807 | F21: M. Arif Sirajuddin | G21: Sunat Pangkep Avacare | H21: Jasa Sunat Modern | I21: 6285355435848 | K21: Kabupaten Pangkep Sulawesi Selatan | M21: pria | N21: 5 | R21: -4633975755 | T21: 297000 | U21: Yuni | V21: 45807 | W21: =IFERROR(__xludf.DUMMYFUNCTION("""COMPUTED_VALUE"""),"Sunat Pangkep") -> Sunat Pangkep | X21: ON-Sunat Pangkep-30052025+5-6285355435848 | AA21: https://wa.me/6285355435848
A22: Iklan Tidak Aktif | B22: 22 | C22: ORD-22 | D22: 45808.393 | E22: 45807 | F22: NURKHOLIS | G22: PUTRA MANDIRI HARMONIKA | H22: PRODUKSI PINTU BESI | I22: 6281331854948 | J22: spesialist pintu besi | K22: jombang, lamongan, sidoarjo, mojokerto, kediri | L22: 22-65 th | M22: semua jenis | N22: 10 | R22: -4633975755 | T22: 375000 | U22: Isna | V22: 45807 | W22: =IFERROR(__xludf.DUMMYFUNCTION("""COMPUTED_VALUE"""),"PUTRA MANDIRI") -> PUTRA MANDIRI | X22: ON-PUTRA MANDIRI-30052025+10-6281331854948 | AA22: https://wa.me/6281331854948
A23: Iklan Aktif | B23: 23 | C23: ORD-23 | D23: 45808.396 | E23: 45807 | F23: M. Ramli Zebua | G23: PT MAKMUR JAYA ZEBUA | H23: jasa tukang bangunan | I23: 6282173535013 | J23: jasa tukang bangunan rumah dan kontraktor di bidang pembangunan | K23: kota pekanbaru riau dan sekitarnya | L23: 35 th | M23: laki-laki | N23: 5 | R23: -4633975755 | T23: 197000 | U23: Isna | V23: 45807 | W23: =IFERROR(__xludf.DUMMYFUNCTION("""COMPUTED_VALUE"""),"PT MAKMUR") -> PT MAKMUR | X23: ON-PT MAKMUR-30052025+5-6282173535013 | AA23: https://wa.me/6282173535013 | AB23: 120227423725240200
A24: Iklan Tidak Aktif | B24: 24 | C24: ORD-24 | D24: 45808.4 | E24: 45807 | F24: Inggie | G24: Loundry W&M | H24: Londry | I24: 6288242107169 | J24: cuci kering setrika bisa antar jemput sesuai jarak | K24: dari bundaran samata kampus uin samata | L24: 35 th | M24: perempuan | N24: 5 | O24: 45811 | P24: 45815 | R24: -4633975755 | T24: 197000 | U24: Isna | V24: 45807 | W24: =IFERROR(__xludf.DUMMYFUNCTION("""COMPUTED_VALUE"""),"Loundry W&M") -> Loundry W&M | X24: ON-Loundry W&M-30052025+5-6288242107169 | Y24: R11-759724529202804 | Z24: Promo Bisnis UMKM-R11-672574572602431 | AA24: https://wa.me/6288242107169
A25: Iklan Tidak Aktif | B25: 25 | C25: ORD-25 | D25: 45808.76 | E25: 45802 | F25: Yara | G25: M&Y mahkota salon & yara wedding | H25: wedding & salon kecantikan | I25: 6282159148587 | K25: kalimantan selatan, kalimantan tengah, kalimantan timur | L25: 15-60 th | M25: perempuan | N25: 5 | R25: -4633975755 | T25: 197000 | U25: Isna | V25: 45802 | W25: =IFERROR(__xludf.DUMMYFUNCTION("""COMPUTED_VALUE"""),"M&Y mahkota") -> M&Y mahkota | X25: ON-M&Y mahkota-25052025+5-6282159148587 | AA25: https://wa.me/6282159148587
A26: Iklan Tidak Aktif | B26: 26 | C26: ORD-26 | D26: 45808.766 | E26: 45799 | F26: Lisa | G26: Lisa Beauty Zone | H26: Beauty Studio | I26: 6282314234523 | K26: Area Solo dan Sukoharjo, Jawa Tengah | L26: 18 th keatas | M26: Perempuan | N26: 5 | R26: -4633975755 | T26: 197000 | U26: Devi | V26: 45799 | W26: =IFERROR(__xludf.DUMMYFUNCTION("""COMPUTED_VALUE"""),"Lisa Beauty") -> Lisa Beauty | X26: ON-Lisa Beauty-22052025+5-6282314234523 | AA26: https://wa.me/6282314234523
A27: Iklan Tidak Aktif | B27: 27 | C27: ORD-27 | D27: 45809.405 | E27: 45808 | F27: Bogie Irawan | G27: Dapur Florist (Metro Lampung) | H27: Jasa Sewa Papan Bunga Premium | I27: 6281399998259 | J27: terima pesanan karangan bunga untuk acara wedding, duka cita, sertijab, pelantikan, ulang tahun, wisuda dll. | K27: kota metro, lampung timur, lampung tengah, bandar lampung, provinsi lampung. | L27: 15 th ke atas | M27: male n female | N27: 10 | O27: 45811 | P27: 45820 | R27: -4633975755 | T27: 375000 | U27: Isna | V27: 45808 | W27: =IFERROR(__xludf.DUMMYFUNCTION("""COMPUTED_VALUE"""),"Dapur Florist") -> Dapur Florist | X27: ON-Dapur Florist-31052025+10-6281399998259 | Y27: R11-759724529202804 | Z27: Promo Bisnis UMKM-R11-672574572602431 | AA27: https://wa.me/6281399998259
A28: Iklan Aktif | B28: 28 | C28: ORD-28 | D28: 45809.558 | E28: 45809.558 | F28: EPE Plavon | G28: EPE Plavon | H28: Pasang Plavon dan interior | I28: 6285362101860 | K28: Nias | M28: perempua dan laki laki | N28: 5 | O28: 45811 | P28: 45815 | R28: -4633975755 | T28: 197000 | U28: Devi | V28: 45809.558 | W28: =IFERROR(__xludf.DUMMYFUNCTION("""COMPUTED_VALUE"""),"EPE Plavon") -> EPE Plavon | X28: ON-EPE Plavon-01062025+5-6285362101860 | Y28: R10-174904221976312 | Z28: Pakar Bangun Indonesia-R11-706957285826722 | AA28: https://wa.me/6285362101860
A29: Iklan Tidak Aktif | B29: 29 | C29: ORD-29 | D29: 45809.56 | E29: 45809.558 | F29: Rina | G29: Klinik murabeautycare | H29: klinik kecantikan | I29: 6282274447649 | K29: Medan | L29: 15-65 tahun | M29: Laki laki dan perempuan | N29: 5 | R29: -4633975755 | T29: 197000 | U29: Devi | V29: 45809.558 | W29: =IFERROR(__xludf.DUMMYFUNCTION("""COMPUTED_VALUE"""),"Klinik murabeautycare") -> Klinik murabeautycare | X29: ON-Klinik murabeautycare-01062025+5-6282274447649 | AA29: https://wa.me/6282274447649 | AB29: 120228023839160200
A30: Iklan Tidak Aktif | B30: 30 | C30: ORD-30 | D30: 45809.689 | E30: 45809.558 | F30: Ali Rahman | G30: Sofie Gorden | H30: Usaha gorden | I30: 6282154795446 | J30: Jasa pembuatan gorden dan pemesanan gorden | K30: seluruh Kalimantan Timur | L30: 17 Tahun keatas | M30: perempuan dan laki laki | N30: 5 | R30: -4633975755 | T30: 197000 | U30: Yuni | V30: 45809.558 | W30: =IFERROR(__xludf.DUMMYFUNCTION("""COMPUTED_VALUE"""),"Sofie Gorden") -> Sofie Gorden | X30: ON-Sofie Gorden-01062025+5-6282154795446 | AA30: https://wa.me/6282154795446
A31: Iklan Tidak Aktif | B31: 32 | C31: ORD-32 | D31: 45809.826 | E31: 45809.558 | F31: irsyad a gani | G31: icad Interior | H31: kitchen set interior | I31: 6285211510282 | K31: jakarta, tangerang | L31: 25 - 45 | M31: wanita | N31: 5 | R31: -4633975755 | T31: 197000 | U31: Devi | V31: 45809.558 | W31: =IFERROR(__xludf.DUMMYFUNCTION("""COMPUTED_VALUE"""),"icad Interior") -> icad Interior | X31: ON-icad Interior-01062025+5-6285211510282 | AA31: https://wa.me/6285211510282
A32: Iklan Tidak Aktif | B32: 33 | C32: ORD-33 | D32: 45810.567 | E32: 45809 | F32: umam | G32: sahabat AC malang | H32: servis ac | I32: 6285737244570 | J32: servis AC untuk wilayah malang,harga terjangkau, pasti puas bergaransi | K32: malang Jawa timur | L32: 25++ | M32: perempuan dan laki-laki | N32: 5 | O32: 45811 | P32: 45815 | R32: -4633975755 | T32: 197 | U32: Yuni | V32: 45809 | W32: =IFERROR(__xludf.DUMMYFUNCTION("""COMPUTED_VALUE"""),"sahabat AC") -> sahabat AC | X32: ON-sahabat AC-01062025+5-6285737244570 | Y32: R11-759724529202804 | Z32: Pakar Teknisi-R11-696512170212149 | AA32: https://wa.me/6285737244570
A33: Iklan Tidak Aktif | B33: 34 | C33: ORD-34 | D33: 45810.597 | E33: 45809 | F33: Ngatini | G33: Travel Umroh dan Haji | H33: Samira Travel Pati | I33: 6285290626929 | K33: pati dan sekitarnya | L33: 30 ke atas | M33: pria dan wanita | N33: 5 | O33: 45811 | P33: 45816 | R33: -4633975755 | T33: 197000 | U33: Isna | V33: 45809 | W33: =IFERROR(__xludf.DUMMYFUNCTION("""COMPUTED_VALUE"""),"Travel Umroh") -> Travel Umroh | X33: ON-Travel Umroh-01062025+5-6285290626929 | Y33: R11-759724529202804 | Z33: Promo Bisnis UMKM-R11-672574572602431 | AA33: https://wa.me/6285290626929
A34: Iklan Tidak Aktif | B34: 35 | C34: ORD-35 | D34: 45810.617 | E34: 45809 | F34: Joko Susilo | G34: bengkel mobil sahaja pelita jaya(SPJ) | H34: perbaikan dan layanan jasa Mobil | I34: 6282288123215 | K34: sukarame,Sukabumi,korpri,jati agung, | L34: 18+ | M34: laki-laki dan perempuan | N34: 10 | R34: -4633975755 | T34: 375000 | U34: Yuni | V34: 45809 | W34: =IFERROR(__xludf.DUMMYFUNCTION("""COMPUTED_VALUE"""),"bengkel mobil") -> bengkel mobil | X34: ON-bengkel mobil-01062025+10-6282288123215 | Y34: R06-766589657993298 | Z34: Sahabat Otomotif-R11-645488418650292 | AA34: https://wa.me/6282288123215
A35: Iklan Tidak Aktif | B35: 36 | C35: ORD-36 | D35: 45810.656 | E35: 45809 | F35: Ahmad Bukhori | G35: Dani Interior | H35: interior | I35: 6281384925770 | J35: menerima pesanan kitchen set, backdrop tv, penyekat ruangan, lemari,tolet/meja rias,meja kantor, partisi,meja belajar dll | K35: Sukolilo Pati, Jateng | L35: 18 tahun keatas | M35: perempuan dan laki-laki | N35: 5 | O35: 45813 | P35: 45817 | R35: -4633975755 | T35: 197000 | U35: Yuni | V35: 45809 | W35: =IFERROR(__xludf.DUMMYFUNCTION("""COMPUTED_VALUE"""),"Dani Interior") -> Dani Interior | X35: ON-Dani Interior-01062025+5-6281384925770 | Y35: R06-766589657993298 | Z35: Pakar Bangun Indonesia-R11-706957285826722 | AA35: https://wa.me/6281384925770
A36: Iklan Tidak Aktif | B36: 38 | C36: ORD-38 | D36: 45810.79 | E36: 45810 | F36: Waldy | G36: Yuzef & Kost Homestay Syariah | H36: Kost2an | I36: 628988759290 | J36: yuzef kost harian & bulanan | K36: dekat dengan SMA Taruna, Stikes Payung Negeri Poltekes Riau | L36: 15-23 th | M36: wanita | N36: 13 | O36: 45813 | P36: 45825 | R36: -4633975755 | T36: 500000 | U36: Isna | V36: 45810 | W36: =IFERROR(__xludf.DUMMYFUNCTION("""COMPUTED_VALUE"""),"Yuzef &") -> Yuzef & | X36: ON-Yuzef &-02062025+13-628988759290 | Y36: R10-174904221976312 | Z36: Promo Bisnis UMKM-R11-672574572602431 | AA36: https://wa.me/628988759290 | AB36: 120226464082810694
A37: Iklan Tidak Aktif | B37: 38 | C37: ORD-38 | D37: 45810.895 | E37: 45810 | F37: Darmawan | G37: Pakis Advertising & Kontruksi | H37: Pakis Advertising Menerima pesanan pengerjaan | I37: 6281934079192 | J37: Menerima pesanan pengerjaan | K37: Pekanbaru | L37: 25 keatas | M37: Perempuan & laki2 | N37: 7 | O37: 45812 | R37: -4633975755 | T37: 297000 | U37: Yuni | V37: 45810 | W37: =IFERROR(__xludf.DUMMYFUNCTION("""COMPUTED_VALUE"""),"Pakis Advertising") -> Pakis Advertising | X37: ON-Pakis Advertising-02062025+7-6281934079192 | Y37: R11-759724529202804 | Z37: Promo Bisnis UMKM-R11-672574572602431 | AA37: https://wa.me/6281934079192
A38: Iklan Tidak Aktif | B38: 39 | C38: ORD-39 | D38: 45811.605 | E38: 45810 | F38: ike ria jelita | G38: Griya rias jelita salon | H38: salon dan rias pengantin | I38: 6281335551395 | J38: salon kecantikan dan rias pengantin | K38: Jetis, Mojokerto | L38: 18 tahun keatas | N38: 5 | O38: 45813 | P38: 45817 | R38: -4633975755 | T38: 197000 | U38: Yuni | V38: 45810 | W38: =IFERROR(__xludf.DUMMYFUNCTION("""COMPUTED_VALUE"""),"Griya rias") -> Griya rias | X38: ON-Griya rias-02062025+5-6281335551395 | Y38: R10-174904221976312 | Z38: Beauty Solution-R11-667346859796665 | AA38: https://wa.me/6281335551395
A39: Iklan Tidak Aktif | B39: 40 | C39: ORD-40 | D39: 45811.605 | E39: 45811.605 | F39: Fit Klin | G39: Fit Klin | H39: Fit Klin | I39: 6282350524788 | N39: 30 | O39: 45811 | P39: 45841 | T39: 875000 | U39: Rudi | V39: 45811.605 | W39: =IFERROR(__xludf.DUMMYFUNCTION("""COMPUTED_VALUE"""),"Fit Klin") -> Fit Klin | X39: ON-Fit Klin-03062025+30-6282350524788 | Y39: R11-759724529202804 | Z39: Promo Bisnis UMKM-R11-672574572602431 | AA39: https://wa.me/6282350524788 | AB39: 120227782745500200
A40: Iklan Tidak Aktif | B40: 43 | C40: ORD-43 | D40: 45812.184 | E40: 45811.605 | F40: M Budiman | G40: CV Budi Mulia Berkah | H40: konstruksi bangunan | I40: 6285822386125 | J40: kontruksi bangunan | K40: Pontianak | L40: 18 tahun keatas | M40: laki-laki dan perempuan | N40: 5 | O40: 45813 | P40: 45817 | R40: -4633975755 | T40: 197000 | U40: Yuni | V40: 45811.605 | W40: =IFERROR(__xludf.DUMMYFUNCTION("""COMPUTED_VALUE"""),"CV Budi") -> CV Budi | X40: ON-CV Budi-03062025+5-6285822386125 | Y40: R06-766589657993298 | Z40: Pakar Bangun Indonesia-R11-706957285826722 | AA40: https://wa.me/6285822386125
A41: Iklan Tidak Aktif | B41: 44 | C41: ORD-44 | D41: 45812.51 | E41: 45810 | F41: Danang Istiaji | G41: PT Bangun renov Jaya, melayani jasa arsitek,bangun rumah, renovasi, konsultasi, perencanaan dll | H41: PT Bangun renov Jaya | I41: 6281226605001 | K41: Semarang | L41: 20 - 50 thn | M41: Laki-laki, dan wanita | N41: 5 | O41: 45812 | P41: 45816 | R41: -4633975755 | T41: 197000 | U41: Yuni | V41: 45810 | W41: =IFERROR(__xludf.DUMMYFUNCTION("""COMPUTED_VALUE"""),"PT Bangun") -> PT Bangun | X41: ON-PT Bangun-02062025+5-6281226605001 | Y41: R10-174904221976312 | Z41: Pakar Bangun Indonesia-R11-706957285826722 | AA41: https://wa.me/6281226605001
A42: Iklan Tidak Aktif | B42: 43 | C42: ORD-43 | D42: 45812.599 | E42: 45810 | F42: Lombri | G42: Umam daffa jaya Bengkel Las | H42: Bengkel Las | I42: 6287715040331 | J42: melayani las pagar, pintu,balkon,canopy,kusen, aluminium, kontruksi baja wf, tempa Clasic, stainless steel | K42: Tangerang,Banten, jakarta,Jabar, Jateng | L42: 18 keatas | M42: perempuan dan laki-laki | N42: 5 | O42: 45812 | P42: 45817 | R42: -4633975755 | T42: 197000 | U42: Yuni | V42: 45810 | W42: =IFERROR(__xludf.DUMMYFUNCTION("""COMPUTED_VALUE"""),"Umam daffa") -> Umam daffa | X42: ON-Umam daffa-02062025+5-6287715040331 | Y42: R10-174904221976312 | Z42: Pakar Bangun Indonesia-R11-706957285826722 | AA42: https://wa.me/6287715040331
A43: Iklan Tidak Aktif | B43: 44 | C43: ORD-44 | D43: 45812.632 | E43: 45812 | F43: Novan Afrianto | G43: CV Sejahtera Teknik | H43: Jasa perawatan dan perbaikan Ac | I43: 6281515877050 | K43: Sidoarjo, Jawa Timur | L43: 20-55 | M43: perempuan dan laki-laki | N43: 5 | O43: 45813 | P43: 45817 | R43: -4633975755 | T43: 197000 | U43: Yuni | V43: 45812 | W43: =IFERROR(__xludf.DUMMYFUNCTION("""COMPUTED_VALUE"""),"CV Sejahtera") -> CV Sejahtera | X43: ON-CV Sejahtera-04062025+5-6281515877050 | Y43: R06-766589657993298 | Z43: Pakar Teknisi-R11-696512170212149 | AA43: https://wa.me/6281515877050
A44: Iklan Tidak Aktif | B44: 45 | C44: ORD-45 | D44: 45813.645 | E44: 45813 | F44: Ridwan | G44: PG MILAN ROSTER JAYA | H44: ROSTER | I44: 6281318125688 | K44: Jabotabek | L44: 21-65 | M44: Laki laki perempuan | N44: 5 | O44: 45815 | P44: 45819 | R44: -4633975755 | T44: 197000 | U44: Devi | V44: 45813 | W44: =IFERROR(__xludf.DUMMYFUNCTION("""COMPUTED_VALUE"""),"PG MILAN") -> PG MILAN | X44: ON-PG MILAN-05062025+5-6281318125688 | Y44: R06-766589657993298 | Z44: Pakar Bangun Indonesia-R11-706957285826722 | AA44: https://wa.me/6281318125688
A45: Iklan Tidak Aktif | B45: 46 | C45: ORD-46 | D45: 45813.728 | E45: 45813 | F45: Supriyanto | G45: Bina Karya Marmer | H45: Jasa pasang poles Marmer | I45: 6281219751312 | J45: Jasa poles marmer kristal,meja dapur, lantai,wastapel dll yang berbahan batu marmer alam,tim handal, material bisa pilih sesuai keinginan | K45: Seluruh Indonesia | L45: 18 tahun keatas | M45: perempuan dan laki-laki | N45: 14 | O45: 45815 | P45: 45828 | R45: -4633975755 | T45: 500000 | U45: Yuni | V45: 45813 | W45: =IFERROR(__xludf.DUMMYFUNCTION("""COMPUTED_VALUE"""),"Bina Karya") -> Bina Karya | X45: ON-Bina Karya-05062025+14-6281219751312 | Y45: R06-766589657993298 | Z45: Pakar Bangun Indonesia-R11-706957285826722 | AA45: https://wa.me/6281219751312
A46: Iklan Tidak Aktif | B46: 47 | C46: ORD-47 | D46: 45813.898 | E46: 45813 | F46: M. Rozin/Dyaz | G46: TEKNIK DYAZ AC | H46: Spesialist AC, Maintenance AC, Service AC, Sedia Unit AC Baru/Second berikut pemasangan sampai Tuntas, Jasa Pasang AC & Electrikal | I46: 6287845701116 | K46: kanci-Cirebon,Jawa Barat | L46: 18Th - 65 Th | M46: semua | N46: 5 | O46: 45815 | P46: 45819 | R46: -4633975755 | T46: 197000 | U46: Yuni | V46: 45813 | W46: =IFERROR(__xludf.DUMMYFUNCTION("""COMPUTED_VALUE"""),"TEKNIK DYAZ") -> TEKNIK DYAZ | X46: ON-TEKNIK DYAZ-05062025+5-6287845701116 | Y46: R06-766589657993298 | Z46: Pakar Teknisi-R11-696512170212149 | AA46: https://wa.me/6287845701116
A47: Iklan Tidak Aktif | B47: 48 | C47: ORD-48 | D47: 45813.957 | E47: 05-Juni-2025 | F47: Ismail | G47: Tukang Njatipurno 354 | H47: jasa borong bangun rumah, renovasi rumah | I47: 6283134740502 | K47: wonogiri, karanganyar, girimarto, kec. sidoharjo wonogiri | M47: perempuan/laki-laki | N47: 5 | O47: 45815 | P47: 45819 | R47: -4633975755 | T47: 197000 | U47: Isna | V47: 05-Juni-2025 | W47: =IFERROR(__xludf.DUMMYFUNCTION("""COMPUTED_VALUE"""),"Tukang Njatipurno") -> Tukang Njatipurno | X47: ON-Tukang Njatipurno-05-Juni-2025+5-6283134740502 | Y47: R06-766589657993298 | Z47: Pakar Bangun Indonesia-R11-706957285826722 | AA47: https://wa.me/6283134740502
A48: Iklan Tidak Aktif | B48: 49 | C48: ORD-49 | D48: 45815.669 | E48: 07-Juni-2025 | F48: Rosita Freitas | G48: Rosfreb Shop | H48: Online Shop | I48: 6267074784874 | J48: pakaian, sepatu, kosmetik, aksesoris & perhiasan, tas, dan kain dekorasi | K48: Baucau kota lama | L48: semua usia | M48: semua jenis | N48: 10 | O48: 45819 | P48: 45829 | R48: -4633975755 | T48: 375000 | U48: Isna | V48: 07-Juni-2025 | W48: =IFERROR(__xludf.DUMMYFUNCTION("""COMPUTED_VALUE"""),"Rosfreb Shop") -> Rosfreb Shop | X48: ON-Rosfreb Shop-07-Juni-2025+10-6267074784874 | Y48: R10-174904221976312 | Z48: Beauty Solution-R11-667346859796665 | AA48: https://wa.me/6267074784874 | AB48: 120226538247460694
A49: Iklan Tidak Aktif | B49: 50 | C49: ORD-50 | D49: 45815.669 | E49: 07-Juni-2025 | F49: Medi | G49: Abadi Kaca & Almunium Jepara | H49: Pembuatan Kusen Pintu Jendela Almunium dan Kaca | I49: 6282211675028 | K49: Jln raya wedelan - pltu kaliaman rt 4 rw 2 | N49: 5 | O49: 45820 | P49: 45824 | R49: -4633975755 | T49: 197000 | U49: Isna | V49: 07-Juni-2025 | W49: =IFERROR(__xludf.DUMMYFUNCTION("""COMPUTED_VALUE"""),"Abadi Kaca") -> Abadi Kaca | X49: ON-Abadi Kaca-07-Juni-2025+5-6282211675028 | Y49: R06-766589657993298 | Z49: Pakar Bangun Indonesia-R11-706957285826722 | AA49: https://wa.me/6282211675028
A50: Iklan Tidak Aktif | B50: 51 | C50: ORD-51 | D50: 45816.881 | E50: 45815 | F50: bapak yolle suryawan | G50: PT. Mengalir Berkat Anugerah | H50: Kontraktor | I50: 6281222110766 | K50: Bali | L50: 35 ke atas | M50: perempuan dan laki laki | N50: 7 | O50: 45819 | P50: 45826 | R50: -4633975755 | T50: 299000 | U50: Devi | V50: 45815 | W50: =IFERROR(__xludf.DUMMYFUNCTION("""COMPUTED_VALUE"""),"PT. Mengalir") -> PT. Mengalir | X50: ON-PT. Mengalir-07062025+7-6281222110766 | Y50: R06-766589657993298 | Z50: Pakar Bangun Indonesia-R11-706957285826722 | AA50: https://wa.me/6281222110766
A51: Iklan Tidak Aktif | B51: 53 | C51: ORD-53 | D51: 45818.346 | E51: 45817 | F51: SMA MUHAMMADIYAH SAMARINDA | G51: SMA MUHAMMADIYAH SAMARINDA | H51: Pendidikan | I51: 6281340892328 | K51: Samarindia | L51: 25 | M51: perempuan dan laki laki | N51: 30 | R51: -4633975755 | T51: 895000 | U51: Rudi | V51: 45817 | W51: =IFERROR(__xludf.DUMMYFUNCTION("""COMPUTED_VALUE"""),"SMA MUHAMMADIYAH") -> SMA MUHAMMADIYAH | X51: ON-SMA MUHAMMADIYAH-09062025+30-6281340892328 | Y51: R06-766589657993298 | Z51: Lembaga Edukasi Pilihan Anda-R10-581334451725831 | AA51: https://wa.me/6281340892328
A52: Iklan Tidak Aktif | B52: 54 | C52: ORD-54 | D52: 45818.346 | E52: 09-Juni-2025 | F52: Daldiri | G52: Mungkid Sejahtera | H52: bidang bangunan gedung dan lain-lain. kanopi pintu gerbang dan segala macem | I52: 6281328119680 | K52: Purworejo, Magelang, Yogyakarta dan sekitarnya | L52: 30-50 th | M52: laki-laki & perempuan | N52: 5 | O52: 45824 | P52: 45828 | R52: -4633975755 | T52: 197000 | U52: Isna | V52: 09-Juni-2025 | W52: =IFERROR(__xludf.DUMMYFUNCTION("""COMPUTED_VALUE"""),"Mungkid Sejahtera") -> Mungkid Sejahtera | X52: ON-Mungkid Sejahtera-09-Juni-2025+5-6281328119680 | Y52: R06-766589657993298 | Z52: Pakar Bangun Indonesia-R11-706957285826722 | AA52: https://wa.me/6281328119680 | AB52: 120227481491120235
A53: Iklan Tidak Aktif | B53: 55 | C53: ORD-55 | D53: 45818.347 | E53: 09-Juni-2025 | F53: Arjuna Batara | G53: ABATA KARYA | H53: tukang bangunan | I53: 6282399006447 | J53: jasa tukang bangunan | K53: Makassar dan Gowa | L53: 25 sampai 45 th | M53: laki-laki dan perempuan | N53: 10 | O53: 45819 | P53: 45829 | R53: -4633975755 | T53: 375000 | U53: Isna | V53: 09-Juni-2025 | W53: =IFERROR(__xludf.DUMMYFUNCTION("""COMPUTED_VALUE"""),"ABATA KARYA") -> ABATA KARYA | X53: ON-ABATA KARYA-09-Juni-2025+10-6282399006447 | Y53: R06-766589657993298 | Z53: Pakar Bangun Indonesia-R11-706957285826722 | AA53: https://wa.me/6282399006447
A54: Iklan Tidak Aktif | B54: 56 | C54: ORD-56 | D54: 45818.347 | E54: 45815 | F54: hasanah | G54: AFIKA DEKORATION AFIKA RIAS | H54: SEWA DEKORASI PELAMINAN TENDA Panggung,Make up | I54: 6285864008882 | J54: Make up pengantin, lamaran, wisuda dll,DEKORASI MEYEWAKAN ALAT PESTA untuk wedding dan lamaran | K54: Cimanggu, Sukabumi jabar | L54: 18 keatas | M54: perempuan dan laki-laki | N54: 5 | O54: 45819 | P54: 45824 | R54: -4633975755 | T54: 148000 | U54: Yuni | V54: 45815 | W54: =IFERROR(__xludf.DUMMYFUNCTION("""COMPUTED_VALUE"""),"AFIKA DEKORATION") -> AFIKA DEKORATION | X54: ON-AFIKA DEKORATION-07062025+5-6285864008882 | Y54: R10-174904221976312 | Z54: Beauty Solution-R11-667346859796665 | AA54: https://wa.me/6285864008882 | AB54: 120226539786220694
A55: Iklan Tidak Aktif | B55: 57 | C55: ORD-57 | D55: 45820.62 | E55: 45818 | F55: Umi Rahmawati | G55: Rahma Gallery | H55: Furniture dan Interior Design | I55: ‪‪6282116044279‬‬ | K55: area jateng | L55: 20 - 50 | M55: pria dan wanita | N55: 10 | T55: 375000 | U55: Yuni | V55: 45818 | W55: =IFERROR(__xludf.DUMMYFUNCTION("""COMPUTED_VALUE"""),"Rahma Gallery") -> Rahma Gallery | X55: ON-Rahma Gallery-10062025+10-‪‪6282116044279‬‬ | Y55: R06-766589657993298 | Z55: Beauty Solution-R11-667346859796665 | AA55: https://wa.me/‪‪6282116044279‬‬
A56: Iklan Tidak Aktif | B56: 57 | C56: ORD-57 | D56: 45820.679 | E56: 45816 | F56: Erna Damayanti | G56: S'three hair and beauty studio | H56: salon kecantikan | I56: 62895401448273 | J56: hair extension, smoting colouring, face treatment, body treatment | K56: Bali | M56: laki laki dan perempuan | N56: 5 | T56: 197000 | U56: Devi | V56: 45816 | W56: =IFERROR(__xludf.DUMMYFUNCTION("""COMPUTED_VALUE"""),"S'three hair") -> S'three hair | X56: ON-S'three hair-08062025+5-62895401448273 | AA56: https://wa.me/62895401448273
A57: Iklan Tidak Aktif | B57: 58 | C57: ORD-58 | D57: 45820.68 | E57: 45819 | F57: Deni Afriadi sinaga | G57: Abizar plafon | H57: jasa pemasangan plafon gypsum dan plafon pvc | I57: 6281278788088 | K57: Sumatra Utara | L57: 25 - 60 | M57: Laki laki dan perempuan | N57: 5 | O57: 45822 | P57: 45826 | T57: 197000 | U57: Devi | V57: 45819 | W57: =IFERROR(__xludf.DUMMYFUNCTION("""COMPUTED_VALUE"""),"Abizar plafon") -> Abizar plafon | X57: ON-Abizar plafon-11062025+5-6281278788088 | Y57: R06-766589657993298 | Z57: Pakar Bangun Indonesia-R11-706957285826722 | AA57: https://wa.me/6281278788088
A58: Iklan Tidak Aktif | B58: 59 | C58: ORD-59 | D58: 45820.681 | E58: 45818 | F58: Saba | G58: PT AGUS ELTRICAL ELEKTRONIK | H58: servis AC cctv intalasi listrik dll | I58: 6282255726295 | K58: wangi wangi selatan, Wakatobi Sulawesi tenggara | L58: 18-55 | M58: semua | N58: 5 | O58: 45822 | P58: 45826 | T58: 197000 | U58: Yuni | V58: 45818 | W58: =IFERROR(__xludf.DUMMYFUNCTION("""COMPUTED_VALUE"""),"PT AGUS") -> PT AGUS | X58: ON-PT AGUS-10062025+5-6282255726295 | Y58: R06-766589657993298 | Z58: Jasa Service AC Terdekat-R10-522032024316690 | AA58: https://wa.me/6282255726295 | AB58: 120227607532660235
A59: Iklan Aktif | B59: 60 | C59: ORD-60 | D59: 45820.682 | E59: 45819 | F59: Pranoto hadi | G59: Hadi property | H59: jasa kontraktor, jasa rancang bangun baru & renovasi, rumah tinggal, ruko, kosan dll. | I59: 628114170888 | K59: samarinda dan sekitarnya mecakup satu kaltim | L59: remaja sampai tua | M59: semua jenis | N59: 5 | O59: 45822 | P59: 45826 | T59: 197000 | U59: Yuni | V59: 45819 | W59: =IFERROR(__xludf.DUMMYFUNCTION("""COMPUTED_VALUE"""),"Hadi property") -> Hadi property | X59: ON-Hadi property-11062025+5-628114170888 | Y59: R06-766589657993298 | Z59: Pakar Bangun Indonesia-R11-706957285826722 | AA59: https://wa.me/628114170888
A60: Iklan Aktif | B60: 61 | C60: ORD-61 | D60: 45820.682 | E60: 45819 | F60: CV REGAN PERMATA ASIA | G60: CV REGAN PERMATA ASIA | H60: bahan bangunan ( Paving,Batako,Buis Beton ) dan property | I60: 6285853370682 | J60: pembuatan design bangunan, pelaksanaan bangunan, | K60: Jatim ( Blitar, Tulungagung, Kediri) | L60: 18 keatas | M60: Semua usia | N60: 5 | O60: 45822 | P60: 45826 | T60: 197000 | U60: Yuni | V60: 45819 | W60: =IFERROR(__xludf.DUMMYFUNCTION("""COMPUTED_VALUE"""),"CV REGAN") -> CV REGAN | X60: ON-CV REGAN-11062025+5-6285853370682 | Y60: R06-766589657993298 | Z60: Pakar Bangun Indonesia-R11-706957285826722 | AA60: https://wa.me/6285853370682
A61: Iklan Aktif | B61: 62 | C61: ORD-62 | D61: 45820.827 | E61: 45820 | F61: Kukuh Nugroho | G61: Griya Terapi Bekam & Gurah "Laa Tahzan" | H61: jasa terapi bekam & gurah | I61: 6281904501876 | J61: melayani terapi bekam untuk keluhan penyakit ringan maupun berat | K61: kabupaten karanganyar | L61: 20-60 th | M61: laki-laki & perempuan | N61: 5 | O61: 45823 | P61: 45827 | T61: 197000 | U61: Isna | V61: 45820 | W61: =IFERROR(__xludf.DUMMYFUNCTION("""COMPUTED_VALUE"""),"Griya Terapi") -> Griya Terapi | X61: ON-Griya Terapi-12062025+5-6281904501876 | Y61: R10-174904221976312 | Z61: Promo Bisnis UMKM-R11-672574572602431 | AA61: https://wa.me/6281904501876 | AB61: 120226909524250694
A62: Iklan Tidak Aktif | B62: 63 | C62: ORD-63 | D62: 45820.829 | E62: 45820 | F62: Dedi | G62: Jasa Bangun | H62: kontraktor | I62: 6285714611166 | K62: jabodetabek | M62: laki-laki & perempuan | N62: 5 | O62: 45822 | P62: 45826 | T62: 197000 | U62: Isna | V62: 45820 | W62: =IFERROR(__xludf.DUMMYFUNCTION("""COMPUTED_VALUE"""),"Jasa Bangun") -> Jasa Bangun | X62: ON-Jasa Bangun-12062025+5-6285714611166 | Y62: R06-766589657993298 | Z62: Pakar Bangun Indonesia-R11-706957285826722 | AA62: https://wa.me/6285714611166
A63: Iklan Aktif | B63: 65 | C63: ORD-65 | D63: 46027 | E63: 45819 | F63: Budiman | G63: PT Jujur Jaya Sakti Mamuju | H63: Promo Daihatsu Sulawesi Barat Mamuju | I63: 6282347206488 | K63: Mamuju | L63: 31 th ke atas | M63: laki-laki dan perempuan | N63: 5 | R63: -1003470351325 | T63: 197000 | U63: Isna | V63: 45819 | W63: =IFERROR(__xludf.DUMMYFUNCTION("""COMPUTED_VALUE"""),"PT Jujur") -> PT Jujur | X63: ON-PT Jujur-11062025+5-6282347206488 | AA63: https://wa.me/6282347206488
A64: Iklan Aktif | B64: 66 | C64: ORD-66 | D64: 45820.833 | E64: 45819 | F64: Imron | G64: Bengkel Las Lima Sodara | H64: bengkel las | I64: 6281519225886 | K64: lemah abang | L64: bebas | M64: L/P | N64: 5 | O64: 45822 | P64: 45826 | T64: 197000 | U64: Isna | W64: =IFERROR(__xludf.DUMMYFUNCTION("""COMPUTED_VALUE"""),"Bengkel Las") -> Bengkel Las | X64: ON-Bengkel Las-00011900+5-6281519225886 | Y64: R06-766589657993298 | Z64: Pakar Teknisi-R11-696512170212149 | AA64: https://wa.me/6281519225886
A65: Iklan Aktif | B65: 67 | C65: ORD-67 | D65: 25-Des-2025 | E65: 45819 | F65: Agus | G65: Bengkel Las dan Pemasangan Plavon | H65: bengkel las pagar kanopi dll | I65: 6282393168368 | K65: gowa, makassar, maros, takalar, pangkep | L65: 12-70 th | M65: laki-laki & perempuan | N65: 30 | R65: -1003470351325 | T65: 950000 | U65: Isna | V65: 46017.169 | W65: =IFERROR(__xludf.DUMMYFUNCTION("""COMPUTED_VALUE"""),"Bengkel Las") -> Bengkel Las | X65: ON-Bengkel Las-26122025+30-6282393168368 | Y65: R06-766589657993298 | Z65: Pakar Teknisi-R11-696512170212149 | AA65: https://wa.me/6282393168368
A66: Iklan Tidak Aktif | B66: 68 | C66: ORD-68 | D66: 45820.835 | E66: 45819 | F66: Heri Khoerudin | G66: Mitra Karya Jaya Aluminium | H66: kontruksi aluminium kaca | I66: 6285353864755 | K66: bogor, jabodetabek, jawa barat | N66: 5 | O66: 45822 | P66: 45826 | T66: 197000 | U66: Isna | W66: =IFERROR(__xludf.DUMMYFUNCTION("""COMPUTED_VALUE"""),"Mitra Karya") -> Mitra Karya | X66: ON-Mitra Karya-00011900+5-6285353864755 | Y66: R06-766589657993298 | Z66: Pakar Bangun Indonesia-R11-706957285826722 | AA66: https://wa.me/6285353864755
A67: Iklan Tidak Aktif | B67: 69 | C67: ORD-69 | D67: 45820.836 | E67: 45819 | F67: Vivi | G67: Vie Salon Beauty Malang | H67: Salon | I67: 6281216962242 | K67: malang | L67: mulai 13 th | M67: wanita | N67: 5 | O67: 45822 | P67: 45826 | T67: 197000 | U67: Isna | W67: =IFERROR(__xludf.DUMMYFUNCTION("""COMPUTED_VALUE"""),"Vie Salon") -> Vie Salon | X67: ON-Vie Salon-00011900+5-6281216962242 | Y67: R11-759724529202804 | Z67: Beauty Solution-R11-667346859796665 | AA67: https://wa.me/6281216962242 | AB67: 120228392828650200
A68: Iklan Tidak Aktif | B68: 70 | C68: ORD-70 | D68: 45820.837 | E68: 45819 | F68: Hana Harun | G68: Hana Glamour Salon dan Spa | H68: salon kecantikan dan spa | I68: 6281335728695 | J68: menerima berbagai jasa kecantikan hair treatment dan body treatment | K68: kabupaten pasuruan, surabaya dan malang. | L68: 20-40 th | M68: perempuan | N68: 5 | O68: 45822 | P68: 45826 | T68: 197000 | U68: Isna | W68: =IFERROR(__xludf.DUMMYFUNCTION("""COMPUTED_VALUE"""),"Hana Glamour") -> Hana Glamour | X68: ON-Hana Glamour-00011900+5-6281335728695 | Y68: R11-759724529202804 | Z68: Beauty Solution-R11-667346859796665 | AA68: https://wa.me/6281335728695 | AB68: 120228395930460200
A69: Iklan Tidak Aktif | B69: 71 | C69: ORD-71 | D69: 45820.837 | E69: 45819 | F69: Thurman | G69: Pt Natama Sarana Tehnik | H69: kontruksi sipil design & mep | I69: 6285261023204 | K69: sumatera utara & jawa | L69: segala usia | M69: L/P | N69: 5 | O69: 45823 | P69: 45827 | T69: 197000 | U69: Isna | W69: =IFERROR(__xludf.DUMMYFUNCTION("""COMPUTED_VALUE"""),"Pt Natama") -> Pt Natama | X69: ON-Pt Natama-00011900+5-6285261023204 | Y69: R06-766589657993298 | Z69: Pakar Bangun Indonesia-R11-706957285826722 | AA69: https://wa.me/6285261023204 | AB69: 120227451579360235
A70: Iklan Aktif | B70: 72 | C70: ORD-72 | D70: 45820.839 | E70: 45818 | F70: Widianto | G70: WD Kontruksi | H70: civil building | I70: 6285747906282 | J70: jasa bangun rumah atau renovasi | K70: area purwokerto jawa tengah dan sekitarnya | L70: 36 th | M70: laki-laki | N70: 10 | O70: 45822 | P70: 45831 | T70: 375000 | U70: Isna | W70: =IFERROR(__xludf.DUMMYFUNCTION("""COMPUTED_VALUE"""),"WD Kontruksi") -> WD Kontruksi | X70: ON-WD Kontruksi-00011900+10-6285747906282 | Y70: R06-766589657993298 | Z70: Pakar Bangun Indonesia-R11-706957285826722 | AA70: https://wa.me/6285747906282
A71: Iklan Tidak Aktif | B71: 73 | C71: ORD-73 | D71: 45820.839 | E71: 45818 | F71: Pulung Windu Hantoro | G71: Bangun Griya | H71: kontraktor bangunan | I71: 6281952482523 | J71: jasa bangun baru dan renovasi | K71: solo-boyolali semarang | L71: 38 th | M71: laki-laki | N71: 10 | T71: 375000 | U71: Isna | W71: =IFERROR(__xludf.DUMMYFUNCTION("""COMPUTED_VALUE"""),"Bangun Griya") -> Bangun Griya | X71: ON-Bangun Griya-00011900+10-6281952482523 | AA71: https://wa.me/6281952482523
A72: Iklan Aktif | B72: 74 | C72: ORD-74 | D72: 45820.84 | E72: 45817 | F72: Saepul Anwar | G72: Mandorbogor | H72: jasa bangun dan renovasi | I72: 6285220216325 | K72: Jabodetabek | N72: 10 | T72: 375000 | U72: Isna | W72: =IFERROR(__xludf.DUMMYFUNCTION("""COMPUTED_VALUE"""),"Mandorbogor") -> Mandorbogor | X72: ON-Mandorbogor-00011900+10-6285220216325 | AA72: https://wa.me/6285220216325
A73: Iklan Tidak Aktif | B73: 75 | C73: ORD-75 | D73: 45820.841 | E73: 09-Juni-2025 | F73: Arjuna Batara | G73: Abata Karya | H73: jasa tukang bangunan | I73: 6282399006447 | J73: jasa tukang bangunan | K73: Makassar dan Gowa | L73: 25-45 th | M73: laki-laki & perempuan | N73: 10 | T73: 375000 | U73: Isna | W73: =IFERROR(__xludf.DUMMYFUNCTION("""COMPUTED_VALUE"""),"Abata Karya") -> Abata Karya | X73: ON-Abata Karya-00011900+10-6282399006447 | AA73: https://wa.me/6282399006447
A74: Iklan Tidak Aktif | B74: 76 | C74: ORD-76 | D74: 45820.842 | E74: 09-Juni-2025 | F74: Daldiri | G74: Mungkid Sejahtera | H74: bidang bangunan gedung dll, kanopi pintu gerbang dan segala macam | I74: 6281328119680 | K74: purworejo, magelang, yogyakarta dan sekitarnya | L74: 30-50 th | M74: laki-laki & perempuan | N74: 5 | T74: 197000 | U74: Isna | W74: =IFERROR(__xludf.DUMMYFUNCTION("""COMPUTED_VALUE"""),"Mungkid Sejahtera") -> Mungkid Sejahtera | X74: ON-Mungkid Sejahtera-00011900+5-6281328119680 | AA74: https://wa.me/6281328119680
A75: Iklan Aktif | B75: 77 | C75: ORD-77 | D75: 45820.843 | E75: 45816 | F75: Riza Ramadhon | G75: PHONE CELL CENTER | H75: toko service handphone | I75: 6281241440688 | J75: servis hp berkualitas, bisa di tunggu dan garansi 1 bulan , melayani segala kerusakan handphone | K75: jln. Pulau semama. Samping SDN 019 tanjung redeb. Kab. Berau kalimantan timur | L75: 20-45 th | M75: laki-laki & perempuan | N75: 5 | T75: 197000 | U75: Isna | W75: =IFERROR(__xludf.DUMMYFUNCTION("""COMPUTED_VALUE"""),"PHONE CELL") -> PHONE CELL | X75: ON-PHONE CELL-00011900+5-6281241440688 | AA75: https://wa.me/6281241440688
A76: Iklan Tidak Aktif | B76: 78 | C76: ORD-78 | D76: 45820.895 | E76: 45817 | F76: Eko Budiono | G76: Amanah Interior Jambi | H76: Interior Design | I76: 6282280929802 | J76: melayani segala macam pembuatan interior. menyesuaikan budget yang di sediakan konsumen. gambar design mengikuti budget. survey dan gambar design free. garansi perawatan | K76: kota jambi dan muaro jambi (daerah sawit), batang hari (jambi) dan bayung lencir (kabupaten banyuasin sumsel) | M76: laki-laki & perempuan | N76: 5 | T76: 197000 | U76: Isna | W76: =IFERROR(__xludf.DUMMYFUNCTION("""COMPUTED_VALUE"""),"Amanah Interior") -> Amanah Interior | X76: ON-Amanah Interior-00011900+5-6282280929802 | AA76: https://wa.me/6282280929802
A77: Iklan Tidak Aktif | B77: 79 | C77: ORD-79 | D77: 45821.827 | E77: 45821 | F77: Randy | G77: Bhoemi Kontraktor | H77: Kontruksi | I77: 6283185169816 | K77: Medan | L77: 31-59 th | M77: laki-laki & perempuan | N77: 5 | O77: 45822 | P77: 45826 | T77: 197000 | U77: Isna | W77: =IFERROR(__xludf.DUMMYFUNCTION("""COMPUTED_VALUE"""),"Bhoemi Kontraktor") -> Bhoemi Kontraktor | X77: ON-Bhoemi Kontraktor-00011900+5-6283185169816 | Y77: R06-766589657993298 | Z77: Pakar Bangun Indonesia-R11-706957285826722 | AA77: https://wa.me/6283185169816
A78: Iklan Tidak Aktif | B78: 80 | C78: ORD-80 | D78: 46038 | E78: 45821 | F78: Samidi | G78: Samidi Plafon PVC | H78: Pemasangan Plavon | I78: 6285210107607 | K78: Muktisari | L78: 35-60 th | M78: laki-laki dan perempuan | N78: 7 | R78: -1003470351325 | T78: 297000 | U78: Isna | V78: 46040.301 | W78: =IFERROR(__xludf.DUMMYFUNCTION("""COMPUTED_VALUE"""),"Samidi Plafon") -> Samidi Plafon | X78: ON-Samidi Plafon-18012026+7-6285210107607 | Y78: R06-766589657993298 | Z78: Pakar Bangun Indonesia-R11-706957285826722 | AA78: https://wa.me/6285210107607
A79: Iklan Tidak Aktif | B79: 81 | C79: ORD-81 | D79: 45821.834 | E79: 45821 | F79: Dilla | G79: Rumah Cantik Drwskincare | H79: Salon & Skincare | I79: 6288215445661 | J79: Produk kecantikan dari Drwskincare by Dokter Wahyu Triasmara dan All Treatment Salon | K79: Purbalingga, Purwokerto, Banjarnegara | M79: Perempuan | N79: 5 | O79: 45822 | P79: 45826 | T79: 197000 | U79: Isna | W79: =IFERROR(__xludf.DUMMYFUNCTION("""COMPUTED_VALUE"""),"Rumah Cantik") -> Rumah Cantik | X79: ON-Rumah Cantik-00011900+5-6288215445661 | Y79: R11-759724529202804 | Z79: Beauty Solution-R11-667346859796665 | AA79: https://wa.me/6288215445661 | AB79: 120228489547990200
A80: Iklan Tidak Aktif | B80: 82 | C80: ORD-82 | D80: 45822.389 | E80: 45820 | F80: Pa'saoran Batur Batur st. | G80: PT. Medan Bangun persada | H80: Kontraktor | I80: 6282162580404 | J80: Arsitek, interior,exterior,mekanik dan elektrikal | K80: Medan, sumatera Utara | L80: 18 -55 | M80: perempuan dan laki-laki | N80: 5 | O80: 45824 | P80: 45828 | T80: 197000 | U80: Yuni | W80: =IFERROR(__xludf.DUMMYFUNCTION("""COMPUTED_VALUE"""),"PT. Medan") -> PT. Medan | X80: ON-PT. Medan-00011900+5-6282162580404 | Y80: R06-766589657993298 | Z80: Pakar Bangun Indonesia-R11-706957285826722 | AA80: https://wa.me/6282162580404 | AB80: 120227527913110235
A81: Proses OTP | B81: 83 | C81: ORD-83 | D81: 45822.389 | E81: 45820 | F81: Kipon | G81: Anjas Jaya | H81: Mebel furniture | I81: 6281337029495 | J81: produksi/pembuatan Furniture dan mebel | K81: Sangatta Selatan Kalimantan Timur | L81: 17-55 | M81: perempuan dan laki-laki | N81: 5 | O81: 45824 | P81: 45828 | T81: 197000 | U81: Yuni | W81: =IFERROR(__xludf.DUMMYFUNCTION("""COMPUTED_VALUE"""),"Anjas Jaya") -> Anjas Jaya | X81: ON-Anjas Jaya-00011900+5-6281337029495 | Y81: R10-174904221976312 | Z81: Jasa Interior dan Exterior Terdekat-R10-514784225046611 | AA81: https://wa.me/6281337029495 | AB81: 120227006509980694
A82: Iklan Aktif | B82: 84 | C82: ORD-84 | D82: 45822.707 | E82: 45822 | F82: Julia rizkia | G82: BATRA SENTUTORAF | H82: Pengobatan sendiri tulang otot dan saraf | I82: 6282258886603 | J82: Klinik kami memberikan layanan gabungan antara tradisional terapi atw yg dikenal dengan pijit dengan modern terapi yaitu penggunaan alat fisio seperti lampu uv, ultrasound dan tense. | K82: Jabodetabek | M82: wanita dan ski laki | N82: 5 | O82: 45824 | P82: 45829 | T82: 197000 | U82: Devi | W82: =IFERROR(__xludf.DUMMYFUNCTION("""COMPUTED_VALUE"""),"BATRA SENTUTORAF") -> BATRA SENTUTORAF | X82: ON-BATRA SENTUTORAF-00011900+5-6282258886603 | Y82: R10-174904221976312 | Z82: Griya Sehat-R10-576779842182895 | AA82: https://wa.me/6282258886603 | AB82: 120227002983460694
A83: Iklan Aktif | B83: 85 | C83: ORD-85 | D83: 46065 | E83: 45822 | F83: Eko | G83: CV Fajar Gemilang | H83: kontraktor/aplikator acp , kaca , aluminium , interior , arsitektur gedung dll | I83: 6281338789995 | K83: kupang ntt | L83: 25-60 | M83: semua | N83: 14 | R83: -1003470351325 | T83: 550000 | U83: Yuni | V83: 46065.369 | W83: =IFERROR(__xludf.DUMMYFUNCTION("""COMPUTED_VALUE"""),"CV Fajar") -> CV Fajar | X83: ON-CV Fajar-12022026+14-6281338789995 | Y83: R06-766589657993298 | Z83: Pakar Bangun Indonesia-R11-706957285826722 | AA83: https://wa.me/6281338789995 | AB83: 120227535164300235
A84: Iklan Tidak Aktif | B84: 86 | C84: ORD-86 | D84: 45822.861 | E84: 45822 | F84: Rady | G84: Aqila clean | H84: jasa cuci karpet kantor cuci karpet masjid cuci sepringbed cuci sofa | I84: 6281905836259 | J84: jasa cuci karpet kantor karpet masjid cuci sepringbed sofa panggilan jabodetabek | K84: Jabodetabek | L84: 20 tahun keatas | M84: Laki laki dan wanita | N84: 7 | O84: 45824 | P84: 45830 | T84: 225000 | U84: Devi | W84: =IFERROR(__xludf.DUMMYFUNCTION("""COMPUTED_VALUE"""),"Aqila clean") -> Aqila clean | X84: ON-Aqila clean-00011900+7-6281905836259 | Y84: R10-174904221976312 | Z84: Promo Bisnis UMKM-R11-672574572602431 | AA84: https://wa.me/6281905836259 | AB84: 120226995402390694
A85: Iklan Aktif | B85: 87 | C85: ORD-87 | D85: 45823.326 | E85: 45822 | F85: Artha Jaya | G85: Artha Jaya Kaca Mobil | H85: Jasa ganti kaca mobil | I85: 6285757057088 | K85: Surakarta | L85: 20 tahun keatas | M85: Laki laki dan wanita | N85: 30 | T85: 895000 | U85: Isna | W85: =IFERROR(__xludf.DUMMYFUNCTION("""COMPUTED_VALUE"""),"Artha Jaya") -> Artha Jaya | X85: ON-Artha Jaya-00011900+30-6285757057088 | Y85: R11-759724529202804 | Z85: Jasa Otomotif Terdekat-R10-476331375569214 | AA85: https://wa.me/6285757057088 | AB85: 120227358608350200
A86: Iklan Aktif | B86: 88 | C86: ORD-88 | D86: 45823.332 | E86: 45817 | F86: Arifin | G86: TERAPY SEHAT QUR'ANY | H86: ONLINE Pelatihan Ruqyah Praktis | I86: 6285274759862 | K86: Pati Jateng | L86: 20-50 | M86: laki-laki & perempuan | N86: 5 | T86: 197000 | U86: Yuni | W86: =IFERROR(__xludf.DUMMYFUNCTION("""COMPUTED_VALUE"""),"TERAPY SEHAT") -> TERAPY SEHAT | X86: ON-TERAPY SEHAT-00011900+5-6285274759862 | AA86: https://wa.me/6285274759862 | AB86: 120226549070030694
A87: Iklan Aktif | B87: 89 | C87: ORD-89 | D87: 45823.392 | E87: 45823 | F87: Abdul Rozak | G87: AR Kontraktor | H87: kontraktor bangunan | I87: 6281316155059 | J87: jasa kontraktor bangunan sivil renovasi rumah dan bangun baru,serta kontruksi baja, mekanikal electrical dan jasa pengelasan pembuatan kanopi pagar tralis | K87: jabodetabek | L87: 18 ke atas | M87: semua | N87: 5 | T87: 197000 | U87: Yuni | W87: =IFERROR(__xludf.DUMMYFUNCTION("""COMPUTED_VALUE"""),"AR Kontraktor") -> AR Kontraktor | X87: ON-AR Kontraktor-00011900+5-6281316155059 | Y87: R06-766589657993298 | Z87: Pakar Bangun Indonesia-R11-706957285826722 | AA87: https://wa.me/6281316155059 | AB87: 120227616873540235
A88: Iklan Aktif | B88: 91 | C88: ORD-91 | D88: 45823.409 | E88: 45823 | F88: Kak Yopi | G88: CV BIMA ARSITEKA | H88: Kontraktor bangun rumah mewah di Palembang | I88: 6282176695820 | J88: Kontraktor bangun rumah mewah di Palembang | K88: Palembang dan sekitarnya | L88: 20 thn sd 60 tahun | M88: Laki-laki dan Perempuan. | N88: 7 | O88: 45832 | P88: 45838 | T88: 297000 | U88: Yuni | W88: =IFERROR(__xludf.DUMMYFUNCTION("""COMPUTED_VALUE"""),"CV BIMA") -> CV BIMA | X88: ON-CV BIMA-00011900+7-6282176695820 | Y88: R06-766589657993298 | Z88: Pakar Bangun Indonesia-R11-706957285826722 | AA88: https://wa.me/6282176695820 | AB88: 120227665462840235 | AD88: Ikhsan
A89: Iklan Aktif | B89: 91 | C89: ORD-91 | D89: 45823.455 | E89: 45823 | F89: Heriyana | G89: CV permadana dipta | H89: booth container kusen almunium tralis canopi dll | I89: 6289523308892 | K89: Cirebon Kuningan Brebes | L89: 25-50 | M89: laki-laki | N89: 5 | O89: 45825 | P89: 45829 | T89: 200000 | U89: Devi | W89: =IFERROR(__xludf.DUMMYFUNCTION("""COMPUTED_VALUE"""),"CV permadana") -> CV permadana | X89: ON-CV permadana-00011900+5-6289523308892 | Y89: R06-766589657993298 | Z89: Pakar Bangun Indonesia-R11-706957285826722 | AA89: https://wa.me/6289523308892 | AB89: 120227597002480235
A90: Iklan Aktif | B90: 92 | C90: ORD-92 | D90: 45823.522 | E90: 45823 | F90: Sutarno | G90: Lintang interior | H90: interior | I90: 6281632236409 | K90: Padang, Sumbar | L90: 17-55 | M90: semua | N90: 5 | O90: 45826 | P90: 45830 | T90: 197000 | U90: Yuni | W90: =IFERROR(__xludf.DUMMYFUNCTION("""COMPUTED_VALUE"""),"Lintang interior") -> Lintang interior | X90: ON-Lintang interior-00011900+5-6281632236409 | Y90: R06-766589657993298 | Z90: Pakar Bangun Indonesia-R11-706957285826722 | AA90: https://wa.me/6281632236409 | AB90: 120227621495260235
A91: Iklan Aktif | B91: 93 | C91: ORD-93 | D91: 45823.522 | E91: 45823 | F91: Etiana | G91: Coach Etiana Ris | H91: bisnis on line | I91: 628127962347 | J91: produk digital | K91: Seluruh indonesia | L91: 18 th keatas | M91: laki dan perempuan | N91: 10 | O91: 45825 | P91: 45835 | T91: 375000 | U91: Yuni | W91: =IFERROR(__xludf.DUMMYFUNCTION("""COMPUTED_VALUE"""),"Coach Etiana") -> Coach Etiana | X91: ON-Coach Etiana-00011900+10-628127962347 | Y91: R10-174904221976312 | Z91: Promo Bisnis UMKM-R11-672574572602431 | AA91: https://wa.me/628127962347 | AB91: 120227060953170694
A92: Iklan Aktif | B92: 94 | C92: ORD-94 | D92: 45824.328 | E92: 45824 | F92: bpk Irawan | G92: CV MJB property | H92: jasa bangun rumah , desain | I92: 6282141603091 | J92: bangun rumah toko kantor baru dan renovasi ,desain , profesional | K92: Gresik, Surabaya, Sidoarjo, Mojokerto, Lamongan | L92: 17-55 | N92: 5 | O92: 45826 | P92: 45830 | T92: 197000 | U92: Yuni | W92: =IFERROR(__xludf.DUMMYFUNCTION("""COMPUTED_VALUE"""),"CV MJB") -> CV MJB | X92: ON-CV MJB-00011900+5-6282141603091 | Y92: R06-766589657993298 | Z92: Pakar Bangun Indonesia-R11-706957285826722 | AA92: https://wa.me/6282141603091 | AB92: 120227665552330235 | AD92: Ikhsan
A93: Iklan Aktif | B93: 95 | C93: ORD-95 | D93: 45824.338 | E93: 45824 | F93: fery | G93: MULTI JASA POOL | H93: pembuatan kolam renang, renovasi dan maintenance kolam renang | I93: 6282324392716 | J93: pembuatan kolam renang, renovasi dan maintenance kolam renang | K93: Jabodetabek | L93: 17-55 | M93: Semua | N93: 5 | O93: 45826 | P93: 45830 | T93: 197000 | U93: Yuni | W93: =IFERROR(__xludf.DUMMYFUNCTION("""COMPUTED_VALUE"""),"MULTI JASA") -> MULTI JASA | X93: ON-MULTI JASA-00011900+5-6282324392716 | Y93: R06-766589657993298 | Z93: Pakar Bangun Indonesia-R11-706957285826722 | AA93: https://wa.me/6282324392716 | AB93: 120227665559290235 | AD93: Ikhsan
A94: Iklan Aktif | B94: 96 | C94: ORD-96 | D94: 46064 | E94: 45824 | F94: khafid ali | G94: cv adam jaya construction | H94: desain dan bangun | I94: 6281283325291 | K94: Cibubur,Jaksel,Cipete ,Lebak bulus dan sekitarnya | L94: 17-55 thn | M94: laki laki dan perempuan | N94: 5 | R94: -1003470351325 | T94: 197000 | U94: Yuni | V94: 46064.931 | W94: =IFERROR(__xludf.DUMMYFUNCTION("""COMPUTED_VALUE"""),"cv adam") -> cv adam | X94: ON-cv adam-11022026+5-6281283325291 | Y94: R06-766589657993298 | Z94: Pakar Bangun Indonesia-R11-706957285826722 | AA94: https://wa.me/6281283325291 | AB94: 120227665562340235 | AD94: Ikhsan
A95: Iklan Aktif | B95: 97 | C95: ORD-97 | D95: 12-Des-2025 | E95: 45820 | F95: Para Ir. Berpengalaman | G95: PT. Panorama Jaya Labana | H95: Usaha Jasa Konstruksi spesialist bangun / renovasi Rumah | I95: 628122102657 | K95: Radius 10 Km dari lokasi kantor | L95: 17-55 | M95: SU | N95: 30 | R95: -1003470351325 | T95: 1000000 | U95: Yuni | V95: 46003.46 | W95: =IFERROR(__xludf.DUMMYFUNCTION("""COMPUTED_VALUE"""),"PT. Panorama") -> PT. Panorama | X95: ON-PT. Panorama-12122025+30-628122102657 | Y95: R03-768362231010540 | Z95: Promo Bisnis UMKM-R11-672574572602431 | AA95: https://wa.me/628122102657
A96: Iklan Aktif | B96: 98 | C96: ORD-98 | D96: 45824.583 | E96: 45820 | F96: A,R,Huda | G96: Uwais property | H96: pengembangan perumahan | I96: 6281575323811 | K96: lokasi tengah kampung,solo sragen Karanganyar, lokasi perumahan sudah difasilitasi masjid | L96: para pasangan muda mudi | N96: 5 | O96: 45825 | P96: 45829 | T96: 197000 | U96: Rokhma | W96: =IFERROR(__xludf.DUMMYFUNCTION("""COMPUTED_VALUE"""),"Uwais property") -> Uwais property | X96: ON-Uwais property-00011900+5-6281575323811 | Y96: R03-768362231010540 | Z96: Promo Bisnis UMKM-R11-672574572602431 | AA96: https://wa.me/6281575323811 | AB96: 120227596978200235
A97: Proses OTP | B97: 99 | C97: ORD-99 | D97: 45824.584 | E97: 45823 | F97: Mahmudi | G97: CV Cahaya Makmur Sentosa | H97: kontraktor | I97: 6281327680909 | K97: Abiansemal | L97: Dewasa | M97: Laki laki | N97: 30 | T97: 1000000 | U97: Rokhma | W97: =IFERROR(__xludf.DUMMYFUNCTION("""COMPUTED_VALUE"""),"CV Cahaya") -> CV Cahaya | X97: ON-CV Cahaya-00011900+30-6281327680909 | Y97: R06-766589657993298 | Z97: Pakar Bangun Indonesia-R11-706957285826722 | AA97: https://wa.me/6281327680909 | AB97: 120227597591780235
A98: Iklan Aktif | B98: 100 | C98: ORD-100 | D98: 45824.778 | E98: 45823 | F98: Budi Muhdiar | G98: Dearhouse | H98: kontraktor | I98: 6287778562681 | J98: jasa perbaikan rumah tinggal, renovasi dan bangun baru | K98: jakarta tangerang (banten) | L98: 35 th ke atas | M98: L/P | N98: 10 | O98: 45829 | P98: 45838 | T98: 375000 | U98: Isna | W98: =IFERROR(__xludf.DUMMYFUNCTION("""COMPUTED_VALUE"""),"Dearhouse") -> Dearhouse | X98: ON-Dearhouse-00011900+10-6287778562681 | Y98: R06-766589657993298 | Z98: Pakar Bangun Indonesia-R11-706957285826722 | AA98: https://wa.me/6287778562681 | AB98: 120227597633480235 | AD98: Ikhsan
A99: Iklan Aktif | B99: 101 | C99: ORD-101 | D99: 45824.78 | E99: 45823 | F99: Ety | G99: Salon Ety Wedding | H99: salon kecantikan dan rias pengantin | I99: 6285642607938 | K99: adiwerna tegal. brebes. slawi dan sekitarnya | L99: anak-anak, remaja, dewasa | M99: perempuan | N99: 5 | O99: 45826 | P99: 45830 | T99: 197000 | U99: Isna | W99: =IFERROR(__xludf.DUMMYFUNCTION("""COMPUTED_VALUE"""),"Salon Ety") -> Salon Ety | X99: ON-Salon Ety-00011900+5-6285642607938 | Y99: R11-759724529202804 | Z99: Pakar Bangun Indonesia-R11-706957285826722 | AA99: https://wa.me/6285642607938 | AB99: 120228726720460200
A100: Iklan Aktif | B100: 102 | C100: ORD-102 | D100: 45824.782 | E100: 45824 | F100: Budiyanto | G100: Berkah Contruction | H100: kontruksi bangunan atau renovasi | I100: 6283866009989 | J100: pembangunan rumah pribadi dari 0 atau renovasi kantor, gudang. | K100: jawa tengah | M100: L/P | N100: 10 | O100: 45827 | P100: 45836 | T100: 375000 | U100: Isna | W100: =IFERROR(__xludf.DUMMYFUNCTION("""COMPUTED_VALUE"""),"Berkah Contruction") -> Berkah Contruction | X100: ON-Berkah Contruction-00011900+10-6283866009989 | Y100: R06-766589657993298 | Z100: Pakar Bangun Indonesia-R11-706957285826722 | AA100: https://wa.me/6283866009989 | AB100: 120227705617350235 | AD100: Ikhsan
...

Sheet Log
A1: 45975.534 | B1: Trigger: #inputlaporan# Laporan CS Jasa Iklan UMKM ------- Nama CS: Isna Tanggal: 13-Nov-2025 Leads:60 Jumlah Closing: Paket 1: Paket 2: Paket 3: Paket 4: Paket 5: Repeat Paket 1: Repeat Paket 2: Repeat Paket 3: Repeat Paket 4: Repeat Paket 5: Catatan: 26 nores 18 cek harga 10 tanya tanya 5 isi data 1 ngga jadi
A2: 45975.534 | B2: ERROR: ReferenceError: parseLaporanCS is not defined
A3: 45975.537 | B3: Trigger: #inputlaporan# Laporan CS Jasa Iklan UMKM ------- Nama CS: Isna Tanggal: 13-Nov-2025 Leads:60 Jumlah Closing: Paket 1: Paket 2: Paket 3: Paket 4: Paket 5: Repeat Paket 1: Repeat Paket 2: Repeat Paket 3: Repeat Paket 4: Repeat Paket 5: Catatan: 26 nores 18 cek harga 10 tanya tanya 5 isi data 1 ngga jadi
A4: 45975.537 | B4: Exception: De parameters (String,String,String) komen niet overeen met de methodehandtekening voor Utilities.formatDate.
A5: 45975.537 | B5: LAPORAN SAVED: false
A6: 45975.538 | B6: Trigger: #inputlaporan# Laporan CS Jasa Iklan UMKM ------- Nama CS: Isna Tanggal: 13-Nov-2025 Leads:60 Jumlah Closing: Paket 1: Paket 2: Paket 3: Paket 4: Paket 5: Repeat Paket 1: Repeat Paket 2: Repeat Paket 3: Repeat Paket 4: Repeat Paket 5: Catatan: 26 nores 18 cek harga 10 tanya tanya 5 isi data 1 ngga jadi
A7: 45975.538 | B7: Exception: De parameters (String,String,String) komen niet overeen met de methodehandtekening voor Utilities.formatDate.
A8: 45975.538 | B8: LAPORAN SAVED: false
A9: 45976.387 | B9: Trigger: /start
A10: 45976.388
A11: 45976.389
A12: 45976.389
A13: 45976.389
A14: 45976.398
A15: 45976.407
A16: 45976.415
A17: 45976.422
A18: 45976.466 | B18: Trigger: /start
A19: 45976.468 | B19: Trigger: #inputorder# Data Pesanan Jasa Iklan UMKM Data Pemesan ---- Tanggal: 15-Nov-2025 Nama: Para Ir. Berpengalaman Nama Usaha: PT. Panorama Jaya Labana Jenis Usaha: Usaha Jasa Konstruksi spesialist bangun / renovasi Rumah No Whatsapp Bisnis: 628122102657 Alamat usaha: Bandung Deskripsi produk/jasa: AHLI BANGUNAN KAMI YANG BERGERAK DIBIDANG JASA PROPERTY DAN KONTRUKSI JASA BANGUN RUMAH, RENOVASI PROFESIONAL , INT,ERIOR DESN ANDA BUTUH RENOVASI RUMAH ATAU BANGUN RUMAH?? DENGAN DESAIN GAMBAR SERTA RencanaAnggaran Biaya (RAB). KAMI SIAP MEMBANTU ANDA!!! Jasa Kontraktor, Konstruksi, Bangun Baru Bangunan,Rumah tinggal, kos-kosan, kantor, tempat usaha, ruko, cafe,rumah butik, rumah kantor, rumah gudang/pabrik dll. Free: – Konsultasi arsitek & sipil bangunan – Desain arsitektur 3D – Gambar kerja lengkap – Sket denah ruangan dan interior – RAB Harga berdasarkan RAB bisa disesuaikan budget berdasar rencana gambar setelah survey lokasi dan atau konsultasi Perkiraan: Rumah sederhana: 3,2 Jt/m2 s.d. 3.5 Jt/m2 Rumah mewah (1 Lantai): 3.6 Jt/m2 s.d. 4,0 Jt/m2 Rumah mewah (2 Lantai): 4,2 Jt/m2 s.d. 5,0 Jt/m2 Rumah exclusive: lebih dari 5,0 Jt/m2 Juga melayani: – Renovasi dan Perbaikan bangunan – Jasa Desain Eksterior (Gambar Kerja Bangunan), Gambar Syarat IMB, Gambar 3D, Hitung Struktur, RAB | Perencanaan – Jasa Desain Interior dan Pembuatan Custom Furniture – Jasa penambahan ruang / pengalihan ruang seperti garasi menjadi butik, rumah menjadi rumah butik KONSULTASI dan SURVEY LOKASI GRATISS masalah harga NEGOTIABLE Data Target Iklan ---- Lokasi: Bandung,Jawa barat, seluruh Indonesia Usia: 17-55 Jenis kelamin:SU Data iklan ---- Durasi:14 Data Pembayaran ---- Total Bayar: 500000 Cs: Yuni Status: Perpanjang
A20: 45976.468 | B20: Memeriksa nomor WA setelah dibersihkan: '628122102657' (Tipe: string)
A21: 45976.468 | B21: Hasil validasi: Valid
A22: 45976.468 | B22: ORDER SAVED: ORD-1512
A23: 45976.478 | B23: Trigger: #inputorder# Data Pesanan Jasa Iklan UMKM Data Pemesan ---- Tanggal: 14-Nov-2025 Nama: Ali Imron Nama Usaha: Sinar Gorden Interior Jenis Usaha: Gorden, wallpaper, kaca film, flooring No Whatsapp Bisnis: 628156626447 Alamat: Jl Kol HR Hadijanto Banaran Sekaran Gunungpati Semarang Durasi: 14 Deskripsi produk/jasa: *Keunggulan usaha (wajib):*Gorden ukuran custom, gratis survey, konsultasi, pemasangan *keunikan usaha (wajib):* Banyak pilihan jenis motif dan warna. Kualitas bagus, harga bersahabat Promo: -Roller Blinds Harga mulai Rp.400.000 permeter persegi -Vertical Blinds Harga mulai Rp.300.000 permeter persegi -Venetian Blinds Mulai harga Rp.300.000 permeter persegi -Paket Super A : Jendela Lebar 130 - 160 cm Spesifikasi : - Gorden Blackout (L 200 cm T maks 300 cm) x 2 pcs - Vitrase L 320 cm T 300 cm - Roulet (pipa) tebal P 160 cm - Rel kotak tebal P 160 cm - Tali dan Gantungan - Free antar dan pasang ~Rp.1.300.000~ Rp.1.200.000 Gratis Survey Area Semarang dan sekitarnya Data Target Iklan ---- Lokasi: Semarang, Ungaran Usia: 25-60 th Jenis kelamin: laki-laki dan perempuan Data Pembayaran ---- Total Bayar: 550000 Cs: Isna Status: Baru
A24: 45976.478 | B24: Memeriksa nomor WA setelah dibersihkan: '628156626447' (Tipe: string)
A25: 45976.478 | B25: Hasil validasi: Valid
A26: 45976.478 | B26: ORDER SAVED: ORD-1513
A27: 45976.478 | B27: Trigger: #inputorder# Data Pesanan Jasa Iklan UMKM Data Pemesan ---- Tanggal: 14-Nov-2025 Nama: Sumini Mitro Suwarno Nama Usaha: Rumah Sehat Tradisional Holistic "AZELA" Jenis Usaha: Kesehatan Tradisional No Whatsapp Bisnis: 6281316122975 Alamat: Ruko Megalegenda 2 Blok D3 no 15 Batam Center Durasi: 7 Deskripsi produk/jasa: Menangani patah tulang, treatment perut + masker, treatment pasca melahirkan, lulur/body scrub, pijat tradisional, perawatan stroke, bekam tanduk, bekam api, hijamah dll Data Target Iklan ---- Lokasi: Batam Usia: semua umur Jenis kelamin: laki-laki dan perempuan Data Pembayaran ---- Total Bayar: 297000 Cs: Isna Status: Perpanjang
A28: 45976.478 | B28: Memeriksa nomor WA setelah dibersihkan: '6281316122975' (Tipe: string)
A29: 45976.478 | B29: Hasil validasi: Valid
... A65: 45976.804 | B65: ERROR: Exception: The data you entered in cell U1524 violates the data validation rules set on this cell. Please enter one of the following values: Isna, Devi, Yuni, Rudi, Jeff, Ilham, Rokhma, Maya, Tika.
A66: 45977.231
A67: 45977.231
A68: 45977.232
A69: 45977.232
A70: 45977.24
A71: 45977.245
A72: 45977.252
A73: 45977.258
A74: 45977.291 | B74: Trigger: #inputlaporan# Laporan CS Jasa Iklan UMKM ------- Nama CS: Yuni Tanggal: 15-Nov-2025 Leads: Jumlah Closing: 1 Paket 1: Paket 2: Paket 3: Paket 4: Paket 5: Repeat Paket 1: Repeat Paket 2: Repeat Paket 3: 1 Repeat Paket 4: Repeat Paket 5: Catatan:
A75: 45977.291 | B75: Exception: De parameters (String,String,String) komen niet overeen met de methodehandtekening voor Utilities.formatDate.
A76: 45977.291 | B76: LAPORAN SAVED: false
A77: 45978.232 | B77: Trigger: #inputorder# Data Pesanan Jasa Iklan UMKM Data Pemesan ---- Tanggal: 16-Nov-2025 Nama: Drs I Wayan Sudana MSI Nama Usaha: Institut Olah Pikir Nusantara Jenis Usaha: Workshop dan Terapi Hipnoterapi Klinis No Whatsapp Bisnis: 6281775758999 Alamat: Jomblang legok tanah putih RT 03 RW 02 No 8 kelurahan Jomblang kecamatan Candisari kota Semarang 50256 Durasi: 10 Deskripsi produk/jasa: Pelatihan Hypnoterapi Keunggulan Usaha: legal terpercaya mendidik calon Hypnoterapi klinis profesional ,kompeten,berdaya saing tinggi gelar MCH prestisius bergengsi Keunikan Usaha: Dibimbing trainer berpendidikan tinggi dan berpengalaman sebagai praktisi dan trainer. materi program lengkap teratur sistematis Promo: Dua hari program fundamental Hipnoterapis klinis Data Target Iklan ---- Lokasi: Semarang dan Sekitarnya Usia: 28-65 th Jenis kelamin: laki-laki dan perempuan Data Pembayaran ---- Total Bayar: 375000 Cs: Isna Status: Baru
A78: 45978.232 | B78: Memeriksa nomor WA setelah dibersihkan: '6281775758999' (Tipe: string)
A79: 45978.232 | B79: Hasil validasi: Valid
A80: 45978.232 | B80: ORDER SAVED: ORD-1524
A81: 45978.233 | B81: Trigger: #inputorder# Data Pesanan Jasa Iklan UMKM Data Pemesan ---- Tanggal: 16-Nov-2025 Nama: Ninis Nama Usaha: Samira Travel Jenis Usaha: Travel Umroh No Whatsapp Bisnis: 6281216704496 Alamat: Jalan Padmosusastro 74 A Surabaya Durasi: 10 Deskripsi produk/jasa: keunggulan Usaha: Legal, Amanah, Berpengalaman melayani ribuan jamaah, muthawwif berilmu, sabar dan profesional, Terpercaya, Fasilitas nyaman, melayani dengan hati Keunikan Usaha: Harga Transparan dan bisa dicicil Tanpa riba Promo: Gratis Paspor Trus nanti saya ada tambahan "free kereta cepat bulan november dan desember 2025" Data Target Iklan ---- Lokasi: Surabaya, Sidoarjo, Gresik Usia: 21thn keatas, keluarga muda, lansia Jenis kelamin: Laki-laki Dan Perempuan Data Pembayaran ---- Total Bayar: 375000 Cs: Isna Status: Perpanjang
A82: 45978.233 | B82: Memeriksa nomor WA setelah dibersihkan: '6281216704496' (Tipe: string)
A83: 45978.233 | B83: Hasil validasi: Valid
A84: 45978.233 | B84: ORDER SAVED: ORD-1525
A85: 45978.233 | B85: Trigger: #inputorder# Data Pesanan Jasa Iklan UMKM Data Pemesan ---- Tanggal: 16-Nov-2025 Nama: Usman Nama Usaha: Usman Cleaning Jenis Usaha: Deep Cleaning Panggilan No Whatsapp Bisnis: 6288971067899 Alamat: Cihaur RT 03 RW 02 Desa Sukamulya kecamatan Rancaekek kabupaten Bandung Durasi: 7 Deskripsi produk/jasa: Keunggulan Usaha: Hasil cleaning Maksimal Keunikan Usaha: Hasil Cleaning Maksimal Data Target Iklan ---- Lokasi: Rancaekek, Cinunuk, Cileunyi Usia: 20 th keatas Jenis kelamin: laki-laki dan perempuan Data Pembayaran ---- Total Bayar: 297000 Cs: Isna Status: Baru
... A98: 45978.245 | B98: LAPORAN SAVED: false
A99: 45978.364
A100: 45978.364
A101: 45978.364
A102: 45978.364
A103: 45978.364
A104: 45978.364
A105: 45978.364
A106: 45978.63 | B106: Trigger: #inputlaporan# Laporan CS Jasa Iklan UMKM ------- Nama CS: Yuni Tanggal: 16-Nov-2025 Leads: Jumlah Closing: 1 Paket 1: Paket 2: Paket 3: Paket 4: Paket 5: Repeat Paket 1: Repeat Paket 2: Repeat Paket 3: Repeat Paket 4: Repeat Paket 5: 1 Catatan:
A107: 45978.63 | B107: Exception: De parameters (String,String,String) komen niet overeen met de methodehandtekening voor Utilities.formatDate.
A108: 45978.63 | B108: LAPORAN SAVED: false
A109: 45978.632 | B109: Trigger: #inputorder# Data Pesanan Jasa Iklan UMKM Data Pemesan Tanggal:16-Nov-2025 Nama: Rustoyo Nama Usaha: BANDUNG AUTO FILM Jenis Usaha: KACA FILM No Whatsapp Bisnis:6287790276733 Alamat usaha: jln. Terusan Jakarta no. 360 , suka miskin , kec Arcamanik , Bandung , Jawa Barat , 40125 Deskripsi produk/jasa: Pusat kaca film terlengkap & berkualitas di bandung By Produc : - LLUMAR SUPERBLACK PREMIUM - SOLARGARD BLACKPHANTOM PREMIIUM - 3M AUTO FILM - ICEBERG NIGHTVISION - AC PREMIUM LUXURY - SOLAR MASK - SUN PROTEC Tips memilih kaca film , agar tidak salah pilih : 1. Pilihlah kaca film yang merk bahan terkenal , berkualitas , original 2. Pilihlah bahan yang IRR ( Tolak panas) & UVR ( Tolak sinar ultra violet ) nya tinggi , supaya tidak terlalu panas ke ruangan kabin 3. Sesuaikan tingkat kegelapannya ( 20% , 40% , 60% , 80% ) 4. Pilihlah yng bergaransi 5 - 7 tahun 5. Pilihlah pandangan yang gelap dariluar , tetapi terang dari dalam ( night vision ) 6. Pilihlah teknisi yng profesional & berpengalaman supaya hasil pemasangan memuaskan *Keunggulan usaha (wajib):* *keunikan usaha (wajib):* Promo: Diskon 10% Data Target Iklan Lokasi: Bandung kota Usia:18-65 Jenis kelamin:semua Durasi:30 Data Pembayaran ---- Total Bayar: 1000000 Cs: Yuni Status: Perpanjang
A110: 45978.632 | B110: Memeriksa nomor WA setelah dibersihkan: '6287790276733' (Tipe: string)
A111: 45978.632 | B111: Hasil validasi: Valid
A112: 45978.632 | B112: ORDER SAVED: ORD-1528
A113: 45978.632 | B113: Trigger: #inputorder# Data Pesanan Jasa Iklan UMKM Data Pemesan Tanggal:17-Nov-2025 Nama:Yasmin Nama Usaha: Yasmine health staycation Jenis Usaha: health staycation No Whatsapp Bisnis:6281288965454 Alamat usaha: Deskripsi produk/jasa: 3 days pain free on the weekend. Jumat Sabtu Minggu *Keunggulan usaha (wajib):* Keunggulan usaha 1 Tekhnologi kedokteran intervensi nyeri dari Jerman dan Rusia >> sekali datang nyeri hilang ...sekali talaksana nyeri reda .satu satunya di Jabodetabek 2 merangsang regenerasi perbaikan jaringan yang rusak penyebab nyeri kronis berkepanjangan.BUKAN HANYA SEKEDAR TARGET BEBAS NYERI . 3.TAK PERLU OPERASI .CUKUP 30 MENIT ..PERBAIKAN NYERI LANGSUNG DAPAT DIRASAKAN DI KEDATANGAN KE 1 4.PROSEDUR TANPA PERLU BIUS UMUM DAN PASIEN SADAR ,RASA SAKIT SANGAT MINIMAL 5.PENGALAMAN 15 TAHUN .RIBUAN PASIEN NYERI LUTUT DAN NYERI SARAF KEJEPIT TELAH DITANGANI 6.MURAH , BERKUALITAS INTERNASIONAL 7.PASIEN SELESAI TINDAKAN LANGSUNG PULANG DAN BERAKTIVITAS 8 .TIDAK ADA PANTANGAN DALAM PROSES TINDAKAN *keunikan usaha(wajib):* Keunikan usaha 1 Tekhnologi stimulasi ke aktivasi stem Cell endogen ( alamiah tubuh pasien ) 2.satu satunya di Jabodetabek 3 tak perlu masuk ke kamar operasi 4.cukup rawat jalan 5 .hasil langsung dirasakan 95 persen di kedatangan ke 1 6.untik nyeri lutut dan nyeri saraf kejepit rerata hanya 5 kali kedatangan saja setiap sebulan sekali Promo: Data Target Iklan Lokasi: Jabodetabek Usia:50keatas Jenis kelamin: semua Durasi:5 Data Pembayaran ---- Total Bayar: 197000 Cs: Yuni Status: Perpanjang
A114: 45978.632 | B114: Memeriksa nomor WA setelah dibersihkan: '6281288965454' (Tipe: string)
A115: 45978.632 | B115: Hasil validasi: Valid
A116: 45978.632 | B116: ORDER SAVED: ORD-1529
A117: 45978.678 | B117: Trigger: #inputorder# Data Pesanan Jasa Iklan UMKM Data Pemesan Tanggal:17-Nov-2025 Nama: windu Nama Usaha: PT FREMONT GREEN VISION Jenis Usaha: jasa arsitektur pengurusan PPKPR , SLF dan PBG No Whatsapp Bisnis:6285270194027 Alamat usaha: Mansyur USU Regency,jl. SMTK 6 blok A no. 1 Padang bulan selayang 1,Medan selayang Deskripsi produk/jasa: jasa arsitektur, interior ,pengurusan PPKPR , FS,SLF dan PBG Pengurusan PBG Mulai dari 5 Jutaan saja. *Keunggulan usaha (wajib):Tenaga Ahli Berpengalaman, Sudah Banyak Menangani Pengurusan Ijin PBG dan SLF* *keunikan usaha (wajib):* Promo: Data Target Iklan Lokasi: Pekanbaru dan Sumatra Utara Usia: 25-55 Jenis kelamin: semua Durasi:10 Data Pembayaran ---- Total Bayar:375000 Cs: Yuni Status: Perpanjang
... A179: 45978.786 | B179: ORDER SAVED: ORD-1537
A180: 45979.002
A181: 45979.002
A182: 45979.003
A183: 45979.003
A184: 45979.003
A185: 45979.004
A186: 45979.004
A187: 45979.14 | B187: ERROR: TypeError: Cannot read properties of undefined (reading 'contents')
A188: 45979.14 | B188: ERROR: TypeError: Cannot read properties of undefined (reading 'contents')
A189: 45979.141 | B189: Trigger: #inputorder# Data Pesanan Jasa Iklan UMKM Data Pemesan ---- Tanggal: 15-Nov-2025 Nama: Imam Asri Gorden Nama Usaha: Grosir Gordyn Jenis Usaha: Gordyn No Whatsapp Bisnis: 628156563072 Alamat: toko imam asri gordyn Durasi: 24 Deskripsi produk/jasa: produk..vertical horizontal blinds..Roller blinds Keunggulan: harga murah berkualitas Keunikan: pengukuran dan pemasangan gratis Data Target Iklan ---- Lokasi: Pekalongan, Batang, Pemalang, Kajen dan Sekitarnya Usia: 25 th keatas Jenis kelamin: perempuan Data Pembayaran ---- Total Bayar: 550000 Cs: Isna Status: Baru
A190: 45979.141 | B190: Memeriksa nomor WA setelah dibersihkan: '628156563072' (Tipe: string)
A191: 45979.141 | B191: Hasil validasi: Valid
A192: 45979.141 | B192: ORDER SAVED: ORD-1537
A193: 45979.143 | B193: Trigger: #inputorder# Nama: Budi Nama Usaha: Toko Sukses Jenis Usaha: Laundry No Whatsapp Bisnis: 6281234567890 Deskripsi Produk Jasa: Cuci kilat Lokasi: Bekasi Usia: 30 Jenis Kelamin: Laki-laki Durasi: 7 Mulai: 2025-11-17 Selesai: 2025-11-24 Catatan: Test debug Total Bayar: 200000 CS: Rina
A194: 45979.143 | B194: Memeriksa nomor WA setelah dibersihkan: '6281234567890' (Tipe: string)
A195: 45979.143 | B195: Hasil validasi: Valid
A196: 45979.143 | B196: ERROR: Exception: Request failed for https://api.telegram.org returned code 400. Truncated server response: {"ok":false,"error_code":400,"description":"Bad Request: chat not found"} (use muteHttpExceptions option to examine full response)
A197: 45979.144 | B197: Trigger: #inputorder# Status: Baru Nama: Budi Nama Usaha: Toko Sukses Jenis Usaha: Laundry No Whatsapp Bisnis: 6281234567890 Deskripsi Produk Jasa: Cuci kilat Lokasi: Bekasi Usia: 30 Jenis Kelamin: Laki-laki Durasi: 7 Mulai: 2025-11-17 Selesai: 2025-11-24 Catatan: Test debug Total Bayar: 200000 CS: Rina
A198: 45979.144 | B198: Memeriksa nomor WA setelah dibersihkan: '6281234567890' (Tipe: string)
... A319: 45979.234 | B319: Hasil validasi: Valid
A320: 45979.238
A321: 45979.24 | B321: Trigger: #inputorder# Status: Baru Nama: Budi Radman Tanggal: 17-Nov-2025 Nama Usaha: Toko Sukses Jenis Usaha: Laundry Sukses No Whatsapp Bisnis: 6281234567890 Deskripsi Produk Jasa: Cuci kilat sukses ya Lokasi: Bekasi Usia: 45 Jenis Kelamin: Laki-laki - Perempuan - Pria Durasi: 10 Mulai: 2025-11-17 Selesai: 2025-11-24 Catatan: Test debug ok kak Total Bayar: 1970000 CS: Rina Status Pembayaran: DP
A322: 45979.241 | B322: Memeriksa nomor WA setelah dibersihkan: '6281234567890' (Tipe: string)
A323: 45979.241 | B323: Hasil validasi: Valid
A324: 45979.246
A325: 45979.254 | B325: Trigger: #inputorder# Status: Baru Nama: Budi Radman Tanggal: 17-Nov-2025 Nama Usaha: Toko Sukses Jenis Usaha: Laundry Sukses No Whatsapp Bisnis: 6281234567890 Deskripsi Produk Jasa: Cuci kilat sukses ya Lokasi: Bekasi Usia: 45 Jenis Kelamin: Laki-laki - Perempuan - Pria Durasi: 10 Mulai: 2025-11-17 Selesai: 2025-11-24 Catatan: Test debug ok kak Total Bayar: 1970000 CS: Rina Status Pembayaran: DP
A326: 45979.254 | B326: Memeriksa nomor WA setelah dibersihkan: '6281234567890' (Tipe: string)
A327: 45979.254 | B327: Hasil validasi: Valid
A328: 45979.255 | B328: Trigger: #inputorder# Status: Baru Nama: Budi Radman Tanggal: 17-Nov-2025 Nama Usaha: Toko Sukses Jenis Usaha: Laundry Sukses No Whatsapp Bisnis: 6281234567890 Deskripsi Produk Jasa: Cuci kilat sukses ya Lokasi: Bekasi Usia: 45 Jenis Kelamin: Laki-laki - Perempuan - Pria Durasi: 7 Mulai: 2025-11-17 Selesai: 2025-11-24 Catatan: Test debug ok kak Total Bayar: 297000 CS: Rina Status Pembayaran: DP
...

Sheet Performa Iklan Klien
A1: AkunIklanId | B1: NamaAkun | C1: KampanyeId | D1: Nama Usaha | E1: Whatsapp | F1: Tanggal | G1: Reach | H1: CPM | I1: LinkKlik | J1: Spend | K1: KlikWA | L1: VideoView | M1: Komentar | N1: Nama Kampanye | O1: Column 1
A2: 759724529202804 | B2: R11 | C2: 120227433380380200 | D2: Sunat Pangkep Avacare | E2: 6285255435848 | F2: 45809 | G2: 111 | H2: 6973.2143 | I2: 0 | J2: 781 | K2: 0 | L2: 41 | M2: 0 | N2: ON-Sunat Pangkep Avacare-02062025+7-6285255435848-ilham
A3: 759724529202804 | B3: R11 | C3: 120227432781140200 | D3: PUTRA MANDIRI HARMONIKA | E3: 6281331854948 | F3: 45809 | G3: 114 | H3: 11786.325 | I3: 0 | J3: 1379 | K3: 0 | L3: 37 | M3: 0 | N3: ON-PUTRA MANDIRI HARMONIKA-02062025+10-6281331854948-ilham
A4: 759724529202804 | B4: R11 | C4: 120227429269270200 | D4: Nyaraa Salon | E4: 6282348365032 | F4: 45809 | G4: 105 | H4: 11055.046 | I4: 4 | J4: 1205 | K4: 0 | L4: 29 | M4: 0 | N4: ON-Nyaraa Salon-02062025+5-6282348365032-ilham
A5: 759724529202804 | B5: R11 | C5: 120227423725240200 | D5: PT MAKMUR JAYA ZEBUA | E5: 6285220903499 | F5: 45809 | G5: 569 | H5: 17272.595 | I5: 23 | J5: 11849 | K5: 6 | L5: 278 | M5: 0 | N5: ON-PT MAKMUR JAYA ZEBUA-01062025+5-6285220903499-ilham
A6: 759724529202804 | B6: R11 | C6: 120227403909070200 | D6: khairan Wedding, Hair and Beauty | F6: 45809 | G6: 11726 | H6: 1260.1054 | I6: 19 | J6: 15057 | K6: 0 | L6: 1423 | M6: 0 | N6: ON-khairan Wedding, Hair and Beauty-01062025+6285220903499-ilham
A7: 759724529202804 | B7: R11 | C7: 120227400653870200 | D7: ISAL SALON | E7: 6285240684331 | F7: 45809 | G7: 1006 | H7: 12147.126 | I7: 22 | J7: 15852 | K7: 3 | L7: 228 | M7: 0 | N7: ON-ISAL SALON-01062025+5-6285240684331-ilham
A8: 759724529202804 | B8: R11 | C8: 120227397964810200 | D8: Neng Ay salon | E8: 6282154483973 | F8: 45809 | G8: 1510 | H8: 7866.3814 | I8: 30 | J8: 16543 | K8: 4 | L8: 418 | M8: 0 | N8: ON-Neng Ay salon-01062025+10-6282154483973-ilham
A9: 759724529202804 | B9: R11 | C9: 120227358608350200 | D9: Artha Jaya | E9: 6285757057088 | F9: 45809 | G9: 1031 | H9: 10509.921 | I9: 46 | J9: 15891 | K9: 2 | L9: 1 | M9: 1 | N9: ON-Artha Jaya-30052025+30-6285757057088
A10: 759724529202804 | B10: R11 | C10: 120227357012290200 | D10: Devy Kikim Salon & Wedding Organizer | E10: 6282136666049 | F10: 45809 | G10: 955 | H10: 14038.324 | I10: 23 | J10: 15751 | K10: 4 | L10: 275 | M10: 0 | N10: ON-Devy Kikim Salon & Wedding Organizer-31052025+5-6282136666049-ilham
A11: 759724529202804 | B11: R11 | C11: 120227286789550200 | D11: Eny M&Y mahkota salon & yara wedding | E11: 6282159148587 | F11: 45809 | G11: 713 | H11: 16799.534 | I11: 12 | J11: 14414 | K11: 1 | L11: 280 | M11: 0 | N11: ON-Eny M&Y mahkota salon & yara wedding-29052025+5-6282159148587-ilham
A12: 759724529202804 | B12: R11 | C12: 120227218075240200 | D12: AJP.ADI JAYA PLAFON | F12: 45809 | G12: 2 | H12: 12500 | I12: 0 | J12: 25 | K12: 0 | L12: 1 | M12: 0 | N12: ON-AJP.ADI JAYA PLAFON
A13: 759724529202804 | B13: R11 | C13: 120227217218600200 | D13: Eny Laundry karpet & Pakaian | E13: 6283129638348 | F13: 45809 | G13: 31 | H13: 11903.226 | I13: 0 | J13: 369 | K13: 0 | L13: 11 | M13: 0 | N13: ON-Eny Laundry karpet & Pakaian -28052025+5-6283129638348-ilham
A14: 759724529202804 | B14: R11 | C14: 120227215523910200 | D14: zL beauty homecare | E14: 6281549409606 | F14: 45809 | G14: 201 | H14: 22356.164 | I14: 3 | J14: 4896 | K14: 0 | L14: 62 | M14: 0 | N14: ON-zL beauty homecare -27052025+5-6281549409606-ilham
A15: 174904221976312 | B15: R10 | C15: 120225732846460694 | D15: SMA Madina | E15: 6281348555887 | F15: 45809 | G15: 1273 | H15: 8368.0104 | I15: 51 | J15: 12870 | K15: 5 | L15: 498 | M15: 1 | N15: ON-SMA Madina-29052025+20-6281348555887
A16: 174904221976312 | B16: R10 | C16: 120225732456000694 | D16: Aurora Teknik | E16: 6285376667233 | F16: 45809 | G16: 1133 | H16: 9910.7143 | I16: 27 | J16: 13320 | K16: 5 | L16: 402 | M16: 2 | N16: ON-Aurora Teknik-29052025+5-6285376667233
A17: 174904221976312 | B17: R10 | C17: 120225711165240694 | D17: Bang Banten | E17: 6282172291579 | F17: 45809 | G17: 897 | H17: 12435.455 | I17: 44 | J17: 13679 | K17: 6 | L17: 538 | M17: 0 | N17: ON-Bang Banten-31042025+10-6282172291579-Rudi
A18: 174904221976312 | B18: R10 | C18: 120225575002440694 | D18: Toko Emas Sembiring | E18: 6281263113266 | F18: 45809 | G18: 1507 | H18: 8065.6214 | I18: 60 | J18: 13889 | K18: 5 | L18: 746 | M18: 0 | N18: ON-Toko Emas Sembiring-15052025+30-6281263113266-Ilham - 2 - RCVR
A19: 174904221976312 | B19: R10 | C19: 120225346217950694 | D19: Verrocosta | E19: 6282226594414 | F19: 45809 | G19: 3350 | H19: 3210.4867 | I19: 146 | J19: 12797 | K19: 21 | L19: 1001 | M19: 4 | N19: ON-Verrocosta-23052025+10-6282226594414-ilham - Copy
A20: 174904221976312 | B20: R10 | C20: 120225230850710694 | D20: CV MZ banyu agung | E20: 62882001677470 | F20: 45809 | G20: 538 | H20: 20453.507 | I20: 17 | J20: 12538 | K20: 3 | L20: 226 | M20: 1 | N20: ON-CV MZ banyu agung-29052025+5-62882001677470-ilham
A21: 174904221976312 | B21: R10 | C21: 120225065069670694 | D21: LK spa n beauty | E21: 6282341426767 | F21: 45809 | G21: 354 | H21: 22997.674 | I21: 18 | J21: 9889 | K21: 5 | L21: 89 | M21: 0 | N21: ON-LK spa n beauty-19052025+14-6282341426767-ilham
A22: 759724529202804 | B22: R11 | C22: 120227459128820200 | D22: Karya Tukang | E22: 628872305953 | F22: 45810 | G22: 273 | H22: 39841.935 | I22: 3 | J22: 12351 | K22: 0 | L22: 77 | M22: 0 | N22: ON-Karya Tukang-25052025+5-628872305953-ilham - Copy
A23: 759724529202804 | B23: R11 | C23: 120227433380380200 | D23: Sunat Pangkep Avacare | E23: 6285255435848 | F23: 45810 | G23: 1046 | H23: 10273.894 | I23: 12 | J23: 14404 | K23: 3 | L23: 528 | M23: 0 | N23: ON-Sunat Pangkep Avacare-02062025+7-6285255435848-ilham
A24: 759724529202804 | B24: R11 | C24: 120227432781140200 | D24: PUTRA MANDIRI HARMONIKA | E24: 6281331854948 | F24: 45810 | G24: 696 | H24: 14277.19 | I24: 25 | J24: 14834 | K24: 3 | L24: 370 | M24: 0 | N24: ON-PUTRA MANDIRI HARMONIKA-02062025+10-6281331854948-ilham
... A26: 759724529202804 | B26: R11 | C26: 120227423725240200 | D26: PT MAKMUR JAYA ZEBUA | E26: 6285220903499 | F26: 45810 | G26: 754 | H26: 14830.439 | I26: 24 | J26: 14519 | K26: 1 | L26: 329 | M26: 0 | N26: ON-PT MAKMUR JAYA ZEBUA-01062025+5-6285220903499-ilham
A27: 759724529202804 | B27: R11 | C27: 120227403909070200 | D27: khairan Wedding, Hair and Beauty | F27: 45810 | G27: 11368 | H27: 1225.982 | I27: 16 | J27: 14420 | K27: 0 | L27: 1175 | M27: 0 | N27: ON-khairan Wedding, Hair and Beauty-01062025+6285220903499-ilham
A28: 759724529202804 | B28: R11 | C28: 120227400653870200 | D28: ISAL SALON | E28: 6285240684331 | F28: 45810 | G28: 944 | H28: 13401.603 | I28: 31 | J28: 15050 | K28: 6 | L28: 201 | M28: 3 | N28: ON-ISAL SALON-01062025+5-6285240684331-ilham
A29: 759724529202804 | B29: R11 | C29: 120227397964810200 | D29: Neng Ay salon | E29: 6282154483973 | F29: 45810 | G29: 1610 | H29: 7142.3407 | I29: 33 | J29: 15806 | K29: 3 | L29: 421 | M29: 1 | N29: ON-Neng Ay salon-01062025+10-6282154483973-ilham
A30: 759724529202804 | B30: R11 | C30: 120227358608350200 | D30: Artha Jaya | E30: 6285757057088 | F30: 45810 | G30: 1295 | H30: 8111.6585 | I30: 48 | J30: 14820 | K30: 6 | L30: 0 | M30: 0 | N30: ON-Artha Jaya-30052025+30-6285757057088
A31: 759724529202804 | B31: R11 | C31: 120227357012290200 | D31: Devy Kikim Salon & Wedding Organizer | E31: 6282136666049 | F31: 45810 | G31: 726 | H31: 18214.452 | I31: 18 | J31: 15628 | K31: 2 | L31: 239 | M31: 0 | N31: ON-Devy Kikim Salon & Wedding Organizer-31052025+5-6282136666049-ilham
A32: 759724529202804 | B32: R11 | C32: 120227286789550200 | D32: Eny M&Y mahkota salon & yara wedding | E32: 6282159148587 | F32: 45810 | G32: 1311 | H32: 8927.4093 | I32: 13 | J32: 14266 | K32: 0 | L32: 428 | M32: 0 | N32: ON-Eny M&Y mahkota salon & yara wedding-29052025+5-6282159148587-ilham
A33: 759724529202804 | B33: R11 | C33: 120227218075240200 | D33: AJP.ADI JAYA PLAFON | F33: 45810 | G33: 716 | H33: 17576.651 | I33: 20 | J33: 14905 | K33: 2 | L33: 190 | M33: 0 | N33: ON-AJP.ADI JAYA PLAFON
A34: 174904221976312 | B34: R10 | C34: 120225943524550694 | D34: Dapur Florist | E34: 6281399998259 | F34: 45810 | G34: 220 | H34: 10638.393 | I34: 6 | J34: 2383 | K34: 0 | L34: 92 | M34: 0 | N34: ON-Dapur Florist-03062025+10-6281399998259-ilham
A35: 174904221976312 | B35: R10 | C35: 120225924609850694 | D35: Amanah Interior | E35: 6282183184641 | F35: 45810 | G35: 1309 | H35: 8815.0773 | I35: 36 | J35: 13681 | K35: 3 | L35: 387 | M35: 0 | N35: ON- Amanah Interior-21052025+5-6282183184641 -ilham - NEW
A36: 174904221976312 | B36: R10 | C36: 120225732846460694 | D36: SMA Madina | E36: 6281348555887 | F36: 45810 | G36: 1360 | H36: 7290.4509 | I36: 31 | J36: 10994 | K36: 1 | L36: 457 | M36: 1 | N36: ON-SMA Madina-29052025+20-6281348555887
A37: 174904221976312 | B37: R10 | C37: 120225732456000694 | D37: Aurora Teknik | E37: 6285376667233 | F37: 45810 | G37: 1284 | H37: 9392.2652 | I37: 20 | J37: 13600 | K37: 3 | L37: 386 | M37: 0 | N37: ON-Aurora Teknik-29052025+5-6285376667233
A38: 174904221976312 | B38: R10 | C38: 120225711165240694 | D38: Bang Banten | E38: 6282172291579 | F38: 45810 | G38: 1066 | H38: 10798.038 | I38: 40 | J38: 13206 | K38: 6 | L38: 611 | M38: 0 | N38: ON-Bang Banten-31042025+10-6282172291579-Rudi
A39: 174904221976312 | B39: R10 | C39: 120225575002440694 | D39: Toko Emas Sembiring | E39: 6281263113266 | F39: 45810 | G39: 1205 | H39: 8665.6739 | I39: 45 | J39: 11638 | K39: 4 | L39: 553 | M39: 0 | N39: ON-Toko Emas Sembiring-15052025+30-6281263113266-Ilham - 2 - RCVR
A40: 174904221976312 | B40: R10 | C40: 120225366947220694 | D40: LPK ERBANSA AKADEMI | E40: 6282226594414 | F40: 45810 | G40: 1044 | H40: 12229.623 | I40: 29 | J40: 13954 | K40: 1 | L40: 262 | M40: 0 | N40: ON-LPK ERBANSA AKADEMI-25052025+5-6282226594414-ilham - Copy
A41: 174904221976312 | B41: R10 | C41: 120225346217950694 | D41: Verrocosta | E41: 6282226594414 | F41: 45810 | G41: 716 | H41: 2914.8649 | I41: 35 | J41: 2157 | K41: 6 | L41: 165 | M41: 0 | N41: ON-Verrocosta-23052025+10-6282226594414-ilham - Copy
A42: 174904221976312 | B42: R10 | C42: 120225230850710694 | D42: CV MZ banyu agung | E42: 62882001677470 | F42: 45810 | G42: 601 | H42: 19614.265 | I42: 15 | J42: 13475 | K42: 0 | L42: 247 | M42: 0 | N42: ON-CV MZ banyu agung-29052025+5-62882001677470-ilham
A43: 174904221976312 | B43: R10 | C43: 120225065069670694 | D43: LK spa n beauty | E43: 6282341426767 | F43: 45810 | G43: 389 | H43: 25661.702 | I43: 11 | J43: 12061 | K43: 1 | L43: 112 | M43: 0 | N43: ON-LK spa n beauty-19052025+14-6282341426767-ilham
A44: 174904221976312 | B44: R10 | C44: 120224822861740694 | D44: Daihatsu Mamuju | E44: 6282347206488 | F44: 45810 | G44: 1301 | H44: 8177.8334 | I44: 48 | J44: 13060 | K44: 9 | L44: 643 | M44: 0 | N44: ON-Daihatsu Mamuju-02062025+5-6282347206488-Ilham
A45: 759724529202804 | B45: R11 | C45: 120227526331870200 | D45: Sahabat AC | E45: 6285737244570 | F45: 45811 | G45: 668 | H45: 15269.388 | I45: 15 | J45: 11223 | K45: 1 | L45: 203 | M45: 0 | N45: ON-Sahabat AC-03062025+5-6285737244570
... A50: 759724529202804 | B50: R11 | C50: 120227423725240200 | D50: PT MAKMUR JAYA ZEBUA | E50: 6285220903499 | F50: 45811 | G50: 1167 | H50: 11761.73 | I50: 31 | J50: 16043 | K50: 3 | L50: 473 | M50: 2 | N50: ON-PT MAKMUR JAYA ZEBUA-01062025+5-6285220903499-ilham
A51: 759724529202804 | B51: R11 | C51: 120227403909070200 | D51: khairan Wedding, Hair and Beauty | F51: 45811 | G51: 11138 | H51: 1265.5584 | I51: 3 | J51: 14540 | K51: 0 | L51: 1114 | M51: 0 | N51: ON-khairan Wedding, Hair and Beauty-01062025+6285220903499-ilham
A52: 759724529202804 | B52: R11 | C52: 120227400653870200 | D52: ISAL SALON | E52: 6285240684331 | F52: 45811 | G52: 1140 | H52: 11844.268 | I52: 18 | J52: 16428 | K52: 3 | L52: 237 | M52: 1 | N52: ON-ISAL SALON-01062025+5-6285240684331-ilham
A53: 759724529202804 | B53: R11 | C53: 120227397964810200 | D53: Neng Ay salon | E53: 6282154483973 | F53: 45811 | G53: 1487 | H53: 8233.241 | I53: 40 | J53: 14861 | K53: 3 | L53: 321 | M53: 1 | N53: ON-Neng Ay salon-01062025+10-6282154483973-ilham
A54: 759724529202804 | B54: R11 | C54: 120227358608350200 | D54: Artha Jaya | E54: 6285757057088 | F54: 45811 | G54: 624 | H54: 14878.271 | I54: 31 | J54: 13078 | K54: 2 | L54: 0 | M54: 0 | N54: ON-Artha Jaya-30052025+30-6285757057088
A55: 759724529202804 | B55: R11 | C55: 120227357012290200 | D55: Devy Kikim Salon & Wedding Organizer | E55: 6282136666049 | F55: 45811 | G55: 740 | H55: 17201.835 | I55: 14 | J55: 15000 | K55: 1 | L55: 239 | M55: 0 | N55: ON-Devy Kikim Salon & Wedding Organizer-31052025+5-6282136666049-ilham
A56: 759724529202804 | B56: R11 | C56: 120227218075240200 | D56: AJP.ADI JAYA PLAFON | F56: 45811 | G56: 762 | H56: 19793.379 | I56: 19 | J56: 17339 | K56: 1 | L56: 296 | M56: 0 | N56: ON-AJP.ADI JAYA PLAFON
A57: 174904221976312 | B57: R10 | C57: 120225980267140694 | D57: Icad Interior | E57: 6285211510282 | F57: 45811 | G57: 387 | H57: 26826.406 | I57: 2 | J57: 10972 | K57: 0 | L57: 98 | M57: 0 | N57: ON-Icad Interior-03062025+5-6285211510282-ilham - Copy
A58: 174904221976312 | B58: R10 | C58: 120225943524550694 | D58: Dapur Florist | E58: 6281399998259 | F58: 45811 | G58: 953 | H58: 10091.864 | I58: 28 | J58: 11535 | K58: 3 | L58: 300 | M58: 0 | N58: ON-Dapur Florist-03062025+10-6281399998259-ilham
A59: 174904221976312 | B59: R10 | C59: 120225924609850694 | D59: Amanah Interior | E59: 6282183184641 | F59: 45811 | G59: 1054 | H59: 10368.088 | I59: 17 | J59: 13126 | K59: 4 | L59: 295 | M59: 0 | N59: ON- Amanah Interior-21052025+5-6282183184641 -ilham - NEW
A60: 174904221976312 | B60: R10 | C60: 120225732846460694 | D60: SMA Madina | E60: 6281348555887 | F60: 45811 | G60: 1353 | H60: 7490.8722 | I60: 30 | J60: 11079 | K60: 2 | L60: 435 | M60: 2 | N60: ON-SMA Madina-29052025+20-6281348555887
A61: 174904221976312 | B61: R10 | C61: 120225732456000694 | D61: Aurora Teknik | E61: 6285376667233 | F61: 45811 | G61: 1184 | H61: 10580.572 | I61: 31 | J61: 14051 | K61: 7 | L61: 353 | M61: 0 | N61: ON-Aurora Teknik-29052025+5-6285376667233
A62: 174904221976312 | B62: R10 | C62: 120225711165240694 | D62: Bang Banten | E62: 6282172291579 | F62: 45811 | G62: 939 | H62: 12786.496 | I62: 40 | J62: 14014 | K62: 3 | L62: 519 | M62: 2 | N62: ON-Bang Banten-31042025+10-6282172291579-Rudi
A63: 174904221976312 | B63: R10 | C63: 120225575002440694 | D63: Toko Emas Sembiring | E63: 6281263113266 | F63: 45811 | G63: 3726 | H63: 8496.5686 | I63: 137 | J63: 34666 | K63: 11 | L63: 1821 | M63: 3 | N63: ON-Toko Emas Sembiring-15052025+30-6281263113266-Ilham - 2 - RCVR
A64: 174904221976312 | B64: R10 | C64: 120225065069670694 | D64: LK spa n beauty | E64: 6282341426767 | F64: 45811 | G64: 500 | H64: 24640 | I64: 31 | J64: 14784 | K64: 5 | L64: 164 | M64: 0 | N64: ON-LK spa n beauty-19052025+14-6282341426767-ilham
A65: 174904221976312 | B65: R10 | C65: 120224822861740694 | D65: Daihatsu Mamuju | E65: 6282347206488 | F65: 45811 | G65: 1398 | H65: 7626.506 | I65: 45 | J65: 13293 | K65: 4 | L65: 672 | M65: 0 | N65: ON-Daihatsu Mamuju-02062025+5-6282347206488-Ilham
A66: 766589657993298 | B66: R06 | C66: 120226449010810235 | D66: Naufal interior | E66: 6281347321820 | F66: 45811 | G66: 1207 | H66: 12157.826 | I66: 41 | J66: 18565 | K66: 9 | L66: 545 | M66: 0 | N66: ON-Naufal interior-03062025+5-6281347321820
A67: 766589657993298 | B67: R06 | C67: 120226446980020235 | D67: Loundry W&M | F67: 45811 | G67: 678 | H67: 16864.03 | I67: 16 | J67: 13643 | K67: 3 | L67: 246 | M67: 0 | N67: ON-Loundry W&M-03062025+5-088242107169
A68: 759724529202804 | B68: R11 | C68: 120227526331870200 | D68: Sahabat AC | E68: 6285737244570 | F68: 45812 | G68: 754 | H68: 17955.9 | I68: 16 | J68: 15065 | K68: 4 | L68: 230 | M68: 0 | N68: ON-Sahabat AC-03062025+5-6285737244570
A69: 759724529202804 | B69: R11 | C69: 120227459128820200 | D69: Karya Tukang | E69: 628872305953 | F69: 45812 | G69: 299 | H69: 43674.487 | I69: 8 | J69: 14893 | K69: 2 | L69: 0 | M69: 0 | N69: ON-Karya Tukang-25052025+5-628872305953-ilham - Copy
A70: 759724529202804 | B70: R11 | C70: 120227433380380200 | D70: Sunat Pangkep Avacare | E70: 6285255435848 | F70: 45812 | G70: 1900 | H70: 6973.4723 | I70: 23 | J70: 14721 | K70: 0 | L70: 743 | M70: 0 | N70: ON-Sunat Pangkep Avacare-02062025+7-6285255435848-ilham
A71: 759724529202804 | B71: R11 | C71: 120227432781140200 | D71: PUTRA MANDIRI HARMONIKA | E71: 6281331854948 | F71: 45812 | G71: 896 | H71: 13827.681 | I71: 24 | J71: 15086 | K71: 2 | L71: 368 | M71: 0 | N71: ON-PUTRA MANDIRI HARMONIKA-02062025+10-6281331854948-ilham
A72: 759724529202804 | B72: R11 | C72: 120227429269270200 | D72: Nyaraa Salon | E72: 6282348365032 | F72: 45812 | G72: 792 | H72: 15105.005 | I72: 21 | J72: 15392 | K72: 3 | L72: 194 | M72: 0 | N72: ON-Nyaraa Salon-02062025+5-6282348365032-ilham
A73: 759724529202804 | B73: R11 | C73: 120227423725240200 | D73: PT MAKMUR JAYA ZEBUA | E73: 6285220903499 | F73: 45812 | G73: 931 | H73: 15183.594 | I73: 17 | J73: 15548 | K73: 5 | L73: 334 | M73: 1 | N73: ON-PT MAKMUR JAYA ZEBUA-01062025+5-6285220903499-ilham
A74: 759724529202804 | B74: R11 | C74: 120227403909070200 | D74: khairan Wedding, Hair and Beauty | F74: 45812 | G74: 11590 | H74: 1264.4014 | I74: 15 | J74: 15145 | K74: 0 | L74: 1059 | M74: 0 | N74: ON-khairan Wedding, Hair and Beauty-01062025+6285220903499-ilham
A75: 759724529202804 | B75: R11 | C75: 120227400653870200 | D75: ISAL SALON | E75: 6285240684331 | F75: 45812 | G75: 1157 | H75: 10795.421 | I75: 8 | J75: 14617 | K75: 0 | L75: 194 | M75: 0 | N75: ON-ISAL SALON-01062025+5-6285240684331-ilham
A76: 759724529202804 | B76: R11 | C76: 120227397964810200 | D76: Neng Ay salon | E76: 6282154483973 | F76: 45812 | G76: 1597 | H76: 7220.7921 | I76: 31 | J76: 14586 | K76: 2 | L76: 339 | M76: 0 | N76: ON-Neng Ay salon-01062025+10-6282154483973-ilham
A77: 759724529202804 | B77: R11 | C77: 120227358608350200 | D77: Artha Jaya | E77: 6285757057088 | F77: 45812 | G77: 960 | H77: 11119.969 | I77: 26 | J77: 14367 | K77: 0 | L77: 0 | M77: 0 | N77: ON-Artha Jaya-30052025+30-6285757057088
A78: 759724529202804 | B78: R11 | C78: 120227357012290200 | D78: Devy Kikim Salon & Wedding Organizer | E78: 6282136666049 | F78: 45812 | G78: 995 | H78: 15386.977 | I78: 23 | J78: 16541 | K78: 5 | L78: 274 | M78: 0 | N78: ON-Devy Kikim Salon & Wedding Organizer-31052025+5-6282136666049-ilham
A79: 759724529202804 | B79: R11 | C79: 120227218075240200 | D79: AJP.ADI JAYA PLAFON | F79: 45812 | G79: 654 | H79: 22297.151 | I79: 13 | J79: 16433 | K79: 0 | L79: 96 | M79: 1 | N79: ON-AJP.ADI JAYA PLAFON
A80: 174904221976312 | B80: R10 | C80: 120226052237140694 | D80: Umam daffa | F80: 45812 | G80: 359 | H80: 12613.514 | I80: 3 | J80: 4667 | K80: 0 | L80: 92 | M80: 0 | N80: ON-Umam daffa-02-Juni-2025+5-+62 877-1504-0331 - Copy
A81: 174904221976312 | B81: R10 | C81: 120226032160860694 | D81: EPE Plavon | F81: 45812 | G81: 1110 | H81: 8438.4365 | I81: 66 | J81: 12953 | K81: 11 | L81: 459 | M81: 3 | N81: ON-EPE Plavon-04062025+5-085362101860
A82: 174904221976312 | B82: R10 | C82: 120225980267140694 | D82: Icad Interior | E82: 6285211510282 | F82: 45812 | G82: 201 | H82: 57389.908 | I82: 3 | J82: 12511 | K82: 0 | L82: 48 | M82: 0 | N82: ON-Icad Interior-03062025+5-6285211510282-ilham - Copy
A83: 174904221976312 | B83: R10 | C83: 120225943524550694 | D83: Dapur Florist | E83: 6281399998259 | F83: 45812 | G83: 1578 | H83: 7252.8027 | I83: 23 | J83: 12939 | K83: 0 | L83: 481 | M83: 0 | N83: ON-Dapur Florist-03062025+10-6281399998259-ilham
A84: 174904221976312 | B84: R10 | C84: 120225924609850694 | D84: Amanah Interior | E84: 6282183184641 | F84: 45812 | G84: 1100 | H84: 11523.506 | I84: 34 | J84: 14462 | K84: 4 | L84: 332 | M84: 3 | N84: ON- Amanah Interior-21052025+5-6282183184641 -ilham - NEW
A85: 174904221976312 | B85: R10 | C85: 120225732846460694 | D85: SMA Madina | E85: 6281348555887 | F85: 45812 | G85: 1426 | H85: 7192.8934 | I85: 37 | J85: 11336 | K85: 2 | L85: 464 | M85: 0 | N85: ON-SMA Madina-29052025+20-6281348555887
A86: 174904221976312 | B86: R10 | C86: 120225732456000694 | D86: Aurora Teknik | E86: 6285376667233 | F86: 45812 | G86: 352 | H86: 11611.979 | I86: 7 | J86: 4459 | K86: 3 | L86: 121 | M86: 0 | N86: ON-Aurora Teknik-29052025+5-6285376667233
A87: 174904221976312 | B87: R10 | C87: 120225711165240694 | D87: Bang Banten | E87: 6282172291579 | F87: 45812 | G87: 764 | H87: 13616.253 | I87: 30 | J87: 12064 | K87: 1 | L87: 390 | M87: 4 | N87: ON-Bang Banten-31042025+10-6282172291579-Rudi
A88: 174904221976312 | B88: R10 | C88: 120225575002440694 | D88: Toko Emas Sembiring | E88: 6281263113266 | F88: 45812 | G88: 3152 | H88: 7935.4929 | I88: 126 | J88: 28417 | K88: 11 | L88: 1481 | M88: 5 | N88: ON-Toko Emas Sembiring-15052025+30-6281263113266-Ilham - 2 - RCVR
A89: 174904221976312 | B89: R10 | C89: 120224822861740694 | D89: Daihatsu Mamuju | E89: 6282347206488 | F89: 45812 | G89: 2244 | H89: 5493.5522 | I89: 61 | J89: 14058 | K89: 7 | L89: 989 | M89: 0 | N89: ON-Daihatsu Mamuju-02062025+5-6282347206488-Ilham
A90: 766589657993298 | B90: R06 | C90: 120226524173690235 | D90: Bangun Renov | E90: 62812 | F90: 45812 | G90: 132 | H90: 45834.532 | I90: 0 | J90: 6371 | K90: 0 | L90: 25 | M90: 0 | N90: ON-Bangun Renov-04062025+5-62812-2660-5001
A91: 766589657993298 | B91: R06 | C91: 120226503616670235 | D91: bengkel mobil | E91: 6282288123215 | F91: 45812 | G91: 706 | H91: 9121.7277 | I91: 9 | J91: 6969 | K91: 1 | L91: 190 | M91: 0 | N91: ON-bengkel mobil-01062025+10-6282288123215 - Copy
A92: 766589657993298 | B92: R06 | C92: 120226497822570235 | D92: Sofie Gorden | E92: 6282154795446 | F92: 45812 | G92: 639 | H92: 15788.714 | I92: 2 | J92: 12031 | K92: 0 | L92: 129 | M92: 0 | N92: ON-Sofie Gorden-04062025+5-6282154795446
A93: 766589657993298 | B93: R06 | C93: 120226449010810235 | D93: Naufal interior | E93: 6281347321820 | F93: 45812 | G93: 1056 | H93: 9966.9917 | I93: 25 | J93: 13286 | K93: 1 | L93: 422 | M93: 0 | N93: ON-Naufal interior-03062025+5-6281347321820
A94: 766589657993298 | B94: R06 | C94: 120226446980020235 | D94: Loundry W&M | F94: 45812 | G94: 500 | H94: 23904.159 | I94: 6 | J94: 13219 | K94: 0 | L94: 138 | M94: 0 | N94: ON-Loundry W&M-03062025+5-088242107169
A95: 759724529202804 | B95: R11 | C95: 120227526331870200 | D95: Sahabat AC | E95: 6285737244570 | F95: 45813 | G95: 773 | H95: 17711.561 | I95: 13 | J95: 14860 | K95: 1 | L95: 228 | M95: 0 | N95: ON-Sahabat AC-03062025+5-6285737244570
A96: 759724529202804 | B96: R11 | C96: 120227433380380200 | D96: Sunat Pangkep Avacare | E96: 6285255435848 | F96: 45813 | G96: 1541 | H96: 8842.8334 | I96: 21 | J96: 15979 | K96: 1 | L96: 614 | M96: 0 | N96: ON-Sunat Pangkep Avacare-02062025+7-6285255435848-ilham
A97: 759724529202804 | B97: R11 | C97: 120227432781140200 | D97: PUTRA MANDIRI HARMONIKA | E97: 6281331854948 | F97: 45813 | G97: 1108 | H97: 12431.215 | I97: 25 | J97: 15452 | K97: 4 | L97: 456 | M97: 0 | N97: ON-PUTRA MANDIRI HARMONIKA-02062025+10-6281331854948-ilham
A98: 759724529202804 | B98: R11 | C98: 120227429269270200 | D98: Nyaraa Salon | E98: 6282348365032 | F98: 45813 | G98: 737 | H98: 18231.195 | I98: 15 | J98: 16481 | K98: 2 | L98: 169 | M98: 1 | N98: ON-Nyaraa Salon-02062025+5-6282348365032-ilham
A99: 759724529202804 | B99: R11 | C99: 120227423725240200 | D99: PT MAKMUR JAYA ZEBUA | E99: 6285220903499 | F99: 45813 | G99: 1066 | H99: 14812.284 | I99: 26 | J99: 17123 | K99: 6 | L99: 382 | M99: 0 | N99: ON-PT MAKMUR JAYA ZEBUA-01062025+5-6285220903499-ilham
A100: 759724529202804 | B100: R11 | C100: 120227403909070200 | D100: khairan Wedding, Hair and Beauty | F100: 45813 | G100: 11928 | H100: 1346.2441 | I100: 18 | J100: 16058 | K100: 0 | L100: 1151 | M100: 0 | N100: ON-khairan Wedding, Hair and Beauty-01062025+6285220903499-ilham
A101: 759724529202804 | B101: R11 | C101: 120227400653870200 | D101: ISAL SALON | E101: 6285240684331 | F101: 45813 | G101: 1575 | H101: 9165.8456 | I101: 29 | J101: 16746 | K101: 2 | L101: 272 | M101: 0 | N101: ON-ISAL SALON-01062025+5-6285240684331-ilham
A102: 759724529202804 | B102: R11 | C102: 120227397964810200 | D102: Neng Ay salon | E102: 6282154483973 | F102: 45813 | G102: 1698 | H102: 7381.7829 | I102: 33 | J102: 15236 | K102: 3 | L102: 309 | M102: 0 | N102: ON-Neng Ay salon-01062025+10-6282154483973-ilham
A103: 759724529202804 | B103: R11 | C103: 120227358608350200 | D103: Artha Jaya | E103: 6285757057088 | F103: 45813 | G103: 915 | H103: 12689.451 | I103: 26 | J103: 15037 | K103: 0 | L103: 0 | M103: 0 | N103: ON-Artha Jaya-30052025+30-6285757057088
A104: 174904221976312 | B104: R10 | C104: 120226052237140694 | D104: Umam daffa | F104: 45813 | G104: 216 | H104: 46639.485 | I104: 5 | J104: 10867 | K104: 1 | L104: 69 | M104: 0 | N104: ON-Umam daffa-02-Juni-2025+5-+62 877-1504-0331 - Copy
A105: 174904221976312 | B105: R10 | C105: 120226032160860694 | D105: EPE Plavon | F105: 45813 | G105: 1460 | H105: 6687.5329 | I105: 67 | J105: 12713 | K105: 7 | L105: 578 | M105: 3 | N105: ON-EPE Plavon-04062025+5-085362101860
...

Sheet Performa Iklan
A1: AkunIklanId | B1: NamaAkun | C1: KampanyeId | D1: KampanyeName | E1: Tanggal | F1: Reach | G1: CPM | H1: LinkKlik | I1: Budget | J1: KlikWhatsapp | K1: VideoView | L1: Komentar | M1: NamaUsaha | N1: NoWhatsapp | O1: PesanWhatsapp
A2: 759724529202804 | B2: R11 | C2: 120241465022560200 | D2: Custom-Deriano-Baru | E2: 46072 | F2: 1162 | G2: 37772.897 | H2: 44 | I2: 50729 | J2: 7 | K2: 451 | L2: 0 | M2: Deriano | O2: *Laporan Jasa Iklan UMKM* 📅 19-02-2026 👨‍💼 Data Klient KampanyeId: 120241465022560200 Nama: *Deriano* 📊 Performa Iklan Jangkauan: 1162 Hasil: *7 klik Whatsapp* Video Ditonton: 451 Komentar: 0 Linkklik: 44 Catatan: Hasil = Jumlah klik whatsapp jumlahnya suka berbeda dengan real Whatsapp masuk. Semoga banyak yang DEAL ya Kak! Mau konsultasi? Langsung balas aja chatnya, mimin siap membantu.😊 | P2: Gagal: Data tidak lengkap
A3: 174904221976312 | B3: R10 | C3: 120230030877630694 | D3: ON-CV.BAGUS DAN-31072025+30-6281357754513-ext 0702-30 - R3 1902 Rusdian | E3: 46072 | F3: 445 | G3: 28713.542 | H3: 14 | I3: 16539 | J3: 3 | K3: 1 | L3: 0 | M3: CV.BAGUS DAN | N3: 6281357754513 | O3: *Laporan Jasa Iklan UMKM* 📅 19-02-2026 👨‍💼 Data Klient KampanyeId: 120230030877630694 Nama: *CV.BAGUS DAN* 📊 Performa Iklan Jangkauan: 445 Hasil: *3 klik Whatsapp* Video Ditonton: 1 Komentar: 0 Linkklik: 14 Catatan: Hasil = Jumlah klik whatsapp jumlahnya suka berbeda dengan real Whatsapp masuk. Semoga banyak yang DEAL ya Kak! Mau konsultasi? Langsung balas aja chatnya, mimin siap membantu.😊 | P3: Gagal: {"status":404,"message":"WhatsApp account doesn't exist!","data":false}
A4: 174904221976312 | B4: R10 | C4: 120230494969540694 | D4: ON-Yono motor-11082025+5-6287701349406-1602-5 | E4: 46072 | F4: 2546 | G4: 5107.1061 | H4: 89 | I4: 14877 | J4: 0 | K4: 100 | L4: 0 | M4: Yono motor | N4: 6287701349406 | O4: *Laporan Jasa Iklan UMKM* 📅 19-02-2026 👨‍💼 Data Klient KampanyeId: 120230494969540694 Nama: *Yono motor* 📊 Performa Iklan Jangkauan: 2546 Hasil: *0 klik Whatsapp* Video Ditonton: 100 Komentar: 0 Linkklik: 89 Catatan: Hasil = Jumlah klik whatsapp jumlahnya suka berbeda dengan real Whatsapp masuk. Semoga banyak yang DEAL ya Kak! Mau konsultasi? Langsung balas aja chatnya, mimin siap membantu.😊 | P4: Gagal: {"status":404,"message":"WhatsApp account doesn't exist!","data":false}
A5: 174904221976312 | B5: R10 | C5: 120230878618490694 | D5: ON-Rumah Sehat-16082025+30-6282166986254-ext 2601-30 - R1 1302 Rusdian | E5: 46072 | F5: 720 | G5: 18311.688 | H5: 42 | I5: 15510 | J5: 8 | K5: 333 | L5: 0 | M5: Rumah Sehat | N5: 6282166986254 | O5: *Laporan Jasa Iklan UMKM* 📅 19-02-2026 👨‍💼 Data Klient KampanyeId: 120230878618490694 Nama: *Rumah Sehat* 📊 Performa Iklan Jangkauan: 720 Hasil: *8 klik Whatsapp* Video Ditonton: 333 Komentar: 0 Linkklik: 42 Catatan: Hasil = Jumlah klik whatsapp jumlahnya suka berbeda dengan real Whatsapp masuk. Semoga banyak yang DEAL ya Kak! Mau konsultasi? Langsung balas aja chatnya, mimin siap membantu.😊 | P5: Gagal: {"status":404,"message":"WhatsApp account doesn't exist!","data":false}
A6: 174904221976312 | B6: R10 | C6: 120231473177720694 | D6: ON-Nizam Traveling-27082025+5-6285361118289-ext: 0402-30 - R4 1902 Rusdian | E6: 46072 | F6: 776 | G6: 18846.523 | H6: 26 | I6: 15718 | J6: 1 | K6: 12 | L6: 0 | M6: Nizam Traveling | N6: 6285361118289 | O6: *Laporan Jasa Iklan UMKM* 📅 19-02-2026 👨‍💼 Data Klient KampanyeId: 120231473177720694 Nama: *Nizam Traveling* 📊 Performa Iklan Jangkauan: 776 Hasil: *1 klik Whatsapp* Video Ditonton: 12 Komentar: 0 Linkklik: 26 Catatan: Hasil = Jumlah klik whatsapp jumlahnya suka berbeda dengan real Whatsapp masuk. Semoga banyak yang DEAL ya Kak! Mau konsultasi? Langsung balas aja chatnya, mimin siap membantu.😊 | P6: Gagal: {"status":404,"message":"WhatsApp account doesn't exist!","data":false}
A7: 174904221976312 | B7: R10 | C7: 120232493664810694 | D7: ON-Rumah Sehat-11092025+5-6281316122975-TT1709-ext 1202-5 | E7: 46072 | F7: 642 | G7: 18053.061 | H7: 17 | I7: 13269 | J7: 2 | K7: 219 | L7: 0 | M7: Rumah Sehat | N7: 6281316122975 | O7: *Laporan Jasa Iklan UMKM* 📅 19-02-2026 👨‍💼 Data Klient KampanyeId: 120232493664810694 Nama: *Rumah Sehat* 📊 Performa Iklan Jangkauan: 642 Hasil: *2 klik Whatsapp* Video Ditonton: 219 Komentar: 0 Linkklik: 17 Catatan: Hasil = Jumlah klik whatsapp jumlahnya suka berbeda dengan real Whatsapp masuk. Semoga banyak yang DEAL ya Kak! Mau konsultasi? Langsung balas aja chatnya, mimin siap membantu.😊 | P7: Gagal: {"status":404,"message":"WhatsApp account doesn't exist!","data":false}
A8: 174904221976312 | B8: R10 | C8: 120234436313700694 | D8: ON-Maniaka Catering-21102025+20-6281246072868-TT2410-ext 1002-20 - R3 1702 Rusdian | E8: 46072 | F8: 531 | G8: 26602.564 | H8: 29 | I8: 16600 | J8: 4 | K8: 178 | L8: 0 | M8: Maniaka Catering | N8: 6281246072868 | O8: *Laporan Jasa Iklan UMKM* 📅 19-02-2026 👨‍💼 Data Klient KampanyeId: 120234436313700694 Nama: *Maniaka Catering* 📊 Performa Iklan Jangkauan: 531 Hasil: *4 klik Whatsapp* Video Ditonton: 178 Komentar: 0 Linkklik: 29 Catatan: Hasil = Jumlah klik whatsapp jumlahnya suka berbeda dengan real Whatsapp masuk. Semoga banyak yang DEAL ya Kak! Mau konsultasi? Langsung balas aja chatnya, mimin siap membantu.😊 | P8: Gagal: {"status":404,"message":"WhatsApp account doesn't exist!","data":false}
A9: 174904221976312 | B9: R10 | C9: 120236224250950694 | D9: ON-Bimbel Antusias-20112025+10-6285292365257-TT2211-ext 0802-14 - R3 1502 Rusdian | E9: 46072 | F9: 599 | G9: 18508.527 | H9: 9 | I9: 11938 | J9: 0 | K9: 0 | L9: 0 | M9: Bimbel Antusias | N9: 6285292365257 | O9: *Laporan Jasa Iklan UMKM* 📅 19-02-2026 👨‍💼 Data Klient KampanyeId: 120236224250950694 Nama: *Bimbel Antusias* 📊 Performa Iklan Jangkauan: 599 Hasil: *0 klik Whatsapp* Video Ditonton: 0 Komentar: 0 Linkklik: 9 Catatan: Hasil = Jumlah klik whatsapp jumlahnya suka berbeda dengan real Whatsapp masuk. Semoga banyak yang DEAL ya Kak! Mau konsultasi? Langsung balas aja chatnya, mimin siap membantu.😊 | P9: Gagal: {"status":404,"message":"WhatsApp account doesn't exist!","data":false}
A10: 174904221976312 | B10: R10 | C10: 120238476998550694 | D10: ON-PT Garuda-05012026+5-6282261184459-TT0701 - ext 0602-14 - R3 1502 Rusdian | E10: 46072 | F10: 300 | G10: 59108.911 | H10: 8 | I10: 17910 | J10: 2 | K10: 0 | L10: 0 | M10: PT Garuda | N10: 6282261184459 | O10: *Laporan Jasa Iklan UMKM* 📅 19-02-2026 👨‍💼 Data Klient KampanyeId: 120238476998550694 Nama: *PT Garuda* 📊 Performa Iklan Jangkauan: 300 Hasil: *2 klik Whatsapp* Video Ditonton: 0 Komentar: 0 Linkklik: 8 Catatan: Hasil = Jumlah klik whatsapp jumlahnya suka berbeda dengan real Whatsapp masuk. Semoga banyak yang DEAL ya Kak! Mau konsultasi? Langsung balas aja chatnya, mimin siap membantu.😊 | P10: Gagal: {"status":404,"message":"WhatsApp account doesn't exist!","data":false}
A11: 174904221976312 | B11: R10 | C11: 120238645880620694 | D11: ON-kredit toko-11012026+5-6282286712200-TT1101-ext 1602-5 | E11: 46072 | F11: 730 | G11: 17933.404 | H11: 47 | I11: 16965 | J11: 7 | K11: 183 | L11: 0 | M11: kredit toko | N11: 6282286712200 | O11: *Laporan Jasa Iklan UMKM* 📅 19-02-2026 👨‍💼 Data Klient KampanyeId: 120238645880620694 Nama: *kredit toko* 📊 Performa Iklan Jangkauan: 730 Hasil: *7 klik Whatsapp* Video Ditonton: 183 Komentar: 0 Linkklik: 47 Catatan: Hasil = Jumlah klik whatsapp jumlahnya suka berbeda dengan real Whatsapp masuk. Semoga banyak yang DEAL ya Kak! Mau konsultasi? Langsung balas aja chatnya, mimin siap membantu.😊 | P11: Gagal: {"status":404,"message":"WhatsApp account doesn't exist!","data":false}
A12: 174904221976312 | B12: R10 | C12: 120238672136120694 | D12: ON-king auto-09012026+5-62895603690686-TT1201-ext 1902-7 | E12: 46072 | F12: 1011 | G12: 14898.998 | H12: 43 | I12: 17849 | J12: 0 | K12: 439 | L12: 0 | M12: king auto | N12: 62895603690686 | O12: *Laporan Jasa Iklan UMKM* 📅 19-02-2026 👨‍💼 Data Klient KampanyeId: 120238672136120694 Nama: *king auto* 📊 Performa Iklan Jangkauan: 1011 Hasil: *0 klik Whatsapp* Video Ditonton: 439 Komentar: 0 Linkklik: 43 Catatan: Hasil = Jumlah klik whatsapp jumlahnya suka berbeda dengan real Whatsapp masuk. Semoga banyak yang DEAL ya Kak! Mau konsultasi? Langsung balas aja chatnya, mimin siap membantu.😊 | P12: Gagal: {"status":404,"message":"WhatsApp account doesn't exist!","data":false}
A13: 174904221976312 | B13: R10 | C13: 120238965258630694 | D13: ON-Deler Honda-19012026+5-6287861389777-TT2001-ext 1802-7 | E13: 46072 | F13: 714 | G13: 20434.62 | H13: 63 | I13: 16409 | J13: 11 | K13: 2 | L13: 3 | M13: Deler Honda | N13: 6287861389777 | O13: *Laporan Jasa Iklan UMKM* 📅 19-02-2026 👨‍💼 Data Klient KampanyeId: 120238965258630694 Nama: *Deler Honda* 📊 Performa Iklan Jangkauan: 714 Hasil: *11 klik Whatsapp* Video Ditonton: 2 Komentar: 3 Linkklik: 63 Catatan: Hasil = Jumlah klik whatsapp jumlahnya suka berbeda dengan real Whatsapp masuk. Semoga banyak yang DEAL ya Kak! Mau konsultasi? Langsung balas aja chatnya, mimin siap membantu.😊 | P13: Gagal: {"status":404,"message":"WhatsApp account doesn't exist!","data":false}
A14: 174904221976312 | B14: R10 | C14: 120239034771370694 | D14: ON-Kegiatan AMT-20012026+30-6281904501876-TT2201 - R6 1302 Rusdian | E14: 46072 | F14: 617 | G14: 18818.316 | H14: 22 | I14: 12740 | J14: 2 | K14: 0 | L14: 0 | M14: Kegiatan AMT | N14: 6281904501876 | O14: *Laporan Jasa Iklan UMKM* 📅 19-02-2026 👨‍💼 Data Klient KampanyeId: 120239034771370694 Nama: *Kegiatan AMT* 📊 Performa Iklan Jangkauan: 617 Hasil: *2 klik Whatsapp* Video Ditonton: 0 Komentar: 0 Linkklik: 22 Catatan: Hasil = Jumlah klik whatsapp jumlahnya suka berbeda dengan real Whatsapp masuk. Semoga banyak yang DEAL ya Kak! Mau konsultasi? Langsung balas aja chatnya, mimin siap membantu.😊 | P14: Gagal: {"status":404,"message":"WhatsApp account doesn't exist!","data":false}
... A45: 206726568613432 | B45: R04 | C45: 120235983090370554 | D45: ON-Wiris Variasi-05042025+7-6282242925264-ext: 2211-10 | E45: 46072 | F45: 2133 | G45: 7280.5195 | H45: 75 | I45: 16818 | J45: 1 | K45: 687 | L45: 0 | M45: Wiris Variasi | N45: 6282242925264 | O45: *Laporan Jasa Iklan UMKM* 📅 19-02-2026 👨‍💼 Data Klient KampanyeId: 120235983090370554 Nama: *Wiris Variasi* 📊 Performa Iklan Jangkauan: 2133 Hasil: *1 klik Whatsapp* Video Ditonton: 687 Komentar: 0 Linkklik: 75 Catatan: Hasil = Jumlah klik whatsapp jumlahnya suka berbeda dengan real Whatsapp masuk. Semoga banyak yang DEAL ya Kak! Mau konsultasi? Langsung balas aja chatnya, mimin siap membantu.😊 | P45: Gagal: {"status":404,"message":"WhatsApp account doesn't exist!","data":false}

Sheet LinkWhatsappLaporan
A1: Link Whatsapp
A2: =HYPERLINK( "https://wa.me/"& 'Performa Iklan'!N1& "?text="& _xludf.ENCODEURL('Performa Iklan'!O1), "Kirim WhatsApp" ) -> #NAME?
A3: =HYPERLINK( "https://wa.me/"& 'Performa Iklan'!N2& "?text="& _xludf.ENCODEURL('Performa Iklan'!O2), "Kirim WhatsApp" ) -> #NAME?
A4: =HYPERLINK( "https://wa.me/"& 'Performa Iklan'!N2& "?text="& _xludf.ENCODEURL('Performa Iklan'!O2), "Kirim WhatsApp" ) -> #NAME?
A5: =HYPERLINK( "https://wa.me/"& 'Performa Iklan'!N3& "?text="& _xludf.ENCODEURL('Performa Iklan'!O3), "Kirim WhatsApp" ) -> #NAME?
A6: =HYPERLINK( "https://wa.me/"& 'Performa Iklan'!N4& "?text="& _xludf.ENCODEURL('Performa Iklan'!O4), "Kirim WhatsApp" ) -> #NAME?
A7: =HYPERLINK( "https://wa.me/"& 'Performa Iklan'!N5& "?text="& _xludf.ENCODEURL('Performa Iklan'!O5), "Kirim WhatsApp" ) -> #NAME?
A8: =HYPERLINK( "https://wa.me/"& 'Performa Iklan'!N6& "?text="& _xludf.ENCODEURL('Performa Iklan'!O6), "Kirim WhatsApp" ) -> #NAME?
A9: =HYPERLINK( "https://wa.me/"& 'Performa Iklan'!N7& "?text="& _xludf.ENCODEURL('Performa Iklan'!O7), "Kirim WhatsApp" ) -> #NAME?
A10: =HYPERLINK( "https://wa.me/"& 'Performa Iklan'!N8& "?text="& _xludf.ENCODEURL('Performa Iklan'!O8), "Kirim WhatsApp" ) -> #NAME?
A11: =HYPERLINK( "https://wa.me/"& 'Performa Iklan'!N9& "?text="& _xludf.ENCODEURL('Performa Iklan'!O9), "Kirim WhatsApp" ) -> #NAME?
A12: =HYPERLINK( "https://wa.me/"& 'Performa Iklan'!N10& "?text="& _xludf.ENCODEURL('Performa Iklan'!O10), "Kirim WhatsApp" ) -> #NAME?
A13: =HYPERLINK( "https://wa.me/"& 'Performa Iklan'!N11& "?text="& _xludf.ENCODEURL('Performa Iklan'!O11), "Kirim WhatsApp" ) -> #NAME?
A14: =HYPERLINK( "https://wa.me/"& 'Performa Iklan'!N12& "?text="& _xludf.ENCODEURL('Performa Iklan'!O12), "Kirim WhatsApp" ) -> #NAME?
A15: =HYPERLINK( "https://wa.me/"& 'Performa Iklan'!N13& "?text="& _xludf.ENCODEURL('Performa Iklan'!O13), "Kirim WhatsApp" ) -> #NAME?
... A149: =HYPERLINK( "https://wa.me/"& 'Performa Iklan'!N147& "?text="& _xludf.ENCODEURL('Performa Iklan'!O147), "Kirim WhatsApp" ) -> #NAME?

Sheet Performa Iklan Klien By Usia
A1: AkunIklanId | B1: NamaAkun | C1: KampanyeId | D1: Nama Usaha | E1: Whatsapp | F1: Tanggal | G1: Reach | H1: Usia | I1: CPM | J1: LinkKlik | K1: Spend | L1: KlikWA | M1: VideoView | N1: Komentar | O1: Nama Kampanye
A2: 759724529202804 | B2: R11 | C2: 120229046011260200 | D2: Abadi Tehnik | E2: 6285711667433 | F2: 45832 | G2: 52 | H2: 18-24 | I2: 9283.3333 | J2: 1 | K2: 557 | L2: 0 | M2: 0 | N2: 0 | O2: ON-Abadi Tehnik-21062025+5-6285711667433
A3: 759724529202804 | B3: R11 | C3: 120229046011260200 | D3: Abadi Tehnik | E3: 6285711667433 | F3: 45832 | G3: 217 | H3: 25-34 | I3: 9277.1084 | J3: 4 | K3: 2310 | L3: 0 | M3: 0 | N3: 0 | O3: ON-Abadi Tehnik-21062025+5-6285711667433
A4: 759724529202804 | B4: R11 | C4: 120229046011260200 | D4: Abadi Tehnik | E4: 6285711667433 | F4: 45832 | G4: 328 | H4: 35-44 | I4: 10936.986 | J4: 3 | K4: 3992 | L4: 0 | M4: 0 | N4: 0 | O4: ON-Abadi Tehnik-21062025+5-6285711667433
A5: 759724529202804 | B5: R11 | C5: 120229046011260200 | D5: Abadi Tehnik | E5: 6285711667433 | F5: 45832 | G5: 252 | H5: 45-54 | I5: 11962.838 | J5: 6 | K5: 3541 | L5: 1 | M5: 0 | N5: 0 | O5: ON-Abadi Tehnik-21062025+5-6285711667433
A6: 759724529202804 | B6: R11 | C6: 120229046011260200 | D6: Abadi Tehnik | E6: 6285711667433 | F6: 45832 | G6: 47 | H6: 55-64 | I6: 15775.51 | J6: 1 | K6: 773 | L6: 0 | M6: 0 | N6: 0 | O6: ON-Abadi Tehnik-21062025+5-6285711667433
A7: 759724529202804 | B7: R11 | C7: 120229046011260200 | D7: Abadi Tehnik | E7: 6285711667433 | F7: 45832 | G7: 11 | H7: 65+ | I7: 6545.4545 | J7: 0 | K7: 72 | L7: 0 | M7: 0 | N7: 0 | O7: ON-Abadi Tehnik-21062025+5-6285711667433
A8: 759724529202804 | B8: R11 | C8: 120229044952270200 | D8: Alfie salon | E8: 6285775986977 | F8: 45832 | G8: 41 | H8: 18-24 | I8: 13304.348 | J8: 0 | K8: 612 | L8: 0 | M8: 0 | N8: 0 | O8: ON-Alfie salon-19062025+5-6285775986977 - Salin
A9: 759724529202804 | B9: R11 | C9: 120229044952270200 | D9: Alfie salon | E9: 6285775986977 | F9: 45832 | G9: 57 | H9: 25-34 | I9: 62578.125 | J9: 0 | K9: 4005 | L9: 0 | M9: 0 | N9: 0 | O9: ON-Alfie salon-19062025+5-6285775986977 - Salin
A10: 759724529202804 | B10: R11 | C10: 120229044952270200 | D10: Alfie salon | E10: 6285775986977 | F10: 45832 | G10: 75 | H10: 35-44 | I10: 54269.663 | J10: 2 | K10: 4830 | L10: 0 | M10: 0 | N10: 0 | O10: ON-Alfie salon-19062025+5-6285775986977 - Salin
A11: 759724529202804 | B11: R11 | C11: 120229044952270200 | D11: Alfie salon | E11: 6285775986977 | F11: 45832 | G11: 38 | H11: 45-54 | I11: 41878.049 | J11: 0 | K11: 1717 | L11: 0 | M11: 0 | N11: 0 | O11: ON-Alfie salon-19062025+5-6285775986977 - Salin
A12: 759724529202804 | B12: R11 | C12: 120229044952270200 | D12: Alfie salon | E12: 6285775986977 | F12: 45832 | G12: 26 | H12: 55-64 | I12: 51428.571 | J12: 1 | K12: 1440 | L12: 0 | M12: 0 | N12: 0 | O12: ON-Alfie salon-19062025+5-6285775986977 - Salin
A13: 759724529202804 | B13: R11 | C13: 120229044952270200 | D13: Alfie salon | E13: 6285775986977 | F13: 45832 | G13: 18 | H13: 65+ | I13: 77105.263 | J13: 0 | K13: 1465 | L13: 0 | M13: 0 | N13: 0 | O13: ON-Alfie salon-19062025+5-6285775986977 - Salin
... A132: 174904221976312 | B132: R10 | C132: 120226464082810694 | D132: Yuzef homestay | E132: 628988759290 | F132: 45832 | G132: 20 | H132: 65+ | I132: 33230.769 | J132: 4 | K132: 864 | L132: 0 | M132: 3 | N132: 0 | O132: ON-Yuzef homestay-11062025+13-628988759290
A133: 174904221976312 | B133: R10 | C133: 120226351656870694 | D133: Rodrimar Aifunan Fresku | F133: 45832 | G133: 1428 | H133: 18-24 | I133: 1319.9728 | J133: 18 | K133: 1943 | L133: 0 | M133: 84 | N133: 0 | O133: ON-Rodrimar Aifunan Fresku-16052025+14-67077619002-Ilham - 2 - Copy
A134: 174904221976312 | B134: R10 | C134: 120226351656870694 | D134: Rodrimar Aifunan Fresku | F134: 45832 | G134: 1600 | H134: 25-34 | I134: 1786.6667 | J134: 23 | K134: 3082 | L134: 0 | M134: 148 | N134: 0 | O134: ON-Rodrimar Aifunan Fresku-16052025+14-67077619002-Ilham - 2 - Copy
A135: 174904221976312 | B135: R10 | C135: 120226351656870694 | D135: Rodrimar Aifunan Fresku | F135: 45832 | G135: 1416 | H135: 35-44 | I135: 2511.7574 | J135: 26 | K135: 4059 | L135: 0 | M135: 205 | N135: 0 | O135: ON-Rodrimar Aifunan Fresku-16052025+14-67077619002-Ilham - 2 - Copy
A136: 174904221976312 | B136: R10 | C136: 120226351656870694 | D136: Rodrimar Aifunan Fresku | F136: 45832 | G136: 552 | H136: 45-54 | I136: 3138.3855 | J136: 9 | K136: 1905 | L136: 0 | M136: 62 | N136: 0 | O136: ON-Rodrimar Aifunan Fresku-16052025+14-67077619002-Ilham - 2 - Copy
A137: 174904221976312 | B137: R10 | C137: 120226351656870694 | D137: Rodrimar Aifunan Fresku | F137: 45832 | G137: 120 | H137: 55-64 | I137: 3176.8707 | J137: 5 | K137: 467 | L137: 0 | M137: 13 | N137: 0 | O137: ON-Rodrimar Aifunan Fresku-16052025+14-67077619002-Ilham - 2 - Copy
A138: 174904221976312 | B138: R10 | C138: 120226351656870694 | D138: Rodrimar Aifunan Fresku | F138: 45832 | G138: 94 | H138: 65+ | I138: 2410.7143 | J138: 3 | K138: 270 | L138: 0 | M138: 9 | N138: 0 | O138: ON-Rodrimar Aifunan Fresku-16052025+14-67077619002-Ilham - 2 - Copy
A139: 174904221976312 | B139: R10 | C139: 120225924609850694 | D139: Amanah Interior | E139: 6282183184641 | F139: 45832 | G139: 15 | H139: 18-24 | I139: 9533.3333 | J139: 0 | K139: 143 | L139: 0 | M139: 0 | N139: 0 | O139: OFF- Amanah Interior-21052025+5-6282183184641 -ilham - NEW
A140: 174904221976312 | B140: R10 | C140: 120225924609850694 | D140: Amanah Interior | E140: 6282183184641 | F140: 45832 | G140: 100 | H140: 25-34 | I140: 20194.245 | J140: 0 | K140: 2807 | L140: 0 | M140: 0 | N140: 0 | O140: OFF- Amanah Interior-21052025+5-6282183184641 -ilham - NEW
A141: 174904221976312 | B141: R10 | C141: 120225924609850694 | D141: Amanah Interior | E141: 6282183184641 | F141: 45832 | G141: 112 | H141: 35-44 | I141: 18987.654 | J141: 3 | K141: 3076 | L141: 0 | M141: 0 | N141: 0 | O141: OFF- Amanah Interior-21052025+5-6282183184641 -ilham - NEW
A142: 174904221976312 | B142: R10 | C142: 120225924609850694 | D142: Amanah Interior | E142: 6282183184641 | F142: 45832 | G142: 89 | H142: 45-54 | I142: 36603.448 | J142: 7 | K142: 4246 | L142: 0 | M142: 1 | N142: 0 | O142: OFF- Amanah Interior-21052025+5-6282183184641 -ilham - NEW
A143: 174904221976312 | B143: R10 | C143: 120225924609850694 | D143: Amanah Interior | E143: 6282183184641 | F143: 45832 | G143: 41 | H143: 55-64 | I143: 34695.652 | J143: 5 | K143: 1596 | L143: 0 | M143: 0 | N143: 0 | O143: OFF- Amanah Interior-21052025+5-6282183184641 -ilham - NEW
A144: 174904221976312 | B144: R10 | C144: 120225924609850694 | D144: Amanah Interior | E144: 6282183184641 | F144: 45832 | G144: 8 | H144: 65+ | I144: 10888.889 | J144: 0 | K144: 98 | L144: 0 | M144: 0 | N144: 0 | O144: OFF- Amanah Interior-21052025+5-6282183184641 -ilham - NEW
A145: 174904221976312 | B145: R10 | C145: 120225732846460694 | D145: SMA Madina | E145: 6281348555887 | F145: 45832 | G145: 137 | H145: 25-34 | I145: 9556.962 | J145: 6 | K145: 1510 | L145: 0 | M145: 35 | N145: 0 | O145: ON-SMA Madina-29052025+20-6281348555887
A146: 174904221976312 | B146: R10 | C146: 120225732846460694 | D146: SMA Madina | E146: 6281348555887 | F146: 45832 | G146: 464 | H146: 35-44 | I146: 12599.634 | J146: 17 | K146: 6892 | L146: 0 | M146: 151 | N146: 0 | O146: ON-SMA Madina-29052025+20-6281348555887
A147: 174904221976312 | B147: R10 | C147: 120225732846460694 | D147: SMA Madina | E147: 6281348555887 | F147: 45832 | G147: 164 | H147: 45-54 | I147: 18453.608 | J147: 5 | K147: 3580 | L147: 0 | M147: 58 | N147: 0 | O147: ON-SMA Madina-29052025+20-6281348555887
A148: 174904221976312 | B148: R10 | C148: 120225732846460694 | D148: SMA Madina | E148: 6281348555887 | F148: 45832 | G148: 10 | H148: 55-64 | I148: 85833.333 | J148: 1 | K148: 1030 | L148: 0 | M148: 5 | N148: 0 | O148: ON-SMA Madina-29052025+20-6281348555887
A149: 174904221976312 | B149: R10 | C149: 120225732846460694 | D149: SMA Madina | E149: 6281348555887 | F149: 45832 | G149: 12 | H149: 65+ | I149: 5875 | J149: 3 | K149: 94 | L149: 0 | M149: 4 | N149: 0 | O149: ON-SMA Madina-29052025+20-6281348555887
A150: 174904221976312 | B150: R10 | C150: 120225575002440694 | D150: Toko Emas Sembiring | E150: 6281263113266 | F150: 45832 | G150: 39 | H150: 18-24 | I150: 6375 | J150: 2 | K150: 306 | L150: 0 | M150: 0 | N150: 1 | O150: ON-Toko Emas Sembiring-15052025+30-6281263113266-Ilham - 2 - RCVR
... A286: 174904221976312 | B286: R10 | C286: 120226464082810694 | D286: Yuzef homestay | E286: 628988759290 | F286: 45832 | G286: 20 | H286: 65+ | I286: 33269.231 | J286: 4 | K286: 865 | L286: 0 | M286: 3 | N286: 0 | O286: ON-Yuzef homestay-11062025+13-628988759290
A287: 174904221976312 | B287: R10 | C287: 120226351656870694 | D287: Rodrimar Aifunan Fresku | F287: 45832 | G287: 1428 | H287: 18-24 | I287: 1318.8602 | J287: 18 | K287: 1944 | L287: 0 | M287: 84 | N287: 0 | O287: ON-Rodrimar Aifunan Fresku-16052025+14-67077619002-Ilham - 2 - Copy
A288: 174904221976312 | B288: R10 | C288: 120226351656870694 | D288: Rodrimar Aifunan Fresku | F288: 45832 | G288: 1602 | H288: 25-34 | I288: 1786.6667 | J288: 23 | K288: 3082 | L288: 0 | M288: 148 | N288: 0 | O288: ON-Rodrimar Aifunan Fresku-16052025+14-67077619002-Ilham - 2 - Copy
A289: 174904221976312 | B289: R10 | C289: 120226351656870694 | D289: Rodrimar Aifunan Fresku | F289: 45832 | G289: 1420 | H289: 35-44 | I289: 2507.0944 | J289: 26 | K289: 4064 | L289: 0 | M289: 207 | N289: 0 | O289: ON-Rodrimar Aifunan Fresku-16052025+14-67077619002-Ilham - 2 - Copy
A290: 174904221976312 | B290: R10 | C290: 120226351656870694 | D290: Rodrimar Aifunan Fresku | F290: 45832 | G290: 560 | H290: 45-54 | I290: 3153.5948 | J290: 10 | K290: 1930 | L290: 0 | M290: 62 | N290: 0 | O290: ON-Rodrimar Aifunan Fresku-16052025+14-67077619002-Ilham - 2 - Copy
A291: 174904221976312 | B291: R10 | C291: 120226351656870694 | D291: Rodrimar Aifunan Fresku | F291: 45832 | G291: 122 | H291: 55-64 | I291: 3195.9459 | J291: 5 | K291: 473 | L291: 0 | M291: 13 | N291: 0 | O291: ON-Rodrimar Aifunan Fresku-16052025+14-67077619002-Ilham - 2 - Copy
A292: 174904221976312 | B292: R10 | C292: 120226351656870694 | D292: Rodrimar Aifunan Fresku | F292: 45832 | G292: 94 | H292: 65+ | I292: 2410.7143 | J292: 3 | K292: 270 | L292: 0 | M292: 9 | N292: 0 | O292: ON-Rodrimar Aifunan Fresku-16052025+14-67077619002-Ilham - 2 - Copy
A293: 174904221976312 | B293: R10 | C293: 120225924609850694 | D293: Amanah Interior | E293: 6282183184641 | F293: 45832 | G293: 15 | H293: 18-24 | I293: 9533.3333 | J293: 0 | K293: 143 | L293: 0 | M293: 0 | N293: 0 | O293: OFF- Amanah Interior-21052025+5-6282183184641 -ilham - NEW
A294: 174904221976312 | B294: R10 | C294: 120225924609850694 | D294: Amanah Interior | E294: 6282183184641 | F294: 45832 | G294: 101 | H294: 25-34 | I294: 19992.908 | J294: 0 | K294: 2819 | L294: 0 | M294: 0 | N294: 0 | O294: OFF- Amanah Interior-21052025+5-6282183184641 -ilham - NEW
A295: 174904221976312 | B295: R10 | C295: 120225924609850694 | D295: Amanah Interior | E295: 6282183184641 | F295: 45832 | G295: 113 | H295: 35-44 | I295: 18957.317 | J295: 3 | K295: 3109 | L295: 0 | M295: 0 | N295: 0 | O295: OFF- Amanah Interior-21052025+5-6282183184641 -ilham - NEW
A296: 174904221976312 | B296: R10 | C296: 120225924609850694 | D296: Amanah Interior | E296: 6282183184641 | F296: 45832 | G296: 91 | H296: 45-54 | I296: 36756.303 | J296: 7 | K296: 4374 | L296: 0 | M296: 2 | N296: 0 | O296: OFF- Amanah Interior-21052025+5-6282183184641 -ilham - NEW
A297: 174904221976312 | B297: R10 | C297: 120225924609850694 | D297: Amanah Interior | E297: 6282183184641 | F297: 45832 | G297: 41 | H297: 55-64 | I297: 34063.83 | J297: 5 | K297: 1601 | L297: 0 | M297: 0 | N297: 0 | O297: OFF- Amanah Interior-21052025+5-6282183184641 -ilham - NEW
A298: 174904221976312 | B298: R10 | C298: 120225924609850694 | D298: Amanah Interior | E298: 6282183184641 | F298: 45832 | G298: 8 | H298: 65+ | I298: 10888.889 | J298: 0 | K298: 98 | L298: 0 | M298: 0 | N298: 0 | O298: OFF- Amanah Interior-21052025+5-6282183184641 -ilham - NEW
A299: 174904221976312 | B299: R10 | C299: 120225732846460694 | D299: SMA Madina | E299: 6281348555887 | F299: 45832 | G299: 138 | H299: 25-34 | I299: 9944.0994 | J299: 6 | K299: 1601 | L299: 0 | M299: 36 | N299: 0 | O299: ON-SMA Madina-29052025+20-6281348555887
A300: 174904221976312 | B300: R10 | C300: 120225732846460694 | D300: SMA Madina | E300: 6281348555887 | F300: 45832 | G300: 471 | H300: 35-44 | I300: 12549.372 | J300: 17 | K300: 6990 | L300: 0 | M300: 156 | N300: 0 | O300: ON-SMA Madina-29052025+20-6281348555887
A301: 174904221976312 | B301: R10 | C301: 120225732846460694 | D301: SMA Madina | E301: 6281348555887 | F301: 45832 | G301: 165 | H301: 45-54 | I301: 18369.231 | J301: 5 | K301: 3582 | L301: 0 | M301: 59 | N301: 0 | O301: ON-SMA Madina-29052025+20-6281348555887
A302: 174904221976312 | B302: R10 | C302: 120225732846460694 | D302: SMA Madina | E302: 6281348555887 | F302: 45832 | G302: 10 | H302: 55-64 | I302: 85833.333 | J302: 1 | K302: 1030 | L302: 0 | M302: 5 | N302: 0 | O302: ON-SMA Madina-29052025+20-6281348555887
A303: 174904221976312 | B303: R10 | C303: 120225732846460694 | D303: SMA Madina | E303: 6281348555887 | F303: 45832 | G303: 14 | H303: 65+ | I303: 6222.2222 | J303: 3 | K303: 112 | L303: 0 | M303: 4 | N303: 0 | O303: ON-SMA Madina-29052025+20-6281348555887
A304: 174904221976312 | B304: R10 | C304: 120225575002440694 | D304: Toko Emas Sembiring | E304: 6281263113266 | F304: 45832 | G304: 39 | H304: 18-24 | I304: 6395.8333 | J304: 2 | K304: 307 | L304: 0 | M304: 0 | N304: 1 | O304: ON-Toko Emas Sembiring-15052025+30-6281263113266-Ilham - 2 - RCVR
... A458: 174904221976312 | B458: R10 | C458: 120226464082810694 | D458: Yuzef homestay | E458: 628988759290 | F458: 45833 | G458: 1 | H458: 65+ | I458: 9000 | J458: 0 | K458: 9 | L458: 0 | M458: 0 | N458: 0 | O458: ON-Yuzef homestay-11062025+13-628988759290
A459: 174904221976312 | B459: R10 | C459: 120226351656870694 | D459: Rodrimar Aifunan Fresku | F459: 45833 | G459: 799 | H459: 18-24 | I459: 1172.6954 | J459: 8 | K459: 1005 | L459: 0 | M459: 85 | N459: 0 | O459: ON-Rodrimar Aifunan Fresku-16052025+14-67077619002-Ilham - 2 - Copy
A460: 174904221976312 | B460: R10 | C460: 120226351656870694 | D460: Rodrimar Aifunan Fresku | F460: 45833 | G460: 1139 | H460: 25-34 | I460: 1721.5815 | J460: 17 | K460: 2090 | L460: 0 | M460: 146 | N460: 0 | O460: ON-Rodrimar Aifunan Fresku-16052025+14-67077619002-Ilham - 2 - Copy
A461: 174904221976312 | B461: R10 | C461: 120226351656870694 | D461: Rodrimar Aifunan Fresku | F461: 45833 | G461: 808 | H461: 35-44 | I461: 2388.1808 | J461: 9 | K461: 2061 | L461: 0 | M461: 168 | N461: 0 | O461: ON-Rodrimar Aifunan Fresku-16052025+14-67077619002-Ilham - 2 - Copy
A462: 174904221976312 | B462: R10 | C462: 120226351656870694 | D462: Rodrimar Aifunan Fresku | F462: 45833 | G462: 286 | H462: 45-54 | I462: 3227.2727 | J462: 6 | K462: 994 | L462: 1 | M462: 68 | N462: 0 | O462: ON-Rodrimar Aifunan Fresku-16052025+14-67077619002-Ilham - 2 - Copy
A463: 174904221976312 | B463: R10 | C463: 120226351656870694 | D463: Rodrimar Aifunan Fresku | F463: 45833 | G463: 58 | H463: 55-64 | I463: 3892.3077 | J463: 1 | K463: 253 | L463: 1 | M463: 22 | N463: 0 | O463: ON-Rodrimar Aifunan Fresku-16052025+14-67077619002-Ilham - 2 - Copy
A464: 174904221976312 | B464: R10 | C464: 120226351656870694 | D464: Rodrimar Aifunan Fresku | F464: 45833 | G464: 67 | H464: 65+ | I464: 3756.7568 | J464: 0 | K464: 278 | L464: 0 | M464: 7 | N464: 0 | O464: ON-Rodrimar Aifunan Fresku-16052025+14-67077619002-Ilham - 2 - Copy
A465: 174904221976312 | B465: R10 | C465: 120225732846460694 | D465: SMA Madina | E465: 6281348555887 | F465: 45833 | G465: 14 | H465: 25-34 | I465: 9285.7143 | J465: 0 | K465: 130 | L465: 0 | M465: 3 | N465: 0 | O465: ON-SMA Madina-29052025+20-6281348555887
A466: 174904221976312 | B466: R10 | C466: 120225732846460694 | D466: SMA Madina | E466: 6281348555887 | F466: 45833 | G466: 53 | H466: 35-44 | I466: 18586.207 | J466: 0 | K466: 1078 | L466: 0 | M466: 11 | N466: 0 | O466: ON-SMA Madina-29052025+20-6281348555887
A467: 174904221976312 | B467: R10 | C467: 120225732846460694 | D467: SMA Madina | E467: 6281348555887 | F467: 45833 | G467: 23 | H467: 45-54 | I467: 15000 | J467: 1 | K467: 345 | L467: 0 | M467: 6 | N467: 0 | O467: ON-SMA Madina-29052025+20-6281348555887
A468: 174904221976312 | B468: R10 | C468: 120225732846460694 | D468: SMA Madina | E468: 6281348555887 | F468: 45833 | G468: 2 | H468: 65+ | I468: 2000 | J468: 0 | K468: 4 | L468: 0 | M468: 0 | N468: 0 | O468: ON-SMA Madina-29052025+20-6281348555887
A469: 174904221976312 | B469: R10 | C469: 120225575002440694 | D469: Toko Emas Sembiring | E469: 6281263113266 | F469: 45833 | G469: 5 | H469: 18-24 | I469: 9200 | J469: 0 | K469: 46 | L469: 0 | M469: 1 | N469: 0 | O469: ON-Toko Emas Sembiring-15052025+30-6281263113266-Ilham - 2 - RCVR
A470: 174904221976312 | B470: R10 | C470: 120225575002440694 | D470: Toko Emas Sembiring | E470: 6281263113266 | F470: 45833 | G470: 35 | H470: 25-34 | I470: 7972.973 | J470: 1 | K470: 295 | L470: 0 | M470: 9 | N470: 0 | O470: ON-Toko Emas Sembiring-15052025+30-6281263113266-Ilham - 2 - RCVR
A471: 174904221976312 | B471: R10 | C471: 120225575002440694 | D471: Toko Emas Sembiring | E471: 6281263113266 | F471: 45833 | G471: 42 | H471: 35-44 | I471: 10136.364 | J471: 0 | K471: 446 | L471: 0 | M471: 4 | N471: 0 | O471: ON-Toko Emas Sembiring-15052025+30-6281263113266-Ilham - 2 - RCVR
A472: 174904221976312 | B472: R10 | C472: 120225575002440694 | D472: Toko Emas Sembiring | E472: 6281263113266 | F472: 45833 | G472: 26 | H472: 45-54 | I472: 9111.1111 | J472: 1 | K472: 246 | L472: 0 | M472: 11 | N472: 0 | O472: ON-Toko Emas Sembiring-15052025+30-6281263113266-Ilham - 2 - RCVR
A473: 174904221976312 | B473: R10 | C473: 120225575002440694 | D473: Toko Emas Sembiring | E473: 6281263113266 | F473: 45833 | G473: 16 | H473: 55-64 | I473: 11000 | J473: 1 | K473: 187 | L473: 0 | M473: 3 | N473: 0 | O473: ON-Toko Emas Sembiring-15052025+30-6281263113266-Ilham - 2 - RCVR
A474: 174904221976312 | B474: R10 | C474: 120225575002440694 | D474: Toko Emas Sembiring | E474: 6281263113266 | F474: 45833 | G474: 4 | H474: 65+ | I474: 6000 | J474: 0 | K474: 24 | L474: 0 | M474: 0 | N474: 0 | O474: ON-Toko Emas Sembiring-15052025+30-6281263113266-Ilham - 2 - RCVR
A475: 766589657993298 | B475: R06 | C475: 120228145715320235 | D475: PT Cahaya | E475: 6281293309300 | F475: 45833 | G475: 3 | H475: 18-24 | I475: 18333.333 | J475: 0 | K475: 55 | L475: 0 | M475: 0 | N475: 0 | O475: ON-PT Cahaya-14062025+5-6281293309300
A476: 766589657993298 | B476: R06 | C476: 120228145715320235 | D476: PT Cahaya | E476: 6281293309300 | F476: 45833 | G476: 12 | H476: 25-34 | I476: 35166.667 | J476: 0 | K476: 422 | L476: 0 | M476: 0 | N476: 0 | O476: ON-PT Cahaya-14062025+5-6281293309300
... A734: 174904221976312 | B734: R10 | C734: 120226464082810694 | D734: Yuzef homestay | E734: 628988759290 | F734: 45832 | G734: 20 | H734: 65+ | I734: 33230.769 | J734: 4 | K734: 864 | L734: 0 | M734: 3 | N734: 0 | O734: ON-Yuzef homestay-11062025+13-628988759290
A735: 174904221976312 | B735: R10 | C735: 120226351656870694 | D735: Rodrimar Aifunan Fresku | F735: 45832 | G735: 1428 | H735: 18-24 | I735: 1318.8602 | J735: 18 | K735: 1944 | L735: 0 | M735: 84 | N735: 0 | O735: ON-Rodrimar Aifunan Fresku-16052025+14-67077619002-Ilham - 2 - Copy
A736: 174904221976312 | B736: R10 | C736: 120226351656870694 | D736: Rodrimar Aifunan Fresku | F736: 45832 | G736: 1604 | H736: 25-34 | I736: 1784.9711 | J736: 23 | K736: 3088 | L736: 0 | M736: 150 | N736: 0 | O736: ON-Rodrimar Aifunan Fresku-16052025+14-67077619002-Ilham - 2 - Copy
A737: 174904221976312 | B737: R10 | C737: 120226351656870694 | D737: Rodrimar Aifunan Fresku | F737: 45832 | G737: 1420 | H737: 35-44 | I737: 2504.0049 | J737: 26 | K737: 4064 | L737: 0 | M737: 207 | N737: 0 | O737: ON-Rodrimar Aifunan Fresku-16052025+14-67077619002-Ilham - 2 - Copy
A738: 174904221976312 | B738: R10 | C738: 120226351656870694 | D738: Rodrimar Aifunan Fresku | F738: 45832 | G738: 560 | H738: 45-54 | I738: 3156.6069 | J738: 10 | K738: 1935 | L738: 0 | M738: 62 | N738: 0 | O738: ON-Rodrimar Aifunan Fresku-16052025+14-67077619002-Ilham - 2 - Copy
A739: 174904221976312 | B739: R10 | C739: 120226351656870694 | D739: Rodrimar Aifunan Fresku | F739: 45832 | G739: 122 | H739: 55-64 | I739: 3195.9459 | J739: 5 | K739: 473 | L739: 0 | M739: 13 | N739: 0 | O739: ON-Rodrimar Aifunan Fresku-16052025+14-67077619002-Ilham - 2 - Copy
A740: 174904221976312 | B740: R10 | C740: 120226351656870694 | D740: Rodrimar Aifunan Fresku | F740: 45832 | G740: 94 | H740: 65+ | I740: 2410.7143 | J740: 3 | K740: 270 | L740: 0 | M740: 9 | N740: 0 | O740: ON-Rodrimar Aifunan Fresku-16052025+14-67077619002-Ilham - 2 - Copy
A741: 174904221976312 | B741: R10 | C741: 120225924609850694 | D741: Amanah Interior | E741: 6282183184641 | F741: 45832 | G741: 15 | H741: 18-24 | I741: 9533.3333 | J741: 0 | K741: 143 | L741: 0 | M741: 0 | N741: 0 | O741: OFF- Amanah Interior-21052025+5-6282183184641 -ilham - NEW
A742: 174904221976312 | B742: R10 | C742: 120225924609850694 | D742: Amanah Interior | E742: 6282183184641 | F742: 45832 | G742: 102 | H742: 25-34 | I742: 19950.704 | J742: 0 | K742: 2833 | L742: 0 | M742: 0 | N742: 0 | O742: OFF- Amanah Interior-21052025+5-6282183184641 -ilham - NEW
A743: 174904221976312 | B743: R10 | C743: 120225924609850694 | D743: Amanah Interior | E743: 6282183184641 | F743: 45832 | G743: 117 | H743: 35-44 | I743: 21964.912 | J743: 3 | K743: 3756 | L743: 0 | M743: 0 | N743: 0 | O743: OFF- Amanah Interior-21052025+5-6282183184641 -ilham - NEW
A744: 174904221976312 | B744: R10 | C744: 120225924609850694 | D744: Amanah Interior | E744: 6282183184641 | F744: 45832 | G744: 91 | H744: 45-54 | I744: 36731.092 | J744: 7 | K744: 4371 | L744: 0 | M744: 2 | N744: 0 | O744: OFF- Amanah Interior-21052025+5-6282183184641 -ilham - NEW
A745: 174904221976312 | B745: R10 | C745: 120225924609850694 | D745: Amanah Interior | E745: 6282183184641 | F745: 45832 | G745: 43 | H745: 55-64 | I745: 34795.918 | J745: 5 | K745: 1705 | L745: 0 | M745: 0 | N745: 0 | O745: OFF- Amanah Interior-21052025+5-6282183184641 -ilham - NEW
A746: 174904221976312 | B746: R10 | C746: 120225924609850694 | D746: Amanah Interior | E746: 6282183184641 | F746: 45832 | G746: 8 | H746: 65+ | I746: 10888.889 | J746: 0 | K746: 98 | L746: 0 | M746: 0 | N746: 0 | O746: OFF- Amanah Interior-21052025+5-6282183184641 -ilham - NEW
A747: 174904221976312 | B747: R10 | C747: 120225732846460694 | D747: SMA Madina | E747: 6281348555887 | F747: 45832 | G747: 140 | H747: 25-34 | I747: 10625.767 | J747: 6 | K747: 1732 | L747: 0 | M747: 37 | N747: 0 | O747: ON-SMA Madina-29052025+20-6281348555887
A748: 174904221976312 | B748: R10 | C748: 120225732846460694 | D748: SMA Madina | E748: 6281348555887 | F748: 45832 | G748: 473 | H748: 35-44 | I748: 12517.857 | J748: 17 | K748: 7010 | L748: 0 | M748: 156 | N748: 0 | O748: ON-SMA Madina-29052025+20-6281348555887
A749: 174904221976312 | B749: R10 | C749: 120225732846460694 | D749: SMA Madina | E749: 6281348555887 | F749: 45832 | G749: 166 | H749: 45-54 | I749: 18321.429 | J749: 5 | K749: 3591 | L749: 0 | M749: 59 | N749: 0 | O749: ON-SMA Madina-29052025+20-6281348555887
A750: 174904221976312 | B750: R10 | C750: 120225732846460694 | D750: SMA Madina | E750: 6281348555887 | F750: 45832 | G750: 10 | H750: 55-64 | I750: 85833.333 | J750: 1 | K750: 1030 | L750: 0 | M750: 5 | N750: 0 | O750: ON-SMA Madina-29052025+20-6281348555887
A751: 174904221976312 | B751: R10 | C751: 120225732846460694 | D751: SMA Madina | E751: 6281348555887 | F751: 45832 | G751: 14 | H751: 65+ | I751: 6222.2222 | J751: 3 | K751: 112 | L751: 0 | M751: 4 | N751: 0 | O751: ON-SMA Madina-29052025+20-6281348555887
A752: 174904221976312 | B752: R10 | C752: 120225575002440694 | D752: Toko Emas Sembiring | E752: 6281263113266 | F752: 45832 | G752: 39 | H752: 18-24 | I752: 6375 | J752: 2 | K752: 306 | L752: 0 | M752: 0 | N752: 1 | O752: ON-Toko Emas Sembiring-15052025+30-6281263113266-Ilham - 2 - RCVR
... A846: 766589657993298 | B846: R06 | C846: 120227599304890235 | D846: AR Kontraktor | E846: 6281316155059 | F846: 45832 | G846: 50 | H846: 65+ | I846: 44294.118 | J846: 1 | K846: 2259 | L846: 0 | M846: 29 | N846: 0 | O846: ON-AR Kontraktor-15062025+5-6281316155059

Sheet Performa Iklan Klien By Lokasi
A1: AkunIklanId | B1: NamaAkun | C1: KampanyeId | D1: Nama Usaha | E1: Whatsapp | F1: Tanggal | G1: Lokasi | H1: Tipe Lokasi | I1: Reach | J1: Impression | K1: LinkKlik | L1: CPM | M1: Spend | N1: KlikWA | O1: VideoView | P1: Komentar | Q1: Nama Kampanye
A2: 759724529202804 | B2: R11 | C2: 120229046011260200 | D2: Abadi Tehnik | E2: 6285711667433 | F2: 45832 | G2: Banten | H2: region | I2: 113 | J2: 121 | K2: 1 | L2: 8958.6777 | M2: 1084 | N2: 0 | O2: 0 | P2: 0 | Q2: ON-Abadi Tehnik-21062025+5-6285711667433
A3: 759724529202804 | B3: R11 | C3: 120229046011260200 | D3: Abadi Tehnik | E3: 6285711667433 | F3: 45832 | G3: Jakarta | H3: region | I3: 379 | J3: 430 | K3: 11 | L3: 13213.953 | M3: 5682 | N3: 0 | O3: 0 | P3: 0 | Q3: ON-Abadi Tehnik-21062025+5-6285711667433
A4: 759724529202804 | B4: R11 | C4: 120229046011260200 | D4: Abadi Tehnik | E4: 6285711667433 | F4: 45832 | G4: West Java | H4: region | I4: 415 | J4: 479 | K4: 3 | L4: 9350.7307 | M4: 4479 | N4: 1 | O4: 0 | P4: 0 | Q4: ON-Abadi Tehnik-21062025+5-6285711667433
A5: 759724529202804 | B5: R11 | C5: 120229044952270200 | D5: Alfie salon | E5: 6285775986977 | F5: 45832 | G5: Jakarta | H5: region | I5: 226 | J5: 257 | K5: 3 | L5: 51225.681 | M5: 13165 | N5: 0 | O5: 0 | P5: 0 | Q5: ON-Alfie salon-19062025+5-6285775986977 - Salin
A6: 759724529202804 | B6: R11 | C6: 120229044952270200 | D6: Alfie salon | E6: 6285775986977 | F6: 45832 | G6: West Java | H6: region | I6: 29 | J6: 30 | K6: 0 | L6: 30133.333 | M6: 904 | N6: 0 | O6: 0 | P6: 0 | Q6: ON-Alfie salon-19062025+5-6285775986977 - Salin
A7: 759724529202804 | B7: R11 | C7: 120229044725650200 | D7: MA | E7: 6281904501876 | F7: 45832 | G7: Central Java | H7: region | I7: 994 | J7: 1319 | K7: 10 | L7: 9405.6103 | M7: 12406 | N7: 0 | O7: 1 | P7: 0 | Q7: ON-MA- AL-21062025+7-6281904501876
A8: 759724529202804 | B8: R11 | C8: 120229044725650200 | D8: MA | E8: 6281904501876 | F8: 45832 | G8: Special Region of Yogyakarta | H8: region | I8: 2 | J8: 2 | K8: 0 | L8: 9000 | M8: 18 | N8: 0 | O8: 0 | P8: 0 | Q8: ON-MA- AL-21062025+7-6281904501876
A9: 759724529202804 | B9: R11 | C9: 120229043131290200 | D9: Terafis Sinergi | E9: 6281253792753 | F9: 45832 | G9: East Kalimantan | H9: region | I9: 666 | J9: 916 | K9: 14 | L9: 13713.974 | M9: 12562 | N9: 1 | O9: 0 | P9: 0 | Q9: ON-Terafis Sinergi-22062025+5-6281253792753
A10: 759724529202804 | B10: R11 | C10: 120229042741890200 | D10: Deriano | E10: 6282122880328 | F10: 45832 | G10: Aceh | H10: region | I10: 5 | J10: 5 | K10: 0 | L10: 128200 | M10: 641 | N10: 0 | O10: 0 | P10: 0 | Q10: ON-Deriano-20062025+5-6282122880328
A11: 759724529202804 | B11: R11 | C11: 120229042741890200 | D11: Deriano | E11: 6282122880328 | F11: 45832 | G11: Banten | H11: region | I11: 3 | J11: 3 | K11: 0 | L11: 16333.333 | M11: 49 | N11: 0 | O11: 0 | P11: 0 | Q11: ON-Deriano-20062025+5-6282122880328
A12: 759724529202804 | B12: R11 | C12: 120229042741890200 | D12: Deriano | E12: 6282122880328 | F12: 45832 | G12: Bengkulu | H12: region | I12: 4 | J12: 5 | K12: 0 | L12: 61600 | M12: 308 | N12: 0 | O12: 0 | P12: 0 | Q12: ON-Deriano-20062025+5-6282122880328
A13: 759724529202804 | B13: R11 | C13: 120229042741890200 | D13: Deriano | E13: 6282122880328 | F13: 45832 | G13: Central Java | H13: region | I13: 12 | J13: 12 | K13: 1 | L13: 106583.33 | M13: 1279 | N13: 0 | O13: 0 | P13: 0 | Q13: ON-Deriano-20062025+5-6282122880328
... A108: 174904221976312 | B108: R10 | C108: 120226464082810694 | D108: Yuzef homestay | E108: 628988759290 | F108: 45832 | G108: Riau | H108: region | I108: 795 | J108: 1069 | K108: 42 | L108: 12371.375 | M108: 13225 | N108: 2 | O108: 62 | P108: 0 | Q108: ON-Yuzef homestay-11062025+13-628988759290
A109: 174904221976312 | B109: R10 | C109: 120226351656870694 | D109: Rodrimar Aifunan Fresku | F109: 45832 | G109: East Nusa Tenggara | H109: region | I109: 2 | J109: 3 | K109: 0 | L109: 6000 | M109: 18 | N109: 0 | O109: 0 | P109: 0 | Q109: ON-Rodrimar Aifunan Fresku-16052025+14-67077619002-Ilham - 2 - Copy
A110: 174904221976312 | B110: R10 | C110: 120226351656870694 | D110: Rodrimar Aifunan Fresku | F110: 45832 | G110: Timor-Leste | H110: region | I110: 5209 | J110: 5676 | K110: 84 | L110: 2062.7202 | M110: 11708 | N110: 0 | O110: 521 | P110: 0 | Q110: ON-Rodrimar Aifunan Fresku-16052025+14-67077619002-Ilham - 2 - Copy
A111: 174904221976312 | B111: R10 | C111: 120225924609850694 | D111: Amanah Interior | E111: 6282183184641 | F111: 45832 | G111: Jambi | H111: region | I111: 364 | J111: 485 | K111: 15 | L111: 24661.856 | M111: 11961 | N111: 0 | O111: 1 | P111: 0 | Q111: OFF- Amanah Interior-21052025+5-6282183184641 -ilham - NEW
A112: 174904221976312 | B112: R10 | C112: 120225924609850694 | D112: Amanah Interior | E112: 6282183184641 | F112: 45832 | G112: South Sumatra | H112: region | I112: 2 | J112: 2 | K112: 0 | L112: 2500 | M112: 5 | N112: 0 | O112: 0 | P112: 0 | Q112: OFF- Amanah Interior-21052025+5-6282183184641 -ilham - NEW
A113: 174904221976312 | B113: R10 | C113: 120225732846460694 | D113: SMA Madina | E113: 6281348555887 | F113: 45832 | G113: East Kalimantan | H113: region | I113: 787 | J113: 927 | K113: 32 | L113: 14138.08 | M113: 13106 | N113: 0 | O113: 253 | P113: 0 | Q113: ON-SMA Madina-29052025+20-6281348555887
A114: 174904221976312 | B114: R10 | C114: 120225575002440694 | D114: Toko Emas Sembiring | E114: 6281263113266 | F114: 45832 | G114: North Sumatra | H114: region | I114: 1251 | J114: 1493 | K114: 61 | L114: 9444.0723 | M114: 14100 | N114: 5 | O114: 0 | P114: 1 | Q114: ON-Toko Emas Sembiring-15052025+30-6281263113266-Ilham - 2 - RCVR
A115: 759724529202804 | B115: R11 | C115: 120229046011260200 | D115: Abadi Tehnik | E115: 6285711667433 | F115: 45832 | G115: Banten | H115: region | I115: 142 | J115: 155 | K115: 1 | L115: 9580.6452 | M115: 1485 | N115: 0 | O115: 0 | P115: 0 | Q115: ON-Abadi Tehnik-21062025+5-6285711667433
A116: 759724529202804 | B116: R11 | C116: 120229046011260200 | D116: Abadi Tehnik | E116: 6285711667433 | F116: 45832 | G116: Jakarta | H116: region | I116: 472 | J116: 549 | K116: 14 | L116: 13058.288 | M116: 7169 | N116: 1 | O116: 0 | P116: 0 | Q116: ON-Abadi Tehnik-21062025+5-6285711667433
A117: 759724529202804 | B117: R11 | C117: 120229046011260200 | D117: Abadi Tehnik | E117: 6285711667433 | F117: 45832 | G117: West Java | H117: region | I117: 502 | J117: 595 | K117: 3 | L117: 8791.5966 | M117: 5231 | N117: 1 | O117: 0 | P117: 0 | Q117: ON-Abadi Tehnik-21062025+5-6285711667433
A118: 759724529202804 | B118: R11 | C118: 120229044952270200 | D118: Alfie salon | E118: 6285775986977 | F118: 45832 | G118: Jakarta | H118: region | I118: 229 | J118: 260 | K118: 3 | L118: 50896.154 | M118: 13233 | N118: 0 | O118: 0 | P118: 0 | Q118: ON-Alfie salon-19062025+5-6285775986977 - Salin
A119: 759724529202804 | B119: R11 | C119: 120229044952270200 | D119: Alfie salon | E119: 6285775986977 | F119: 45832 | G119: West Java | H119: region | I119: 29 | J119: 30 | K119: 0 | L119: 30133.333 | M119: 904 | N119: 0 | O119: 0 | P119: 0 | Q119: ON-Alfie salon-19062025+5-6285775986977 - Salin
A120: 759724529202804 | B120: R11 | C120: 120229044725650200 | D120: MA | E120: 6281904501876 | F120: 45832 | G120: Central Java | H120: region | I120: 1133 | J120: 1520 | K120: 12 | L120: 9584.2105 | M120: 14568 | N120: 0 | O120: 1 | P120: 0 | Q120: ON-MA- AL-21062025+7-6281904501876
A121: 759724529202804 | B121: R11 | C121: 120229044725650200 | D121: MA | E121: 6281904501876 | F121: 45832 | G121: Special Region of Yogyakarta | H121: region | I121: 2 | J121: 2 | K121: 0 | L121: 9000 | M121: 18 | N121: 0 | O121: 0 | P121: 0 | Q121: ON-MA- AL-21062025+7-6281904501876
A122: 759724529202804 | B122: R11 | C122: 120229043131290200 | D122: Terafis Sinergi | E122: 6281253792753 | F122: 45832 | G122: East Kalimantan | H122: region | I122: 800 | J122: 1106 | K122: 16 | L122: 12995.479 | M122: 14373 | N122: 1 | O122: 0 | P122: 0 | Q122: ON-Terafis Sinergi-22062025+5-6281253792753
... A221: 174904221976312 | B221: R10 | C221: 120226464082810694 | D221: Yuzef homestay | E221: 628988759290 | F221: 45832 | G221: Riau | H221: region | I221: 807 | J221: 1085 | K221: 42 | L221: 12369.585 | M221: 13421 | N221: 2 | O221: 62 | P221: 0 | Q221: ON-Yuzef homestay-11062025+13-628988759290
A222: 174904221976312 | B222: R10 | C222: 120226351656870694 | D222: Rodrimar Aifunan Fresku | F222: 45832 | G222: East Nusa Tenggara | H222: region | I222: 2 | J222: 3 | K222: 0 | L222: 6000 | M222: 18 | N222: 0 | O222: 0 | P222: 0 | Q222: ON-Rodrimar Aifunan Fresku-16052025+14-67077619002-Ilham - 2 - Copy
A223: 174904221976312 | B223: R10 | C223: 120226351656870694 | D223: Rodrimar Aifunan Fresku | F223: 45832 | G223: Timor-Leste | H223: region | I223: 5225 | J223: 5690 | K223: 85 | L223: 2064.1476 | M223: 11745 | N223: 0 | O223: 523 | P223: 0 | Q223: ON-Rodrimar Aifunan Fresku-16052025+14-67077619002-Ilham - 2 - Copy
A224: 174904221976312 | B224: R10 | C224: 120225924609850694 | D224: Amanah Interior | E224: 6282183184641 | F224: 45832 | G224: Jambi | H224: region | I224: 367 | J224: 492 | K224: 15 | L224: 24636.179 | M224: 12121 | N224: 0 | O224: 2 | P224: 0 | Q224: OFF- Amanah Interior-21052025+5-6282183184641 -ilham - NEW
A225: 174904221976312 | B225: R10 | C225: 120225924609850694 | D225: Amanah Interior | E225: 6282183184641 | F225: 45832 | G225: South Sumatra | H225: region | I225: 3 | J225: 3 | K225: 0 | L225: 7666.6667 | M225: 23 | N225: 0 | O225: 0 | P225: 0 | Q225: OFF- Amanah Interior-21052025+5-6282183184641 -ilham - NEW
A226: 174904221976312 | B226: R10 | C226: 120225732846460694 | D226: SMA Madina | E226: 6281348555887 | F226: 45832 | G226: East Kalimantan | H226: region | I226: 798 | J226: 943 | K226: 32 | L226: 14119.83 | M226: 13315 | N226: 0 | O226: 260 | P226: 0 | Q226: ON-SMA Madina-29052025+20-6281348555887
A227: 174904221976312 | B227: R10 | C227: 120225575002440694 | D227: Toko Emas Sembiring | E227: 6281263113266 | F227: 45832 | G227: North Sumatra | H227: region | I227: 1268 | J227: 1520 | K227: 65 | L227: 9481.5789 | M227: 14412 | N227: 5 | O227: 0 | P227: 1 | Q227: ON-Toko Emas Sembiring-15052025+30-6281263113266-Ilham - 2 - RCVR
A228: 766589657993298 | B228: R06 | C228: 120228082065700235 | D228: Antoni kontruksi | E228: 6281383434602 | F228: 45832 | G228: Jakarta | H228: region | I228: 234 | J228: 248 | K228: 4 | L228: 33306.452 | M228: 8260 | N228: 0 | O228: 75 | P228: 1 | Q228: ON-Antoni kontruksi-22062025+5-6281383434602
A229: 766589657993298 | B229: R06 | C229: 120228082065700235 | D229: Antoni kontruksi | E229: 6281383434602 | F229: 45832 | G229: West Java | H229: region | I229: 147 | J229: 159 | K229: 2 | L229: 29578.616 | M229: 4703 | N229: 1 | O229: 51 | P229: 0 | Q229: ON-Antoni kontruksi-22062025+5-6281383434602
A230: 766589657993298 | B230: R06 | C230: 120228074309660235 | D230: Jaya Lasindo | E230: 6281383899119 | F230: 45832 | G230: Jakarta | H230: region | I230: 432 | J230: 479 | K230: 11 | L230: 18517.745 | M230: 8870 | N230: 1 | O230: 0 | P230: 0 | Q230: ON-Jaya Lasindo-19062025+5-6281383899119
A231: 766589657993298 | B231: R06 | C231: 120228074309660235 | D231: Jaya Lasindo | E231: 6281383899119 | F231: 45832 | G231: West Java | H231: region | I231: 158 | J231: 174 | K231: 2 | L231: 24879.31 | M231: 4329 | N231: 0 | O231: 0 | P231: 0 | Q231: ON-Jaya Lasindo-19062025+5-6281383899119
A232: 759724529202804 | B232: R11 | C232: 120229127021080200 | D232: Lubijo Berkah | E232: 6281233038880 | F232: 45833 | G232: Central Java | H232: region | I232: 40 | J232: 40 | K232: 1 | L232: 89200 | M232: 3568 | N232: 0 | O232: 0 | P232: 0 | Q232: ON-Lubijo Berkah-23062025+10-6281233038880
A233: 759724529202804 | B233: R11 | C233: 120229127021080200 | D233: Lubijo Berkah | E233: 6281233038880 | F233: 45833 | G233: Special Region of Yogyakarta | H233: region | I233: 12 | J233: 12 | K233: 0 | L233: 50583.333 | M233: 607 | N233: 0 | O233: 0 | P233: 0 | Q233: ON-Lubijo Berkah-23062025+10-6281233038880
A234: 759724529202804 | B234: R11 | C234: 120229127021080200 | D234: Lubijo Berkah | E234: 6281233038880 | F234: 45833 | G234: Central Java | H234: region | I234: 40 | J234: 40 | K234: 1 | L234: 89200 | M234: 3568 | N234: 0 | O234: 0 | P234: 0 | Q234: ON-Lubijo Berkah-23062025+10-6281233038880
A235: 759724529202804 | B235: R11 | C235: 120229127021080200 | D235: Lubijo Berkah | E235: 6281233038880 | F235: 45833 | G235: Special Region of Yogyakarta | H235: region | I235: 12 | J235: 12 | K235: 0 | L235: 50583.333 | M235: 607 | N235: 0 | O235: 0 | P235: 0 | Q235: ON-Lubijo Berkah-23062025+10-6281233038880
... A318: 174904221976312 | B318: R10 | C318: 120226464082810694 | D318: Yuzef homestay | E318: 628988759290 | F318: 45833 | G318: Riau | H318: region | I318: 114 | J318: 130 | K318: 4 | L318: 11184.615 | M318: 1454 | N318: 0 | O318: 29 | P318: 0 | Q318: ON-Yuzef homestay-11062025+13-628988759290
A319: 174904221976312 | B319: R10 | C319: 120226351656870694 | D319: Rodrimar Aifunan Fresku | F319: 45833 | G319: East Nusa Tenggara | H319: region | I319: 4 | J319: 4 | K319: 0 | L319: 500 | M319: 2 | N319: 0 | O319: 0 | P319: 0 | Q319: ON-Rodrimar Aifunan Fresku-16052025+14-67077619002-Ilham - 2 - Copy
A320: 174904221976312 | B320: R10 | C320: 120226351656870694 | D320: Rodrimar Aifunan Fresku | F320: 45833 | G320: Timor-Leste | H320: region | I320: 2983 | J320: 3377 | K320: 41 | L320: 1977.7909 | M320: 6679 | N320: 2 | O320: 462 | P320: 0 | Q320: ON-Rodrimar Aifunan Fresku-16052025+14-67077619002-Ilham - 2 - Copy
A321: 174904221976312 | B321: R10 | C321: 120225732846460694 | D321: SMA Madina | E321: 6281348555887 | F321: 45833 | G321: East Kalimantan | H321: region | I321: 94 | J321: 98 | K321: 1 | L321: 16030.612 | M321: 1571 | N321: 0 | O321: 20 | P321: 0 | Q321: ON-SMA Madina-29052025+20-6281348555887
A322: 766589657993298 | B322: R06 | C322: 120228145715320235 | D322: PT Cahaya | E322: 6281293309300 | F322: 45833 | G322: Banten | H322: region | I322: 5 | J322: 5 | K322: 2 | L322: 146800 | M322: 734 | N322: 0 | O322: 0 | P322: 0 | Q322: ON-PT Cahaya-14062025+5-6281293309300
A323: 766589657993298 | B323: R06 | C323: 120228145715320235 | D323: PT Cahaya | E323: 6281293309300 | F323: 45833 | G323: Jakarta | H323: region | I323: 36 | J323: 37 | K323: 0 | L323: 47891.892 | M323: 1772 | N323: 0 | O323: 0 | P323: 0 | Q323: ON-PT Cahaya-14062025+5-6281293309300
A324: 766589657993298 | B324: R06 | C324: 120228145715320235 | D324: PT Cahaya | E324: 6281293309300 | F324: 45833 | G324: West Java | H324: region | I324: 12 | J324: 12 | K324: 0 | L324: 64750 | M324: 777 | N324: 0 | O324: 0 | P324: 0 | Q324: ON-PT Cahaya-14062025+5-6281293309300
A325: 766589657993298 | B325: R06 | C325: 120228082065700235 | D325: Antoni kontruksi | E325: 6281383434602 | F325: 45833 | G325: Jakarta | H325: region | I325: 17 | J325: 17 | K325: 0 | L325: 55411.765 | M325: 942 | N325: 0 | O325: 0 | P325: 0 | Q325: ON-Antoni kontruksi-22062025+5-6281383434602
A326: 766589657993298 | B326: R06 | C326: 120228082065700235 | D326: Antoni kontruksi | E326: 6281383434602 | F326: 45833 | G326: West Java | H326: region | I326: 8 | J326: 8 | K326: 0 | L326: 61625 | M326: 493 | N326: 0 | O326: 0 | P326: 0 | Q326: ON-Antoni kontruksi-22062025+5-6281383434602
A327: 766589657993298 | B327: R06 | C327: 120228074309660235 | D327: Jaya Lasindo | E327: 6281383899119 | F327: 45833 | G327: Jakarta | H327: region | I327: 16 | J327: 17 | K327: 0 | L327: 12882.353 | M327: 219 | N327: 0 | O327: 7 | P327: 0 | Q327: ON-Jaya Lasindo-19062025+5-6281383899119
A328: 766589657993298 | B328: R06 | C328: 120228074309660235 | D328: Jaya Lasindo | E328: 6281383899119 | F328: 45833 | G328: West Java | H328: region | I328: 8 | J328: 11 | K328: 0 | L328: 16181.818 | M328: 178 | N328: 0 | O328: 4 | P328: 0 | Q328: ON-Jaya Lasindo-19062025+5-6281383899119
A329: 766589657993298 | B329: R06 | C329: 120228014435350235 | D329: zada karya | E329: 6283135590465 | F329: 45833 | G329: East Java | H329: region | I329: 50 | J329: 53 | K329: 0 | L329: 28773.585 | M329: 1525 | N329: 0 | O329: 10 | P329: 0 | Q329: ON-zada karya-20062025+5-6283135590465
A330: 766589657993298 | B330: R06 | C330: 120227926808950235 | D330: Norma Property | E330: 6281514999073 | F330: 45833 | G330: Banten | H330: region | I330: 2 | J330: 2 | K330: 0 | L330: 10500 | M330: 21 | N330: 0 | O330: 2 | P330: 0 | Q330: ON-Norma Property-17062025+5-6281514999073
A331: 766589657993298 | B331: R06 | C331: 120227926808950235 | D331: Norma Property | E331: 6281514999073 | F331: 45833 | G331: Jakarta | H331: region | I331: 24 | J331: 26 | K331: 0 | L331: 36807.692 | M331: 957 | N331: 0 | O331: 10 | P331: 0 | Q331: ON-Norma Property-17062025+5-6281514999073
A332: 766589657993298 | B332: R06 | C332: 120227926808950235 | D332: Norma Property | E332: 6281514999073 | F332: 45833 | G332: West Java | H332: region | I332: 8 | J332: 10 | K332: 1 | L332: 47400 | M332: 474 | N332: 0 | O332: 3 | P332: 0 | Q332: ON-Norma Property-17062025+5-6281514999073
... A502: 174904221976312 | B502: R10 | C502: 120226464082810694 | D502: Yuzef homestay | E502: 628988759290 | F502: 45832 | G502: Riau | H502: region | I502: 809 | J502: 1089 | K502: 42 | L502: 12443.526 | M502: 13551 | N502: 2 | O502: 62 | P502: 0 | Q502: ON-Yuzef homestay-11062025+13-628988759290
A503: 174904221976312 | B503: R10 | C503: 120226351656870694 | D503: Rodrimar Aifunan Fresku | F503: 45832 | G503: East Nusa Tenggara | H503: region | I503: 2 | J503: 3 | K503: 0 | L503: 6000 | M503: 18 | N503: 0 | O503: 0 | P503: 0 | Q503: ON-Rodrimar Aifunan Fresku-16052025+14-67077619002-Ilham - 2 - Copy
A504: 174904221976312 | B504: R10 | C504: 120226351656870694 | D504: Rodrimar Aifunan Fresku | F504: 45832 | G504: Timor-Leste | H504: region | I504: 5226 | J504: 5697 | K504: 85 | L504: 2063.5422 | M504: 11756 | N504: 0 | O504: 525 | P504: 0 | Q504: ON-Rodrimar Aifunan Fresku-16052025+14-67077619002-Ilham - 2 - Copy
A505: 174904221976312 | B505: R10 | C505: 120225924609850694 | D505: Amanah Interior | E505: 6282183184641 | F505: 45832 | G505: Jambi | H505: region | I505: 374 | J505: 502 | K505: 15 | L505: 25663.347 | M505: 12883 | N505: 0 | O505: 2 | P505: 0 | Q505: OFF- Amanah Interior-21052025+5-6282183184641 -ilham - NEW
A506: 174904221976312 | B506: R10 | C506: 120225924609850694 | D506: Amanah Interior | E506: 6282183184641 | F506: 45832 | G506: South Sumatra | H506: region | I506: 3 | J506: 3 | K506: 0 | L506: 7666.6667 | M506: 23 | N506: 0 | O506: 0 | P506: 0 | Q506: OFF- Amanah Interior-21052025+5-6282183184641 -ilham - NEW
A507: 174904221976312 | B507: R10 | C507: 120225732846460694 | D507: SMA Madina | E507: 6281348555887 | F507: 45832 | G507: East Kalimantan | H507: region | I507: 803 | J507: 949 | K507: 32 | L507: 14199.157 | M507: 13475 | N507: 0 | O507: 261 | P507: 0 | Q507: ON-SMA Madina-29052025+20-6281348555887
A508: 174904221976312 | B508: R10 | C508: 120225575002440694 | D508: Toko Emas Sembiring | E508: 6281263113266 | F508: 45832 | G508: North Sumatra | H508: region | I508: 1280 | J508: 1533 | K508: 66 | L508: 9450.7502 | M508: 14488 | N508: 5 | O508: 0 | P508: 1 | Q508: ON-Toko Emas Sembiring-15052025+30-6281263113266-Ilham - 2 - RCVR
A509: 766589657993298 | B509: R06 | C509: 120228082065700235 | D509: Antoni kontruksi | E509: 6281383434602 | F509: 45832 | G509: Jakarta | H509: region | I509: 266 | J509: 289 | K509: 4 | L509: 31972.318 | M509: 9240 | N509: 0 | O509: 89 | P509: 1 | Q509: ON-Antoni kontruksi-22062025+5-6281383434602
A510: 766589657993298 | B510: R06 | C510: 120228082065700235 | D510: Antoni kontruksi | E510: 6281383434602 | F510: 45832 | G510: West Java | H510: region | I510: 172 | J510: 189 | K510: 2 | L510: 27058.201 | M510: 5114 | N510: 1 | O510: 65 | P510: 0 | Q510: ON-Antoni kontruksi-22062025+5-6281383434602
A511: 766589657993298 | B511: R06 | C511: 120228074309660235 | D511: Jaya Lasindo | E511: 6281383899119 | F511: 45832 | G511: Jakarta | H511: region | I511: 514 | J511: 580 | K511: 15 | L511: 18281.034 | M511: 10603 | N511: 1 | O511: 0 | P511: 0 | Q511: ON-Jaya Lasindo-19062025+5-6281383899119
A512: 766589657993298 | B512: R06 | C512: 120228074309660235 | D512: Jaya Lasindo | E512: 6281383899119 | F512: 45832 | G512: West Java | H512: region | I512: 190 | J512: 215 | K512: 2 | L512: 21604.651 | M512: 4645 | N512: 0 | O512: 0 | P512: 0 | Q512: ON-Jaya Lasindo-19062025+5-6281383899119
A513: 766589657993298 | B513: R06 | C513: 120228014435350235 | D513: zada karya | E513: 6283135590465 | F513: 45832 | G513: East Java | H513: region | I513: 403 | J513: 534 | K513: 9 | L513: 27241.573 | M513: 14547 | N513: 1 | O513: 113 | P513: 0 | Q513: ON-zada karya-20062025+5-6283135590465
A514: 766589657993298 | B514: R06 | C514: 120227926808950235 | D514: Norma Property | E514: 6281514999073 | F514: 45832 | G514: Banten | H514: region | I514: 48 | J514: 57 | K514: 2 | L514: 26333.333 | M514: 1501 | N514: 1 | O514: 23 | P514: 0 | Q514: ON-Norma Property-17062025+5-6281514999073
A515: 766589657993298 | B515: R06 | C515: 120227926808950235 | D515: Norma Property | E515: 6281514999073 | F515: 45832 | G515: Jakarta | H515: region | I515: 212 | J515: 238 | K515: 10 | L515: 35441.176 | M515: 8435 | N515: 3 | O515: 121 | P515: 0 | Q515: ON-Norma Property-17062025+5-6281514999073
A516: 766589657993298 | B516: R06 | C516: 120227926808950235 | D516: Norma Property | E516: 6281514999073 | F516: 45832 | G516: West Java | H516: region | I516: 113 | J516: 133 | K516: 6 | L516: 35481.203 | M516: 4719 | N516: 1 | O516: 67 | P516: 0 | Q516: ON-Norma Property-17062025+5-6281514999073
... A548: 766589657993298 | B548: R06 | C548: 120227599304890235 | D548: AR Kontraktor | E548: 6281316155059 | F548: 45832 | G548: West Java | H548: region | I548: 243 | J548: 254 | K548: 6 | L548: 20200.787 | M548: 5131 | N548: 0 | O548: 127 | P548: 0 | Q548: ON-AR Kontraktor-15062025+5-6281316155059

Sheet Performa Iklan Klien By Placeme
A1: AkunIklanId | B1: NamaAkun | C1: KampanyeId | D1: Nama Usaha | E1: Whatsapp | F1: Tanggal | G1: Reach | H1: Penempatan | I1: CPM | J1: LinkKlik | K1: Spend | L1: KlikWA | M1: VideoView | N1: Komentar | O1: Nama Kampanye

Sheet Rekap Performa Iklan
A1: 45788 | B1: 93 | C1: 23 | D1: 0.25 | E1: 35 | F1: 0.38 | G1: 26 | H1: 0.28 | I1: 9 | J1: 0.1
A2: 45819 | B2: 120 | C2: 10 | D2: 0.25 | E2: 52 | F2: 0.38 | G2: 26 | H2: 0.28 | I2: 9 | J2: 0.1
A3: 45849 | B3: 120 | C3: 5 | D3: 0.25 | E3: 57 | F3: 0.38 | G3: 26 | H3: 0.28 | I3: 9 | J3: 0.1
A4: 45819 | B4: 94 | C4: 16 | D4: 0.17 | E4: 41 | F4: 0.44 | G4: 33 | H4: 0.35 | I4: 4 | J4: 0.04
A5: 45849 | B5: 85 | C5: 18 | D5: 0.21 | E5: 38 | F5: 0.45 | G5: 27 | H5: 0.32 | I5: 2 | J5: 0.02
A6: 45880 | B6: 87 | C6: 23 | D6: 0.26 | E6: 32 | F6: 0.37 | G6: 29 | H6: 0.33 | I6: 3 | J6: 0.03
A7: 45911 | B7: 86 | C7: 19 | D7: 0.22 | E7: 30 | F7: 0.35 | G7: 32 | H7: 0.37 | I7: 5 | J7: 0.06
A8: 45941 | B8: 85 | C8: 16 | D8: 0.19 | E8: 39 | F8: 0.46 | G8: 28 | H8: 0.33 | I8: 2 | J8: 0.02
A9: 45972 | B9: 89 | C9: 21 | D9: 0.24 | E9: 37 | F9: 0.42 | G9: 26 | H9: 0.29 | I9: 5 | J9: 0.06
A10: 13-11-2025 | B10: 85 | C10: 17 | D10: 0.2 | E10: 40 | F10: 0.47 | G10: 20 | H10: 0.24 | I10: 8 | J10: 0.09
A11: 14-11-2025 | B11: 91 | C11: 14 | D11: 0.15 | E11: 42 | F11: 0.46 | G11: 30 | H11: 0.33 | I11: 5 | J11: 0.05
A12: 15-11-2025 | B12: 85 | C12: 16 | D12: 0.19 | E12: 38 | F12: 0.45 | G12: 25 | H12: 0.29 | I12: 6 | J12: 0.07
A13: 16-11-2025 | B13: 72 | C13: 15 | D13: 0.21 | E13: 21 | F13: 0.29 | G13: 30 | H13: 0.42 | I13: 6 | J13: 0.08
A14: 18-11-2025 | B14: 75 | C14: 17 | D14: 0.23 | E14: 33 | F14: 0.44 | G14: 18 | H14: 0.24 | I14: 7 | J14: 0.09
A15: 19-11-2025 | B15: 74 | C15: 19 | D15: 0.26 | E15: 27 | F15: 0.36 | G15: 21 | H15: 0.28 | I15: 7 | J15: 0.09
A16: 20-11-2025 | B16: 77 | C16: 12 | D16: 0.16 | E16: 36 | F16: 0.47 | G16: 19 | H16: 0.25 | I16: 10 | J16: 0.13
A17: 21-11-2025 | B17: 82 | C17: 13 | D17: 0.16 | E17: 38 | F17: 0.46 | G17: 22 | H17: 0.27 | I17: 9 | J17: 0.11
A18: 22-11-2025 | B18: 88 | C18: 21 | D18: 0.24 | E18: 34 | F18: 0.39 | G18: 28 | H18: 0.32 | I18: 5 | J18: 0.06
A19: 23-11-2025 | B19: 82 | C19: 16 | D19: 0.2 | E19: 34 | F19: 0.41 | G19: 28 | H19: 0.34 | I19: 4 | J19: 0.05
A20: 24-11-2025 | B20: 77 | C20: 17 | D20: 0.22 | E20: 30 | F20: 0.39 | G20: 25 | H20: 0.32 | I20: 5 | J20: 0.06
A21: 25-11-2025 | B21: 76 | C21: 18 | D21: 0.24 | E21: 27 | F21: 0.36 | G21: 23 | H21: 0.3 | I21: 8 | J21: 0.11
... A26: 30-11-2025 | B26: 63 | C26: 12 | D26: 0.19 | E26: 25 | F26: 0.4 | G26: 19 | H26: 0.3 | I26: 7 | J26: 0.11
A27: 45669 | B27: 59 | C27: 8 | D27: 0.14 | E27: 26 | F27: 0.44 | G27: 20 | H27: 0.34 | I27: 5 | J27: 0.08
A28: 45700 | B28: 56 | C28: 6 | D28: 0.11 | E28: 22 | F28: 0.39 | G28: 23 | H28: 0.41 | I28: 5 | J28: 0.09
A29: 45728 | B29: 57 | C29: 11 | D29: 0.19 | E29: 20 | F29: 0.35 | G29: 22 | H29: 0.39 | I29: 4 | J29: 0.07
A30: 45759 | B30: 61 | C30: 10 | D30: 0.16 | E30: 27 | F30: 0.44 | G30: 17 | H30: 0.28 | I30: 7 | J30: 0.11
A31: 45789 | B31: 62 | C31: 12 | D31: 0.19 | E31: 26 | F31: 0.42 | G31: 19 | H31: 0.31 | I31: 5 | J31: 0.08
A32: 45820 | B32: 55 | C32: 10 | D32: 0.18 | E32: 23 | F32: 0.42 | G32: 18 | H32: 0.33 | I32: 4 | J32: 0.07
A33: 45850 | B33: 54 | C33: 9 | D33: 0.17 | E33: 21 | F33: 0.39 | G33: 18 | H33: 0.33 | I33: 6 | J33: 0.11
A34: 45881 | B34: 56 | C34: 15 | D34: 0.27 | E34: 18 | F34: 0.32 | G34: 16 | H34: 0.29 | I34: 7 | J34: 0.13
A35: 45912 | B35: 60 | C35: 8 | D35: 0.13 | E35: 22 | F35: 0.37 | G35: 24 | H35: 0.4 | I35: 6 | J35: 0.1
A36: 45942 | B36: 59 | C36: 11 | D36: 0.19 | E36: 23 | F36: 0.39 | G36: 17 | H36: 0.29 | I36: 8 | J36: 0.14
A37: 45973 | B37: 57 | C37: 10 | D37: 0.18 | E37: 23 | F37: 0.4 | G37: 18 | H37: 0.32 | I37: 6 | J37: 0.11
A38: 46003 | B38: 53 | C38: 8 | D38: 0.15 | E38: 18 | F38: 0.34 | G38: 25 | H38: 0.47 | I38: 2 | J38: 0.04
A39: 13-12-2025 | B39: 56 | C39: 11 | D39: 0.2 | E39: 26 | F39: 0.46 | G39: 16 | H39: 0.29 | I39: 3 | J39: 0.05
A40: 14-12-2025 | B40: 47 | C40: 11 | D40: 0.23 | E40: 11 | F40: 0.23 | G40: 22 | H40: 0.47 | I40: 3 | J40: 0.06
A41: 15-12-2025 | B41: 55 | C41: 8 | D41: 0.15 | E41: 23 | F41: 0.42 | G41: 19 | H41: 0.35 | I41: 5 | J41: 0.09
A42: 16-12-2025 | B42: 53 | C42: 8 | D42: 0.15 | E42: 21 | F42: 0.4 | G42: 21 | H42: 0.4 | I42: 3 | J42: 0.06
A43: 17-12-2025 | B43: 52 | C43: 8 | D43: 0.15 | E43: 18 | F43: 0.35 | G43: 24 | H43: 0.46 | I43: 2 | J43: 0.04
A44: 18-12-2025 | B44: 48 | C44: 7 | D44: 0.15 | E44: 19 | F44: 0.4 | G44: 17 | H44: 0.35 | I44: 5 | J44: 0.1
A45: 19-12-2025 | B45: 47 | C45: 16 | D45: 0.34 | E45: 17 | F45: 0.36 | G45: 14 | H45: 0.3 | I45: 0 | J45: 0
A46: 20-12-2025 | B46: 43 | C46: 11 | D46: 0.26 | E46: 17 | F46: 0.4 | G46: 15 | H46: 0.35 | I46: 0 | J46: 0
A47: 21-12-2025 | B47: 40 | C47: 10 | D47: 0.25 | E47: 15 | F47: 0.38 | G47: 11 | H47: 0.28 | I47: 4 | J47: 0.1
A48: 22-12-2025 | B48: 37 | C48: 10 | D48: 0.27 | E48: 15 | F48: 0.41 | G48: 8 | H48: 0.22 | I48: 4 | J48: 0.11
A49: 23-12-2025 | B49: 31 | C49: 5 | D49: 0.16 | E49: 10 | F49: 0.32 | G49: 12 | H49: 0.39 | I49: 4 | J49: 0.13
A50: 24-12-2025 | B50: 33 | C50: 8 | D50: 0.24 | E50: 12 | F50: 0.36 | G50: 9 | H50: 0.27 | I50: 4 | J50: 0.12
... A57: 31-12-2025 | B57: 54 | C57: 13 | D57: 0.24 | E57: 15 | F57: 0.28 | G57: 20 | H57: 0.37 | I57: 6 | J57: 0.11
A58: 46023 | B58: 49 | C58: 5 | D58: 0.1 | E58: 17 | F58: 0.35 | G58: 16 | H58: 0.33 | I58: 11 | J58: 0.22
A59: 46054 | B59: 48 | C59: 10 | D59: 0.21 | E59: 16 | F59: 0.33 | G59: 15 | H59: 0.31 | I59: 7 | J59: 0.15
A60: 46082 | B60: 43 | C60: 5 | D60: 0.12 | E60: 17 | F60: 0.4 | G60: 18 | H60: 0.42 | I60: 3 | J60: 0.07
A61: 46113 | B61: 42 | C61: 3 | D61: 0.07 | E61: 16 | F61: 0.38 | G61: 15 | H61: 0.36 | I61: 8 | J61: 0.19
A62: 46143 | B62: 52 | C62: 8 | D62: 0.15 | E62: 21 | F62: 0.4 | G62: 16 | H62: 0.31 | I62: 7 | J62: 0.13
A63: 46174 | B63: 62 | C63: 8 | D63: 0.13 | E63: 27 | F63: 0.44 | G63: 17 | H63: 0.27 | I63: 10 | J63: 0.16
A64: 46204 | B64: 71 | C64: 8 | D64: 0.11 | E64: 26 | F64: 0.37 | G64: 31 | H64: 0.44 | I64: 6 | J64: 0.08
A65: 46235 | B65: 67 | C65: 8 | D65: 0.12 | E65: 27 | F65: 0.4 | G65: 23 | H65: 0.34 | I65: 9 | J65: 0.13
A66: 46266 | B66: 62 | C66: 9 | D66: 0.15 | E66: 30 | F66: 0.48 | G66: 15 | H66: 0.24 | I66: 8 | J66: 0.13
A67: 46296 | B67: 59 | C67: 11 | D67: 0.19 | E67: 22 | F67: 0.37 | G67: 16 | H67: 0.27 | I67: 10 | J67: 0.17
A68: 46327 | B68: 54 | C68: 8 | D68: 0.15 | E68: 19 | F68: 0.35 | G68: 16 | H68: 0.3 | I68: 11 | J68: 0.2
A69: 13-01-2026 | B69: 53 | C69: 8 | D69: 0.15 | E69: 22 | F69: 0.42 | G69: 15 | H69: 0.28 | I69: 8 | J69: 0.15
A70: 14-01-2026 | B70: 57 | C70: 5 | D70: 0.09 | E70: 29 | F70: 0.51 | G70: 15 | H70: 0.26 | I70: 8 | J70: 0.14
A71: 15-01-2026 | B71: 47 | C71: 5 | D71: 0.11 | E71: 22 | F71: 0.47 | G71: 9 | H71: 0.19 | I71: 11 | J71: 0.23
A72: 16-01-2026 | B72: 51 | C72: 9 | D72: 0.18 | E72: 15 | F72: 0.29 | G72: 19 | H72: 0.37 | I72: 8 | J72: 0.16
A73: 17-01-2026 | B73: 45 | C73: 6 | D73: 0.13 | E73: 13 | F73: 0.29 | G73: 19 | H73: 0.42 | I73: 7 | J73: 0.16
A74: 18-01-2026 | B74: 32 | C74: 5 | D74: 0.16 | E74: 12 | F74: 0.38 | G74: 9 | H74: 0.28 | I74: 6 | J74: 0.19
A75: 19-01-2026 | B75: 42 | C75: 2 | D75: 0.05 | E75: 22 | F75: 0.52 | G75: 9 | H75: 0.21 | I75: 9 | J75: 0.21
A76: 20-01-2026 | B76: 42 | C76: 5 | D76: 0.12 | E76: 12 | F76: 0.29 | G76: 20 | H76: 0.48 | I76: 5 | J76: 0.12
A77: 21-01-2026 | B77: 41 | C77: 6 | D77: 0.15 | E77: 14 | F77: 0.34 | G77: 16 | H77: 0.39 | I77: 5 | J77: 0.12
A78: 22-01-2026 | B78: 42 | C78: 5 | D78: 0.12 | E78: 17 | F78: 0.4 | G78: 17 | H78: 0.4 | I78: 3 | J78: 0.07
A79: 23-01-2026 | B79: 17 | C79: 2 | D79: 0.12 | E79: 4 | F79: 0.24 | G79: 10 | H79: 0.59 | I79: 1 | J79: 0.06
A80: 24-01-2026 | B80: 45 | C80: 6 | D80: 0.13 | E80: 16 | F80: 0.36 | G80: 18 | H80: 0.4 | I80: 5 | J80: 0.11
... A87: 31-01-2026 | B87: 49 | C87: 7 | D87: 0.14 | E87: 20 | F87: 0.41 | G87: 17 | H87: 0.35 | I87: 5 | J87: 0.1
A88: 46024 | B88: 45 | C88: 1 | D88: 0.02 | E88: 21 | F88: 0.47 | G88: 18 | H88: 0.4 | I88: 5 | J88: 0.11
A89: 46055 | B89: 50 | C89: 10 | D89: 0.2 | E89: 21 | F89: 0.42 | G89: 13 | H89: 0.26 | I89: 6 | J89: 0.12
A90: 46083 | B90: 51 | C90: 6 | D90: 0.12 | E90: 20 | F90: 0.39 | G90: 20 | H90: 0.39 | I90: 5 | J90: 0.1
A91: 46114 | B91: 53 | C91: 11 | D91: 0.21 | E91: 21 | F91: 0.4 | G91: 14 | H91: 0.26 | I91: 7 | J91: 0.13
A92: 46144 | B92: 46 | C92: 14 | D92: 0.3 | E92: 15 | F92: 0.33 | G92: 12 | H92: 0.26 | I92: 5 | J92: 0.11
A93: 46175 | B93: 50 | C93: 7 | D93: 0.14 | E93: 23 | F93: 0.46 | G93: 14 | H93: 0.28 | I93: 6 | J93: 0.12
A94: 46205 | B94: 51 | C94: 15 | D94: 0.29 | E94: 17 | F94: 0.33 | G94: 14 | H94: 0.27 | I94: 5 | J94: 0.1
A95: 46236 | B95: 52 | C95: 11 | D95: 0.21 | E95: 17 | F95: 0.33 | G95: 18 | H95: 0.35 | I95: 6 | J95: 0.12
A96: 46267 | B96: 45 | C96: 8 | D96: 0.18 | E96: 16 | F96: 0.36 | G96: 16 | H96: 0.36 | I96: 5 | J96: 0.11
A97: 46297 | B97: 46 | C97: 5 | D97: 0.11 | E97: 19 | F97: 0.41 | G97: 19 | H97: 0.41 | I97: 3 | J97: 0.07
A98: 46328 | B98: 43 | C98: 9 | D98: 0.21 | E98: 14 | F98: 0.33 | G98: 18 | H98: 0.42 | I98: 2 | J98: 0.05
A99: 46358 | B99: 49 | C99: 6 | D99: 0.12 | E99: 18 | F99: 0.37 | G99: 21 | H99: 0.43 | I99: 4 | J99: 0.08
A100: 13-02-2026 | B100: 49 | C100: 7 | D100: 0.14 | E100: 23 | F100: 0.47 | G100: 15 | H100: 0.31 | I100: 4 | J100: 0.08
A101: 14-02-2026 | B101: 45 | C101: 11 | D101: 0.24 | E101: 15 | F101: 0.33 | G101: 17 | H101: 0.38 | I101: 2 | J101: 0.04
A102: 15-02-2026 | B102: 44 | C102: 14 | D102: 0.32 | E102: 16 | F102: 0.36 | G102: 10 | H102: 0.23 | I102: 4 | J102: 0.09
A103: 16-02-2026 | B103: 45 | C103: 10 | D103: 0.22 | E103: 15 | F103: 0.33 | G103: 16 | H103: 0.36 | I103: 4 | J103: 0.09
A104: 17-02-2026 | B104: 37 | C104: 3 | D104: 0.08 | E104: 20 | F104: 0.54 | G104: 13 | H104: 0.35 | I104: 1 | J104: 0.03
A105: 18-02-2026 | B105: 41 | C105: 6 | D105: 0.15 | E105: 15 | F105: 0.37 | G105: 17 | H105: 0.41 | I105: 3 | J105: 0.07

Sheet Resume Iklan
A1: =IFERROR(__xludf.DUMMYFUNCTION("QUERY( SORT( ARRAYFORMULA({ 'Performa Iklan Klien'!A2:A783, 'Performa Iklan Klien'!C2:C783, 'Performa Iklan Klien'!D2:D783, IF('Performa Iklan Klien'!E2:E783<>"""", ""https://wa.me/"" & SUBSTITUTE('Performa Iklan Klien'!E2"&":E783, "" "", """"), """"), IF('Performa Iklan Klien'!E2:E783<>"""", SUBSTITUTE('Performa Iklan Klien'!E2:E783, "" "", """"), """"), IF('Performa Iklan Klien'!G2:G783<>"""", VALUE(SUBSTITUTE('Performa Iklan Klien'!G2:G783, "","", """")),), "&" IF('Performa Iklan Klien'!H2:H783<>"""", VALUE(SUBSTITUTE('Performa Iklan Klien'!H2:H783, "","", """")),), IF('Performa Iklan Klien'!K2:K783<>"""", VALUE(SUBSTITUTE('Performa Iklan Klien'!K2:K783, "","", """")),), IF('Performa Iklan Kl"&"ien'!J2:J783<>"""", VALUE(SUBSTITUTE(SUBSTITUTE('Performa Iklan Klien'!J2:J783, ""Rp"", """"), "","", """")),) }), 5, TRUE ), ""SELECT Col1, Col2, Col3, Col4, Col5, SUM(Col6), AVG(Col7), SUM(Col8), SUM(Col9), SUM(Col9)/SUM(Col8), SUM(Col9)/150"&"00 WHERE Col6 IS NOT NULL GROUP BY Col1, Col2, Col3, Col4, Col5 LABEL Col1 'AkunIklanId', Col2 'KampanyeID', Col3 'Nama Usaha', Col4 'Link WhatsApp', Col5 'Nomor WhatsApp', SUM(Col6) 'Reach', AVG(Col7)"&" 'CPM', SUM(Col8) 'KlikWa', SUM(Col9) 'Spend', SUM(Col9)/SUM(Col8) 'CPR', SUM(Col9)/15000 'Durasi'"" ) "),"AkunIklanId") -> AkunIklanId | B1: =IFERROR(__xludf.DUMMYFUNCTION("""COMPUTED_VALUE"""),"KampanyeID") -> KampanyeID | C1: =IFERROR(__xludf.DUMMYFUNCTION("""COMPUTED_VALUE"""),"Nama Usaha") -> Nama Usaha | D1: =IFERROR(__xludf.DUMMYFUNCTION("""COMPUTED_VALUE"""),"Link WhatsApp") -> Link WhatsApp | E1: =IFERROR(__xludf.DUMMYFUNCTION("""COMPUTED_VALUE"""),"Nomor WhatsApp") -> Nomor WhatsApp | F1: =IFERROR(__xludf.DUMMYFUNCTION("""COMPUTED_VALUE"""),"Reach") -> Reach | G1: =IFERROR(__xludf.DUMMYFUNCTION("""COMPUTED_VALUE"""),"CPM") -> CPM | H1: =IFERROR(__xludf.DUMMYFUNCTION("""COMPUTED_VALUE"""),"KlikWa") -> KlikWa | I1: =IFERROR(__xludf.DUMMYFUNCTION("""COMPUTED_VALUE"""),"Spend") -> Spend | J1: =IFERROR(__xludf.DUMMYFUNCTION("""COMPUTED_VALUE"""),"CPR") -> CPR | K1: =IFERROR(__xludf.DUMMYFUNCTION("""COMPUTED_VALUE"""),"Durasi") -> Durasi | L1: Link Iklan | M1: Status
A2: =IFERROR(__xludf.DUMMYFUNCTION("""COMPUTED_VALUE"""),174904221976312) -> 174904221976312 | B2: =IFERROR(__xludf.DUMMYFUNCTION("""COMPUTED_VALUE"""),"120222033176120694") -> 120222033176120694 | C2: =IFERROR(__xludf.DUMMYFUNCTION("""COMPUTED_VALUE"""),"Wiris Variasi") -> Wiris Variasi | D2: =IFERROR(__xludf.DUMMYFUNCTION("""COMPUTED_VALUE"""),"https://wa.me/6282242925264") -> https://wa.me/6282242925264 | E2: =IFERROR(__xludf.DUMMYFUNCTION("""COMPUTED_VALUE"""),"6282242925264") -> 6282242925264 | F2: =IFERROR(__xludf.DUMMYFUNCTION("""COMPUTED_VALUE"""),86844) -> 86844 | G2: =IFERROR(__xludf.DUMMYFUNCTION("""COMPUTED_VALUE"""),5750.92105263157) -> 5750.9211 | H2: =IFERROR(__xludf.DUMMYFUNCTION("""COMPUTED_VALUE"""),195) -> 195 | I2: =IFERROR(__xludf.DUMMYFUNCTION("""COMPUTED_VALUE"""),549988) -> 549988 | J2: =IFERROR(__xludf.DUMMYFUNCTION("""COMPUTED_VALUE"""),2820.45128205128) -> 2820.4513 | K2: =IFERROR(__xludf.DUMMYFUNCTION("""COMPUTED_VALUE"""),36.6658666666666) -> 36.665867 | L2: {=IF( (A2:A783 <> "") * (B2:B783 <> "") * (C2:C783 <> ""), HYPERLINK( "https://adsmanager.facebook.com/adsmanager/manage/campaigns/edit/standalone?act=" & A2:A783 & "&selected_campaign_ids=" & B2:B783, C2:C783 ), "" )} -> Wiris Variasi
A3: =IFERROR(__xludf.DUMMYFUNCTION("""COMPUTED_VALUE"""),174904221976312) -> 174904221976312 | B3: =IFERROR(__xludf.DUMMYFUNCTION("""COMPUTED_VALUE"""),"120224030796970694") -> 120224030796970694 | C3: =IFERROR(__xludf.DUMMYFUNCTION("""COMPUTED_VALUE"""),"Prima Beauty Centre") -> Prima Beauty Centre | D3: =IFERROR(__xludf.DUMMYFUNCTION("""COMPUTED_VALUE"""),"https://wa.me/628115424402") -> https://wa.me/628115424402 | E3: =IFERROR(__xludf.DUMMYFUNCTION("""COMPUTED_VALUE"""),"628115424402") -> 628115424402 | F3: =IFERROR(__xludf.DUMMYFUNCTION("""COMPUTED_VALUE"""),6839) -> 6839 | G3: =IFERROR(__xludf.DUMMYFUNCTION("""COMPUTED_VALUE"""),13850.1428571428) -> 13850.143 | H3: =IFERROR(__xludf.DUMMYFUNCTION("""COMPUTED_VALUE"""),38) -> 38 | I3: =IFERROR(__xludf.DUMMYFUNCTION("""COMPUTED_VALUE"""),103470) -> 103470 | J3: =IFERROR(__xludf.DUMMYFUNCTION("""COMPUTED_VALUE"""),2722.8947368421) -> 2722.8947 | K3: =IFERROR(__xludf.DUMMYFUNCTION("""COMPUTED_VALUE"""),6.898) -> 6.898 | L3: Wiris Variasi | R3: cpm mahal >20rb
A4: =IFERROR(__xludf.DUMMYFUNCTION("""COMPUTED_VALUE"""),174904221976312) -> 174904221976312 | B4: =IFERROR(__xludf.DUMMYFUNCTION("""COMPUTED_VALUE"""),"120224403680120694") -> 120224403680120694 | C4: =IFERROR(__xludf.DUMMYFUNCTION("""COMPUTED_VALUE"""),"Phone Cell Center") -> Phone Cell Center | D4: =IFERROR(__xludf.DUMMYFUNCTION("""COMPUTED_VALUE"""),"https://wa.me/6281241440688") -> https://wa.me/6281241440688 | E4: =IFERROR(__xludf.DUMMYFUNCTION("""COMPUTED_VALUE"""),"6281241440688") -> 6281241440688 | F4: =IFERROR(__xludf.DUMMYFUNCTION("""COMPUTED_VALUE"""),41573) -> 41573 | G4: =IFERROR(__xludf.DUMMYFUNCTION("""COMPUTED_VALUE"""),6410.30434782608) -> 6410.3043 | H4: =IFERROR(__xludf.DUMMYFUNCTION("""COMPUTED_VALUE"""),29) -> 29 | I4: =IFERROR(__xludf.DUMMYFUNCTION("""COMPUTED_VALUE"""),298719) -> 298719 | J4: =IFERROR(__xludf.DUMMYFUNCTION("""COMPUTED_VALUE"""),10300.6551724137) -> 10300.655 | K4: =IFERROR(__xludf.DUMMYFUNCTION("""COMPUTED_VALUE"""),19.9146) -> 19.9146 | L4: Wiris Variasi | R4: leads < 5
A5: =IFERROR(__xludf.DUMMYFUNCTION("""COMPUTED_VALUE"""),174904221976312) -> 174904221976312 | B5: =IFERROR(__xludf.DUMMYFUNCTION("""COMPUTED_VALUE"""),"120224679214120694") -> 120224679214120694 | C5: =IFERROR(__xludf.DUMMYFUNCTION("""COMPUTED_VALUE"""),"Master Home Decor+15052025") -> Master Home Decor+15052025 | D5: =IFERROR(__xludf.DUMMYFUNCTION("""COMPUTED_VALUE"""),"https://wa.me/6281378757554") -> https://wa.me/6281378757554 | E5: =IFERROR(__xludf.DUMMYFUNCTION("""COMPUTED_VALUE"""),"6281378757554") -> 6281378757554 | F5: =IFERROR(__xludf.DUMMYFUNCTION("""COMPUTED_VALUE"""),3765) -> 3765 | G5: =IFERROR(__xludf.DUMMYFUNCTION("""COMPUTED_VALUE"""),27767.5555555555) -> 27767.556 | H5: =IFERROR(__xludf.DUMMYFUNCTION("""COMPUTED_VALUE"""),13) -> 13 | I5: =IFERROR(__xludf.DUMMYFUNCTION("""COMPUTED_VALUE"""),117961) -> 117961 | J5: =IFERROR(__xludf.DUMMYFUNCTION("""COMPUTED_VALUE"""),9073.92307692307) -> 9073.9231 | K5: =IFERROR(__xludf.DUMMYFUNCTION("""COMPUTED_VALUE"""),7.86406666666666) -> 7.8640667 | L5: Wiris Variasi | R5: cpr>7000
A6: =IFERROR(__xludf.DUMMYFUNCTION("""COMPUTED_VALUE"""),174904221976312) -> 174904221976312 | B6: =IFERROR(__xludf.DUMMYFUNCTION("""COMPUTED_VALUE"""),"120224708398910694") -> 120224708398910694 | C6: =IFERROR(__xludf.DUMMYFUNCTION("""COMPUTED_VALUE"""),"Rodrimar Aifunan Fresku") -> Rodrimar Aifunan Fresku | F6: =IFERROR(__xludf.DUMMYFUNCTION("""COMPUTED_VALUE"""),117338) -> 117338 | G6: =IFERROR(__xludf.DUMMYFUNCTION("""COMPUTED_VALUE"""),2819.92307692307) -> 2819.9231 | H6: =IFERROR(__xludf.DUMMYFUNCTION("""COMPUTED_VALUE"""),137) -> 137 | I6: =IFERROR(__xludf.DUMMYFUNCTION("""COMPUTED_VALUE"""),352799) -> 352799 | J6: =IFERROR(__xludf.DUMMYFUNCTION("""COMPUTED_VALUE"""),2575.17518248175) -> 2575.1752 | K6: =IFERROR(__xludf.DUMMYFUNCTION("""COMPUTED_VALUE"""),23.5199333333333) -> 23.519933 | L6: Wiris Variasi
A7: =IFERROR(__xludf.DUMMYFUNCTION("""COMPUTED_VALUE"""),174904221976312) -> 174904221976312 | B7: =IFERROR(__xludf.DUMMYFUNCTION("""COMPUTED_VALUE"""),"120224822861740694") -> 120224822861740694 | C7: =IFERROR(__xludf.DUMMYFUNCTION("""COMPUTED_VALUE"""),"Daihatsu Mamuju") -> Daihatsu Mamuju | D7: =IFERROR(__xludf.DUMMYFUNCTION("""COMPUTED_VALUE"""),"https://wa.me/6282347206488") -> https://wa.me/6282347206488 | E7: =IFERROR(__xludf.DUMMYFUNCTION("""COMPUTED_VALUE"""),"6282347206488") -> 6282347206488 | F7: =IFERROR(__xludf.DUMMYFUNCTION("""COMPUTED_VALUE"""),27508) -> 27508 | G7: =IFERROR(__xludf.DUMMYFUNCTION("""COMPUTED_VALUE"""),9786.52380952381) -> 9786.5238 | H7: =IFERROR(__xludf.DUMMYFUNCTION("""COMPUTED_VALUE"""),103) -> 103 | I7: =IFERROR(__xludf.DUMMYFUNCTION("""COMPUTED_VALUE"""),276526) -> 276526 | J7: =IFERROR(__xludf.DUMMYFUNCTION("""COMPUTED_VALUE"""),2684.71844660194) -> 2684.7184 | K7: =IFERROR(__xludf.DUMMYFUNCTION("""COMPUTED_VALUE"""),18.4350666666666) -> 18.435067 | L7: Wiris Variasi
A8: =IFERROR(__xludf.DUMMYFUNCTION("""COMPUTED_VALUE"""),174904221976312) -> 174904221976312 | B8: =IFERROR(__xludf.DUMMYFUNCTION("""COMPUTED_VALUE"""),"120225065069670694") -> 120225065069670694 | C8: =IFERROR(__xludf.DUMMYFUNCTION("""COMPUTED_VALUE"""),"LK spa n beauty") -> LK spa n beauty | D8: =IFERROR(__xludf.DUMMYFUNCTION("""COMPUTED_VALUE"""),"https://wa.me/6282341426767") -> https://wa.me/6282341426767 | E8: =IFERROR(__xludf.DUMMYFUNCTION("""COMPUTED_VALUE"""),"6282341426767") -> 6282341426767 | F8: =IFERROR(__xludf.DUMMYFUNCTION("""COMPUTED_VALUE"""),1243) -> 1243 | G8: =IFERROR(__xludf.DUMMYFUNCTION("""COMPUTED_VALUE"""),24433.3333333333) -> 24433.333 | H8: =IFERROR(__xludf.DUMMYFUNCTION("""COMPUTED_VALUE"""),11) -> 11 | I8: =IFERROR(__xludf.DUMMYFUNCTION("""COMPUTED_VALUE"""),36734) -> 36734 | J8: =IFERROR(__xludf.DUMMYFUNCTION("""COMPUTED_VALUE"""),3339.45454545454) -> 3339.4545 | K8: =IFERROR(__xludf.DUMMYFUNCTION("""COMPUTED_VALUE"""),2.44893333333333) -> 2.4489333 | L8: Wiris Variasi
A9: =IFERROR(__xludf.DUMMYFUNCTION("""COMPUTED_VALUE"""),174904221976312) -> 174904221976312 | B9: =IFERROR(__xludf.DUMMYFUNCTION("""COMPUTED_VALUE"""),"120225230850710694") -> 120225230850710694 | C9: =IFERROR(__xludf.DUMMYFUNCTION("""COMPUTED_VALUE"""),"CV MZ banyu agung") -> CV MZ banyu agung | D9: =IFERROR(__xludf.DUMMYFUNCTION("""COMPUTED_VALUE"""),"https://wa.me/62882001677470") -> https://wa.me/62882001677470 | E9: =IFERROR(__xludf.DUMMYFUNCTION("""COMPUTED_VALUE"""),"62882001677470") -> 62882001677470 | F9: =IFERROR(__xludf.DUMMYFUNCTION("""COMPUTED_VALUE"""),9090) -> 9090 | G9: =IFERROR(__xludf.DUMMYFUNCTION("""COMPUTED_VALUE"""),19904.8666666666) -> 19904.867 | H9: =IFERROR(__xludf.DUMMYFUNCTION("""COMPUTED_VALUE"""),18) -> 18 | I9: =IFERROR(__xludf.DUMMYFUNCTION("""COMPUTED_VALUE"""),190172) -> 190172 | J9: =IFERROR(__xludf.DUMMYFUNCTION("""COMPUTED_VALUE"""),10565.1111111111) -> 10565.111 | K9: =IFERROR(__xludf.DUMMYFUNCTION("""COMPUTED_VALUE"""),12.6781333333333) -> 12.678133 | L9: Wiris Variasi
A10: =IFERROR(__xludf.DUMMYFUNCTION("""COMPUTED_VALUE"""),174904221976312) -> 174904221976312 | B10: =IFERROR(__xludf.DUMMYFUNCTION("""COMPUTED_VALUE"""),"120225346217950694") -> 120225346217950694 | C10: =IFERROR(__xludf.DUMMYFUNCTION("""COMPUTED_VALUE"""),"Verrocosta") -> Verrocosta | D10: =IFERROR(__xludf.DUMMYFUNCTION("""COMPUTED_VALUE"""),"https://wa.me/6282226594414") -> https://wa.me/6282226594414 | E10: =IFERROR(__xludf.DUMMYFUNCTION("""COMPUTED_VALUE"""),"6282226594414") -> 6282226594414 | F10: =IFERROR(__xludf.DUMMYFUNCTION("""COMPUTED_VALUE"""),69806) -> 69806 | G10: =IFERROR(__xludf.DUMMYFUNCTION("""COMPUTED_VALUE"""),2988.27777777777) -> 2988.2778 | H10: =IFERROR(__xludf.DUMMYFUNCTION("""COMPUTED_VALUE"""),278) -> 278 | I10: =IFERROR(__xludf.DUMMYFUNCTION("""COMPUTED_VALUE"""),237023) -> 237023 | J10: =IFERROR(__xludf.DUMMYFUNCTION("""COMPUTED_VALUE"""),852.60071942446) -> 852.60072 | K10: =IFERROR(__xludf.DUMMYFUNCTION("""COMPUTED_VALUE"""),15.8015333333333) -> 15.801533 | L10: Wiris Variasi
A11: =IFERROR(__xludf.DUMMYFUNCTION("""COMPUTED_VALUE"""),174904221976312) -> 174904221976312 | B11: =IFERROR(__xludf.DUMMYFUNCTION("""COMPUTED_VALUE"""),"120225366947220694") -> 120225366947220694 | C11: =IFERROR(__xludf.DUMMYFUNCTION("""COMPUTED_VALUE"""),"LPK ERBANSA AKADEMI") -> LPK ERBANSA AKADEMI | D11: =IFERROR(__xludf.DUMMYFUNCTION("""COMPUTED_VALUE"""),"https://wa.me/6282226594414") -> https://wa.me/6282226594414 | E11: =IFERROR(__xludf.DUMMYFUNCTION("""COMPUTED_VALUE"""),"6282226594414") -> 6282226594414 | F11: =IFERROR(__xludf.DUMMYFUNCTION("""COMPUTED_VALUE"""),1044) -> 1044 | G11: =IFERROR(__xludf.DUMMYFUNCTION("""COMPUTED_VALUE"""),12230) -> 12230 | H11: =IFERROR(__xludf.DUMMYFUNCTION("""COMPUTED_VALUE"""),1) -> 1 | I11: =IFERROR(__xludf.DUMMYFUNCTION("""COMPUTED_VALUE"""),13954) -> 13954 | J11: =IFERROR(__xludf.DUMMYFUNCTION("""COMPUTED_VALUE"""),13954) -> 13954 | K11: =IFERROR(__xludf.DUMMYFUNCTION("""COMPUTED_VALUE"""),0.930266666666666) -> 0.93026667 | L11: Wiris Variasi
A12: =IFERROR(__xludf.DUMMYFUNCTION("""COMPUTED_VALUE"""),174904221976312) -> 174904221976312 | B12: =IFERROR(__xludf.DUMMYFUNCTION("""COMPUTED_VALUE"""),"120225575002440694") -> 120225575002440694 | C12: =IFERROR(__xludf.DUMMYFUNCTION("""COMPUTED_VALUE"""),"Toko Emas Sembiring") -> Toko Emas Sembiring | D12: =IFERROR(__xludf.DUMMYFUNCTION("""COMPUTED_VALUE"""),"https://wa.me/6281263113266") -> https://wa.me/6281263113266 | E12: =IFERROR(__xludf.DUMMYFUNCTION("""COMPUTED_VALUE"""),"6281263113266") -> 6281263113266 | F12: =IFERROR(__xludf.DUMMYFUNCTION("""COMPUTED_VALUE"""),54922) -> 54922 | G12: =IFERROR(__xludf.DUMMYFUNCTION("""COMPUTED_VALUE"""),9905.47222222222) -> 9905.4722 | H12: =IFERROR(__xludf.DUMMYFUNCTION("""COMPUTED_VALUE"""),148) -> 148 | I12: =IFERROR(__xludf.DUMMYFUNCTION("""COMPUTED_VALUE"""),595465) -> 595465 | J12: =IFERROR(__xludf.DUMMYFUNCTION("""COMPUTED_VALUE"""),4023.41216216216) -> 4023.4122 | K12: =IFERROR(__xludf.DUMMYFUNCTION("""COMPUTED_VALUE"""),39.6976666666666) -> 39.697667 | L12: Wiris Variasi
A13: =IFERROR(__xludf.DUMMYFUNCTION("""COMPUTED_VALUE"""),174904221976312) -> 174904221976312 | B13: =IFERROR(__xludf.DUMMYFUNCTION("""COMPUTED_VALUE"""),"120225711165240694") -> 120225711165240694 | C13: =IFERROR(__xludf.DUMMYFUNCTION("""COMPUTED_VALUE"""),"Bang Banten") -> Bang Banten | D13: =IFERROR(__xludf.DUMMYFUNCTION("""COMPUTED_VALUE"""),"https://wa.me/6282172291579") -> https://wa.me/6282172291579 | E13: =IFERROR(__xludf.DUMMYFUNCTION("""COMPUTED_VALUE"""),"6282172291579") -> 6282172291579 | F13: =IFERROR(__xludf.DUMMYFUNCTION("""COMPUTED_VALUE"""),22838) -> 22838 | G13: =IFERROR(__xludf.DUMMYFUNCTION("""COMPUTED_VALUE"""),15965.2258064516) -> 15965.226 | H13: =IFERROR(__xludf.DUMMYFUNCTION("""COMPUTED_VALUE"""),136) -> 136 | I13: =IFERROR(__xludf.DUMMYFUNCTION("""COMPUTED_VALUE"""),413378) -> 413378 | J13: =IFERROR(__xludf.DUMMYFUNCTION("""COMPUTED_VALUE"""),3039.54411764705) -> 3039.5441 | K13: =IFERROR(__xludf.DUMMYFUNCTION("""COMPUTED_VALUE"""),27.5585333333333) -> 27.558533 | L13: Wiris Variasi
A14: =IFERROR(__xludf.DUMMYFUNCTION("""COMPUTED_VALUE"""),174904221976312) -> 174904221976312 | B14: =IFERROR(__xludf.DUMMYFUNCTION("""COMPUTED_VALUE"""),"120225732456000694") -> 120225732456000694 | C14: =IFERROR(__xludf.DUMMYFUNCTION("""COMPUTED_VALUE"""),"Aurora Teknik") -> Aurora Teknik | D14: =IFERROR(__xludf.DUMMYFUNCTION("""COMPUTED_VALUE"""),"https://wa.me/6285376667233") -> https://wa.me/6285376667233 | E14: =IFERROR(__xludf.DUMMYFUNCTION("""COMPUTED_VALUE"""),"6285376667233") -> 6285376667233 | F14: =IFERROR(__xludf.DUMMYFUNCTION("""COMPUTED_VALUE"""),40889) -> 40889 | G14: =IFERROR(__xludf.DUMMYFUNCTION("""COMPUTED_VALUE"""),11906.9) -> 11906.9 | H14: =IFERROR(__xludf.DUMMYFUNCTION("""COMPUTED_VALUE"""),149) -> 149 | I14: =IFERROR(__xludf.DUMMYFUNCTION("""COMPUTED_VALUE"""),518434) -> 518434 | J14: =IFERROR(__xludf.DUMMYFUNCTION("""COMPUTED_VALUE"""),3479.42281879194) -> 3479.4228 | K14: =IFERROR(__xludf.DUMMYFUNCTION("""COMPUTED_VALUE"""),34.5622666666666) -> 34.562267 | L14: Wiris Variasi
A15: =IFERROR(__xludf.DUMMYFUNCTION("""COMPUTED_VALUE"""),174904221976312) -> 174904221976312 | B15: =IFERROR(__xludf.DUMMYFUNCTION("""COMPUTED_VALUE"""),"120225732846460694") -> 120225732846460694 | C15: =IFERROR(__xludf.DUMMYFUNCTION("""COMPUTED_VALUE"""),"SMA Madina") -> SMA Madina | D15: =IFERROR(__xludf.DUMMYFUNCTION("""COMPUTED_VALUE"""),"https://wa.me/6281348555887") -> https://wa.me/6281348555887 | E15: =IFERROR(__xludf.DUMMYFUNCTION("""COMPUTED_VALUE"""),"6281348555887") -> 6281348555887 | F15: =IFERROR(__xludf.DUMMYFUNCTION("""COMPUTED_VALUE"""),40205) -> 40205 | G15: =IFERROR(__xludf.DUMMYFUNCTION("""COMPUTED_VALUE"""),11443.9268292682) -> 11443.927 | H15: =IFERROR(__xludf.DUMMYFUNCTION("""COMPUTED_VALUE"""),40) -> 40 | I15: =IFERROR(__xludf.DUMMYFUNCTION("""COMPUTED_VALUE"""),499867) -> 499867 | J15: =IFERROR(__xludf.DUMMYFUNCTION("""COMPUTED_VALUE"""),12496.675) -> 12496.675 | K15: =IFERROR(__xludf.DUMMYFUNCTION("""COMPUTED_VALUE"""),33.3244666666666) -> 33.324467 | L15: Wiris Variasi
A16: =IFERROR(__xludf.DUMMYFUNCTION("""COMPUTED_VALUE"""),174904221976312) -> 174904221976312 | B16: =IFERROR(__xludf.DUMMYFUNCTION("""COMPUTED_VALUE"""),"120225924609850694") -> 120225924609850694 | C16: =IFERROR(__xludf.DUMMYFUNCTION("""COMPUTED_VALUE"""),"Amanah Interior") -> Amanah Interior | D16: =IFERROR(__xludf.DUMMYFUNCTION("""COMPUTED_VALUE"""),"https://wa.me/6282183184641") -> https://wa.me/6282183184641 | E16: =IFERROR(__xludf.DUMMYFUNCTION("""COMPUTED_VALUE"""),"6282183184641") -> 6282183184641 | F16: =IFERROR(__xludf.DUMMYFUNCTION("""COMPUTED_VALUE"""),15490) -> 15490 | G16: =IFERROR(__xludf.DUMMYFUNCTION("""COMPUTED_VALUE"""),16869.5714285714) -> 16869.571 | H16: =IFERROR(__xludf.DUMMYFUNCTION("""COMPUTED_VALUE"""),43) -> 43 | I16: =IFERROR(__xludf.DUMMYFUNCTION("""COMPUTED_VALUE"""),267617) -> 267617 | J16: =IFERROR(__xludf.DUMMYFUNCTION("""COMPUTED_VALUE"""),6223.65116279069) -> 6223.6512 | K16: =IFERROR(__xludf.DUMMYFUNCTION("""COMPUTED_VALUE"""),17.8411333333333) -> 17.841133 | L16: Wiris Variasi
A17: =IFERROR(__xludf.DUMMYFUNCTION("""COMPUTED_VALUE"""),174904221976312) -> 174904221976312 | B17: =IFERROR(__xludf.DUMMYFUNCTION("""COMPUTED_VALUE"""),"120225943524550694") -> 120225943524550694 | C17: =IFERROR(__xludf.DUMMYFUNCTION("""COMPUTED_VALUE"""),"Dapur Florist") -> Dapur Florist | D17: =IFERROR(__xludf.DUMMYFUNCTION("""COMPUTED_VALUE"""),"https://wa.me/6281399998259") -> https://wa.me/6281399998259 | E17: =IFERROR(__xludf.DUMMYFUNCTION("""COMPUTED_VALUE"""),"6281399998259") -> 6281399998259 | F17: =IFERROR(__xludf.DUMMYFUNCTION("""COMPUTED_VALUE"""),7732) -> 7732 | G17: =IFERROR(__xludf.DUMMYFUNCTION("""COMPUTED_VALUE"""),12155.7) -> 12155.7 | H17: =IFERROR(__xludf.DUMMYFUNCTION("""COMPUTED_VALUE"""),4) -> 4 | I17: =IFERROR(__xludf.DUMMYFUNCTION("""COMPUTED_VALUE"""),94583) -> 94583 | J17: =IFERROR(__xludf.DUMMYFUNCTION("""COMPUTED_VALUE"""),23645.75) -> 23645.75 | K17: =IFERROR(__xludf.DUMMYFUNCTION("""COMPUTED_VALUE"""),6.30553333333333) -> 6.3055333 | L17: Wiris Variasi
A18: =IFERROR(__xludf.DUMMYFUNCTION("""COMPUTED_VALUE"""),174904221976312) -> 174904221976312 | B18: =IFERROR(__xludf.DUMMYFUNCTION("""COMPUTED_VALUE"""),"120225980267140694") -> 120225980267140694 | C18: =IFERROR(__xludf.DUMMYFUNCTION("""COMPUTED_VALUE"""),"Icad Interior") -> Icad Interior | D18: =IFERROR(__xludf.DUMMYFUNCTION("""COMPUTED_VALUE"""),"https://wa.me/6285211510282") -> https://wa.me/6285211510282 | E18: =IFERROR(__xludf.DUMMYFUNCTION("""COMPUTED_VALUE"""),"6285211510282") -> 6285211510282 | F18: =IFERROR(__xludf.DUMMYFUNCTION("""COMPUTED_VALUE"""),964) -> 964 | G18: =IFERROR(__xludf.DUMMYFUNCTION("""COMPUTED_VALUE"""),47534) -> 47534 | H18: =IFERROR(__xludf.DUMMYFUNCTION("""COMPUTED_VALUE"""),0) -> 0 | I18: =IFERROR(__xludf.DUMMYFUNCTION("""COMPUTED_VALUE"""),49868) -> 49868 | K18: =IFERROR(__xludf.DUMMYFUNCTION("""COMPUTED_VALUE"""),3.32453333333333) -> 3.3245333 | L18: Wiris Variasi
A19: =IFERROR(__xludf.DUMMYFUNCTION("""COMPUTED_VALUE"""),174904221976312) -> 174904221976312 | B19: =IFERROR(__xludf.DUMMYFUNCTION("""COMPUTED_VALUE"""),"120226032160860694") -> 120226032160860694 | C19: =IFERROR(__xludf.DUMMYFUNCTION("""COMPUTED_VALUE"""),"EPE Plavon") -> EPE Plavon | F19: =IFERROR(__xludf.DUMMYFUNCTION("""COMPUTED_VALUE"""),19153) -> 19153 | G19: =IFERROR(__xludf.DUMMYFUNCTION("""COMPUTED_VALUE"""),8576.64285714285) -> 8576.6429 | H19: =IFERROR(__xludf.DUMMYFUNCTION("""COMPUTED_VALUE"""),91) -> 91 | I19: =IFERROR(__xludf.DUMMYFUNCTION("""COMPUTED_VALUE"""),187713) -> 187713 | J19: =IFERROR(__xludf.DUMMYFUNCTION("""COMPUTED_VALUE"""),2062.78021978022) -> 2062.7802 | K19: =IFERROR(__xludf.DUMMYFUNCTION("""COMPUTED_VALUE"""),12.5142) -> 12.5142 | L19: Wiris Variasi
A20: =IFERROR(__xludf.DUMMYFUNCTION("""COMPUTED_VALUE"""),174904221976312) -> 174904221976312 | B20: =IFERROR(__xludf.DUMMYFUNCTION("""COMPUTED_VALUE"""),"120226052237140694") -> 120226052237140694 | C20: =IFERROR(__xludf.DUMMYFUNCTION("""COMPUTED_VALUE"""),"Umam daffa") -> Umam daffa | F20: =IFERROR(__xludf.DUMMYFUNCTION("""COMPUTED_VALUE"""),1259) -> 1259 | G20: =IFERROR(__xludf.DUMMYFUNCTION("""COMPUTED_VALUE"""),44377.4) -> 44377.4 | H20: =IFERROR(__xludf.DUMMYFUNCTION("""COMPUTED_VALUE"""),5) -> 5 | I20: =IFERROR(__xludf.DUMMYFUNCTION("""COMPUTED_VALUE"""),53318) -> 53318 | J20: =IFERROR(__xludf.DUMMYFUNCTION("""COMPUTED_VALUE"""),10663.6) -> 10663.6 | K20: =IFERROR(__xludf.DUMMYFUNCTION("""COMPUTED_VALUE"""),3.55453333333333) -> 3.5545333 | L20: Wiris Variasi
A21: =IFERROR(__xludf.DUMMYFUNCTION("""COMPUTED_VALUE"""),174904221976312) -> 174904221976312 | B21: =IFERROR(__xludf.DUMMYFUNCTION("""COMPUTED_VALUE"""),"120226089458750694") -> 120226089458750694 | C21: =IFERROR(__xludf.DUMMYFUNCTION("""COMPUTED_VALUE"""),"Griya rias") -> Griya rias | F21: =IFERROR(__xludf.DUMMYFUNCTION("""COMPUTED_VALUE"""),1521) -> 1521 | G21: =IFERROR(__xludf.DUMMYFUNCTION("""COMPUTED_VALUE"""),22208) -> 22208 | H21: =IFERROR(__xludf.DUMMYFUNCTION("""COMPUTED_VALUE"""),0) -> 0 | I21: =IFERROR(__xludf.DUMMYFUNCTION("""COMPUTED_VALUE"""),38479) -> 38479 | K21: =IFERROR(__xludf.DUMMYFUNCTION("""COMPUTED_VALUE"""),2.56526666666666) -> 2.5652667 | L21: Wiris Variasi
A22: =IFERROR(__xludf.DUMMYFUNCTION("""COMPUTED_VALUE"""),174904221976312) -> 174904221976312 | B22: =IFERROR(__xludf.DUMMYFUNCTION("""COMPUTED_VALUE"""),"120226351656870694") -> 120226351656870694 | C22: =IFERROR(__xludf.DUMMYFUNCTION("""COMPUTED_VALUE"""),"Rodrimar Aifunan Fresku") -> Rodrimar Aifunan Fresku | F22: =IFERROR(__xludf.DUMMYFUNCTION("""COMPUTED_VALUE"""),85250) -> 85250 | G22: =IFERROR(__xludf.DUMMYFUNCTION("""COMPUTED_VALUE"""),2671.94117647058) -> 2671.9412 | H22: =IFERROR(__xludf.DUMMYFUNCTION("""COMPUTED_VALUE"""),42) -> 42 | I22: =IFERROR(__xludf.DUMMYFUNCTION("""COMPUTED_VALUE"""),254178) -> 254178 | J22: =IFERROR(__xludf.DUMMYFUNCTION("""COMPUTED_VALUE"""),6051.85714285714) -> 6051.8571 | K22: =IFERROR(__xludf.DUMMYFUNCTION("""COMPUTED_VALUE"""),16.9452) -> 16.9452 | L22: Wiris Variasi
A23: =IFERROR(__xludf.DUMMYFUNCTION("""COMPUTED_VALUE"""),174904221976312) -> 174904221976312 | B23: =IFERROR(__xludf.DUMMYFUNCTION("""COMPUTED_VALUE"""),"120226351716450694") -> 120226351716450694 | C23: =IFERROR(__xludf.DUMMYFUNCTION("""COMPUTED_VALUE"""),"Toko Emas Sembiring") -> Toko Emas Sembiring | D23: =IFERROR(__xludf.DUMMYFUNCTION("""COMPUTED_VALUE"""),"https://wa.me/6281263113266") -> https://wa.me/6281263113266 | E23: =IFERROR(__xludf.DUMMYFUNCTION("""COMPUTED_VALUE"""),"6281263113266") -> 6281263113266 | F23: =IFERROR(__xludf.DUMMYFUNCTION("""COMPUTED_VALUE"""),9175) -> 9175 | G23: =IFERROR(__xludf.DUMMYFUNCTION("""COMPUTED_VALUE"""),9771.6) -> 9771.6 | H23: =IFERROR(__xludf.DUMMYFUNCTION("""COMPUTED_VALUE"""),29) -> 29 | I23: =IFERROR(__xludf.DUMMYFUNCTION("""COMPUTED_VALUE"""),98054) -> 98054 | J23: =IFERROR(__xludf.DUMMYFUNCTION("""COMPUTED_VALUE"""),3381.1724137931) -> 3381.1724 | K23: =IFERROR(__xludf.DUMMYFUNCTION("""COMPUTED_VALUE"""),6.53693333333333) -> 6.5369333 | L23: Wiris Variasi
A24: =IFERROR(__xludf.DUMMYFUNCTION("""COMPUTED_VALUE"""),174904221976312) -> 174904221976312 | B24: =IFERROR(__xludf.DUMMYFUNCTION("""COMPUTED_VALUE"""),"120226464082810694") -> 120226464082810694 | C24: =IFERROR(__xludf.DUMMYFUNCTION("""COMPUTED_VALUE"""),"Yuzef homestay") -> Yuzef homestay | D24: =IFERROR(__xludf.DUMMYFUNCTION("""COMPUTED_VALUE"""),"https://wa.me/628988759290") -> https://wa.me/628988759290 | E24: =IFERROR(__xludf.DUMMYFUNCTION("""COMPUTED_VALUE"""),"628988759290") -> 628988759290 | F24: =IFERROR(__xludf.DUMMYFUNCTION("""COMPUTED_VALUE"""),14147) -> 14147 | G24: =IFERROR(__xludf.DUMMYFUNCTION("""COMPUTED_VALUE"""),12380) -> 12380 | H24: =IFERROR(__xludf.DUMMYFUNCTION("""COMPUTED_VALUE"""),36) -> 36 | I24: =IFERROR(__xludf.DUMMYFUNCTION("""COMPUTED_VALUE"""),220798) -> 220798 | J24: =IFERROR(__xludf.DUMMYFUNCTION("""COMPUTED_VALUE"""),6133.27777777777) -> 6133.2778 | K24: =IFERROR(__xludf.DUMMYFUNCTION("""COMPUTED_VALUE"""),14.7198666666666) -> 14.719867 | L24: Wiris Variasi
A25: =IFERROR(__xludf.DUMMYFUNCTION("""COMPUTED_VALUE"""),174904221976312) -> 174904221976312 | B25: =IFERROR(__xludf.DUMMYFUNCTION("""COMPUTED_VALUE"""),"120226538247460694") -> 120226538247460694 | C25: =IFERROR(__xludf.DUMMYFUNCTION("""COMPUTED_VALUE"""),"Rosfreb Shop") -> Rosfreb Shop | F25: =IFERROR(__xludf.DUMMYFUNCTION("""COMPUTED_VALUE"""),35697) -> 35697 | G25: =IFERROR(__xludf.DUMMYFUNCTION("""COMPUTED_VALUE"""),3120.1) -> 3120.1 | H25: =IFERROR(__xludf.DUMMYFUNCTION("""COMPUTED_VALUE"""),94) -> 94 | I25: =IFERROR(__xludf.DUMMYFUNCTION("""COMPUTED_VALUE"""),130111) -> 130111 | J25: =IFERROR(__xludf.DUMMYFUNCTION("""COMPUTED_VALUE"""),1384.15957446808) -> 1384.1596 | K25: =IFERROR(__xludf.DUMMYFUNCTION("""COMPUTED_VALUE"""),8.67406666666666) -> 8.6740667 | L25: Wiris Variasi
A26: =IFERROR(__xludf.DUMMYFUNCTION("""COMPUTED_VALUE"""),174904221976312) -> 174904221976312 | B26: =IFERROR(__xludf.DUMMYFUNCTION("""COMPUTED_VALUE"""),"120226539786220694") -> 120226539786220694 | C26: =IFERROR(__xludf.DUMMYFUNCTION("""COMPUTED_VALUE"""),"AFIKA DEKORATION") -> AFIKA DEKORATION | D26: =IFERROR(__xludf.DUMMYFUNCTION("""COMPUTED_VALUE"""),"https://wa.me/6285864008882") -> https://wa.me/6285864008882 | E26: =IFERROR(__xludf.DUMMYFUNCTION("""COMPUTED_VALUE"""),"6285864008882") -> 6285864008882 | F26: =IFERROR(__xludf.DUMMYFUNCTION("""COMPUTED_VALUE"""),4861) -> 4861 | G26: =IFERROR(__xludf.DUMMYFUNCTION("""COMPUTED_VALUE"""),10445.4) -> 10445.4 | H26: =IFERROR(__xludf.DUMMYFUNCTION("""COMPUTED_VALUE"""),3) -> 3 | I26: =IFERROR(__xludf.DUMMYFUNCTION("""COMPUTED_VALUE"""),58674) -> 58674 | J26: =IFERROR(__xludf.DUMMYFUNCTION("""COMPUTED_VALUE"""),19558) -> 19558 | K26: =IFERROR(__xludf.DUMMYFUNCTION("""COMPUTED_VALUE"""),3.9116) -> 3.9116 | L26: Wiris Variasi
A27: =IFERROR(__xludf.DUMMYFUNCTION("""COMPUTED_VALUE"""),174904221976312) -> 174904221976312 | B27: =IFERROR(__xludf.DUMMYFUNCTION("""COMPUTED_VALUE"""),"120226642991680694") -> 120226642991680694 | C27: =IFERROR(__xludf.DUMMYFUNCTION("""COMPUTED_VALUE"""),"Rahma Gallery") -> Rahma Gallery | F27: =IFERROR(__xludf.DUMMYFUNCTION("""COMPUTED_VALUE"""),73177) -> 73177 | G27: =IFERROR(__xludf.DUMMYFUNCTION("""COMPUTED_VALUE"""),1178.14285714285) -> 1178.1429 | H27: =IFERROR(__xludf.DUMMYFUNCTION("""COMPUTED_VALUE"""),0) -> 0 | I27: =IFERROR(__xludf.DUMMYFUNCTION("""COMPUTED_VALUE"""),87817) -> 87817 | K27: =IFERROR(__xludf.DUMMYFUNCTION("""COMPUTED_VALUE"""),5.85446666666666) -> 5.8544667 | L27: Wiris Variasi
A28: =IFERROR(__xludf.DUMMYFUNCTION("""COMPUTED_VALUE"""),174904221976312) -> 174904221976312 | B28: =IFERROR(__xludf.DUMMYFUNCTION("""COMPUTED_VALUE"""),"120226804141930694") -> 120226804141930694 | C28: =IFERROR(__xludf.DUMMYFUNCTION("""COMPUTED_VALUE"""),"Suzuki Mamuju") -> Suzuki Mamuju | D28: =IFERROR(__xludf.DUMMYFUNCTION("""COMPUTED_VALUE"""),"https://wa.me/6281221788919") -> https://wa.me/6281221788919 | E28: =IFERROR(__xludf.DUMMYFUNCTION("""COMPUTED_VALUE"""),"6281221788919") -> 6281221788919 | F28: =IFERROR(__xludf.DUMMYFUNCTION("""COMPUTED_VALUE"""),17338) -> 17338 | G28: =IFERROR(__xludf.DUMMYFUNCTION("""COMPUTED_VALUE"""),12503.9) -> 12503.9 | H28: =IFERROR(__xludf.DUMMYFUNCTION("""COMPUTED_VALUE"""),25) -> 25 | I28: =IFERROR(__xludf.DUMMYFUNCTION("""COMPUTED_VALUE"""),253194) -> 253194 | J28: =IFERROR(__xludf.DUMMYFUNCTION("""COMPUTED_VALUE"""),10127.76) -> 10127.76 | K28: =IFERROR(__xludf.DUMMYFUNCTION("""COMPUTED_VALUE"""),16.8796) -> 16.8796 | L28: Wiris Variasi
A29: =IFERROR(__xludf.DUMMYFUNCTION("""COMPUTED_VALUE"""),174904221976312) -> 174904221976312 | B29: =IFERROR(__xludf.DUMMYFUNCTION("""COMPUTED_VALUE"""),"120226887056380694") -> 120226887056380694 | C29: =IFERROR(__xludf.DUMMYFUNCTION("""COMPUTED_VALUE"""),"SMK CENDEKIA") -> SMK CENDEKIA | D29: =IFERROR(__xludf.DUMMYFUNCTION("""COMPUTED_VALUE"""),"https://wa.me/6282129040031") -> https://wa.me/6282129040031 | E29: =IFERROR(__xludf.DUMMYFUNCTION("""COMPUTED_VALUE"""),"6282129040031") -> 6282129040031 | F29: =IFERROR(__xludf.DUMMYFUNCTION("""COMPUTED_VALUE"""),4631) -> 4631 | G29: =IFERROR(__xludf.DUMMYFUNCTION("""COMPUTED_VALUE"""),10330.75) -> 10330.75 | H29: =IFERROR(__xludf.DUMMYFUNCTION("""COMPUTED_VALUE"""),6) -> 6 | I29: =IFERROR(__xludf.DUMMYFUNCTION("""COMPUTED_VALUE"""),55015) -> 55015 | J29: =IFERROR(__xludf.DUMMYFUNCTION("""COMPUTED_VALUE"""),9169.16666666666) -> 9169.1667 | K29: =IFERROR(__xludf.DUMMYFUNCTION("""COMPUTED_VALUE"""),3.66766666666666) -> 3.6676667 | L29: Wiris Variasi
A30: =IFERROR(__xludf.DUMMYFUNCTION("""COMPUTED_VALUE"""),174904221976312) -> 174904221976312 | B30: =IFERROR(__xludf.DUMMYFUNCTION("""COMPUTED_VALUE"""),"120226909635070694") -> 120226909635070694 | C30: =IFERROR(__xludf.DUMMYFUNCTION("""COMPUTED_VALUE"""),"Griya Terapi") -> Griya Terapi | D30: =IFERROR(__xludf.DUMMYFUNCTION("""COMPUTED_VALUE"""),"https://wa.me/6281904501876") -> https://wa.me/6281904501876 | E30: =IFERROR(__xludf.DUMMYFUNCTION("""COMPUTED_VALUE"""),"6281904501876") -> 6281904501876 | F30: =IFERROR(__xludf.DUMMYFUNCTION("""COMPUTED_VALUE"""),4962) -> 4962 | G30: =IFERROR(__xludf.DUMMYFUNCTION("""COMPUTED_VALUE"""),9821) -> 9821 | H30: =IFERROR(__xludf.DUMMYFUNCTION("""COMPUTED_VALUE"""),20) -> 20 | I30: =IFERROR(__xludf.DUMMYFUNCTION("""COMPUTED_VALUE"""),56078) -> 56078 | J30: =IFERROR(__xludf.DUMMYFUNCTION("""COMPUTED_VALUE"""),2803.9) -> 2803.9 | K30: =IFERROR(__xludf.DUMMYFUNCTION("""COMPUTED_VALUE"""),3.73853333333333) -> 3.7385333 | L30: Wiris Variasi
